Workbook
Name SegmentaciónDeDatos_Mes1: #N/A
Name SegmentaciónDeDatos_Mes21: #N/A
Name SegmentaciónDeDatos_Mes3: #N/A
Name SegmentaciónDeDatos_Mes41: #N/A
Name SegmentaciónDeDatos_Semana1: #N/A
Name SegmentaciónDeDatos_Semana21: #N/A
Name SegmentaciónDeDatos_Semana3: #N/A
Name SegmentaciónDeDatos_Semana41: #N/A

Sheet Catalogo
A1: Descripción SKU | B1: Producto | C1: Empresa | E1: SKU | F1: Descripción SKU | G1: Producto | H1: Empresa
A2: "[79669] FLOW SWITCH 24VAC/DC,SS 1/2""NPT (SC050R)" | B2: [79669] FLOW SWITCH 24VAC/DC,SS 1/2" | C2: Supra System | E2: LD018-4 | F2: [LD018-4] ADBS (TAMBOR PLASTICO 220 KG INC) | G2: ADBS | H2: Liderza
A3: "[LD117] TRICLORO TABLETA 3"" CUÑETE 50 KG" | B3: TRICLORO TABLETA 3" | C3: Liderza | E3: LD002-2 | F3: [LD002-2] ACEITE DE PINO L (TAMBOR LAMINA 200 L INC) | G3: ACEITE DE PINO | H3: Liderza
A4: "[SS008] TRICLORO TABLETA 3"" CUÑETE 50 KG" | B4: TRICLORO TABLETA 3" | C4: Supra System | E4: LD023-4 | F4: [LD023-4] ALCOHOL TRIDECILICO 8 MOLES (TAMBOR PLASTICO 200 KG INC) | G4: ALCOHOL TRIDECILICO 8 MOLES | H4: Liderza
A5: [73250] PULSAR PRECISION | B5: [73250] PULSAR PRECISION | C5: Supra System | E5: LD001-4 | F5: ACEITE DE PINO KG | G5: ACEITE DE PINO | H5: Liderza
A6: [73350] PULSAR ACID PLUS FEEDER (pH) | B6: [73350] PULSAR ACID PLUS FEEDER (pH) | C6: Supra System | E6: LD008-3 | F6: ACIDO ACETICO GLACIAL ALIMENTICIO | G6: ACIDO ACETICO GLACIAL ALIMENTICIO | H6: Liderza
A7: [73371] PULSAR PRECISION 30 (with install kit) | B7: [73371] PULSAR PRECISION 30 (with install kit) | C7: Supra System | E7: LD012 | F7: ACIDO CITRICO WEIFANG SACO 25 KG | G7: ACIDO CITRICO WEIFANG | H7: Liderza
A8: [73379] PULSAR PRECISION 30 (mini) | B8: [73379] PULSAR PRECISION 30 (mini) | C8: Supra System | E8: LD016-1 | F8: ACIDO FOSFORICO CLARIFICADO 85% | G8: ACIDO FOSFORICO CLARIFICADO 85% | H8: Liderza
A9: [73389] HCE 30 - ORP KIT | B9: [73389] HCE 30 - ORP KIT | C9: Supra System | E9: LD016-9 | F9: ACIDO FOSFORICO CLARIFICADO 85% | G9: ACIDO FOSFORICO CLARIFICADO 85% | H9: Liderza
A10: [73433] PULSAR CONTROLLER M720 | B10: [73433] PULSAR CONTROLLER M720 | C10: Supra System | E10: LD020-3 | F10: ALCOHOL ETILICO | G10: ALCOHOL ETILICO | H10: Liderza
A11: [73434] PH SENSOR (SXPH) | B11: [73434] PH SENSOR | C11: Supra System | E11: LD028-2 | F11: AROMINA 150 | G11: AROMINA 150 | H11: Liderza
A12: [73435] ORP SENSOR (SXORP) | B12: [73435] ORP SENSOR | C12: Supra System | E12: LD030-1 | F12: BICARBONATO DE SODIO USP | G12: BICARBONATO DE SODIO USP | H12: Liderza
... A236: METANOL | B236: METANOL | C236: Liderza | E236: LD139 | F236: [LD139] HIPOCLORITO DE CALCIO TABLETA 2&5/8 CCH SKU 23220E CUNETE 22.7 KG | G236: HIPOCLORITO DE CALCIO TABLETA CCH | H236: Liderza
A237: METASILICATO DE SODIO PENTASIL SACO 25 KG | B237: METASILICATO DE SODIO PENTASIL | C237: Liderza
A238: MONOETANOLAMINA | B238: MONOETANOLAMINA | C238: Liderza
A239: MONOPROPILENGLICOL USP | B239: MONOPROPILENGLICOL USP | C239: Liderza
A240: NONIL FENOL 10 MOLES | B240: NONIL FENOL 10 MOLES | C240: Liderza
A241: PERCARBONATO DE SODIO PROVOX SACO 25 KG | B241: PERCARBONATO DE SODIO PROVOX | C241: Liderza
A242: PEROXIDO DE HIDROGENO 35% FG | B242: PEROXIDO DE HIDROGENO 35% FG | C242: Liderza
A243: PEROXIDO DE HIDROGENO 50% STD | B243: PEROXIDO DE HIDROGENO 50% STD | C243: Liderza
A244: PIGMENTO AMARILLO IOX Y 02 SACO 20 KG | B244: PIGMENTO AMARILLO | C244: Liderza
A245: PIGMENTO ROJO IOX R 02 SACO 25 KG | B245: PIGMENTO ROJO | C245: Liderza
A246: PISTON PARA AQT-275 Y AQT-290 HWBP | B246: PISTON PARA AQT-275 Y 290 | C246: Liderza
A247: POTASA CAUSTICA EN ESCAMA CHINA SACO 25 KG | B247: POTASA CAUSTICA EN ESCAMA CHINA | C247: Liderza
A248: POTASA CAUSTICA EN ESCAMA ROT SACO 25 KG | B248: POTASA CAUSTICA EN ESCAMA ROT | C248: Liderza
... A328: [LD097-3] PROTEINA VEGETAL PVH 11307 (SACO 22.68 KG) | B328: PROTEINA VEGETAL PVH 11307 | C328: Liderza

Sheet BD Ventas
A1: Asiento contable/Número | B1: Asiento contable/Nombre del partner para mostrar en la factura. | C1: Asiento contable/Fecha de factura | D1: Asiento contable/Partner/Términos de pago del cliente | E1: Asiento contable/Fecha de vencimiento | F1: Líneas de la orden de venta/Vendedor | G1: Líneas de la orden de venta/Producto | H1: Líneas de la orden de venta/Unidad de medida | I1: Líneas de la orden de venta/Cantidad facturada | J1: Líneas de la orden de venta/Costo | K1: Líneas de la orden de venta/Precio unitario | L1: Líneas de la orden de venta/Margen | M1: Líneas de la orden de venta/Margen (%) | N1: Líneas de la orden de venta/Divisa | O1: Crédito | P1: Mes | Q1: Semana | R1: Producto 2 | S1: Ut Bruta MN | T1: Costo Venta MN | U1: TC
A2: HMO/2026/00454 | B2: "PUBLICO EN GENERAL" | C2: 46199 | D2: Pago inmediato | E2: 46199 | F2: ILSE GARCÍA | G2: [LD052-2] ESTIREN ACRILICA (TAMBOR LAMINA 180 KG INC) | H2: KG | I2: 1800 | J2: 31.879394 | K2: 39 | L2: 12817.091 | M2: 0.18257964 | N2: MXN | O2: 70200 | P2: =MONTH(C2) -> 6 | Q2: =WEEKNUM(C2) -> 26 | R2: =VLOOKUP(G2,Catalogo!A:B,2,0) -> ESTIREN ACRILICA | S2: =(K2-J2)*I2*U2 -> 12817.091 | T2: =O2-S2 -> 57382.909 | U2: =IF(N2="USD",(O2/I2/K2),1) -> 1
A3: HMO/2026/00453 | B3: "PUBLICO EN GENERAL" | C3: 46199 | D3: Pago inmediato | E3: 46199 | F3: ILSE GARCÍA | G3: [LD052-2] ESTIREN ACRILICA (TAMBOR LAMINA 180 KG INC) | H3: KG | I3: 1800 | J3: 31.879394 | K3: 39 | L3: 12817.091 | M3: 0.18257964 | N3: MXN | O3: 70200 | P3: =MONTH(C3) -> 6 | Q3: =WEEKNUM(C3) -> 26 | R3: =VLOOKUP(G3,Catalogo!A:B,2,0) -> ESTIREN ACRILICA | S3: =(K3-J3)*I3*U3 -> 12817.091 | T3: =O3-S3 -> 57382.909 | U3: =IF(N3="USD",(O3/I3/K3),1) -> 1
A4: HMO/2026/00452 | B4: "PUBLICO EN GENERAL" | C4: 46199 | D4: Pago inmediato | E4: 46199 | F4: ILSE GARCÍA | G4: [LD052-2] ESTIREN ACRILICA (TAMBOR LAMINA 180 KG INC) | H4: KG | I4: 900 | J4: 31.879389 | K4: 39 | L4: 6408.5499 | M4: 0.18257977 | N4: MXN | O4: 35100 | P4: =MONTH(C4) -> 6 | Q4: =WEEKNUM(C4) -> 26 | R4: =VLOOKUP(G4,Catalogo!A:B,2,0) -> ESTIREN ACRILICA | S4: =(K4-J4)*I4*U4 -> 6408.5499 | T4: =O4-S4 -> 28691.45 | U4: =IF(N4="USD",(O4/I4/K4),1) -> 1
A5: HMO/2026/00451 | B5: "PUBLICO EN GENERAL" | C5: 46199 | D5: Pago inmediato | E5: 46199 | F5: ILSE GARCÍA | G5: [LD022] ALCOHOL POLIVINILICO PVOH 08850 SACO 20 KG | H5: KG | I5: 1000 | J5: 47.37745 | K5: 58 | L5: 10622.55 | M5: 0.18314741 | N5: MXN | O5: 58000 | P5: =MONTH(C5) -> 6 | Q5: =WEEKNUM(C5) -> 26 | R5: =VLOOKUP(G5,Catalogo!A:B,2,0) -> ALCOHOL POLIVINILICO PVOH 08850 | S5: =(K5-J5)*I5*U5 -> 10622.55 | T5: =O5-S5 -> 47377.45 | U5: =IF(N5="USD",(O5/I5/K5),1) -> 1
A6: HMO/2026/00450 | B6: ACUAGRO | C6: 46199 | D6: Pago inmediato | E6: 46199 | F6: ILSE GARCÍA | G6: [LD008-3] ACIDO ACETICO GLACIAL ALIMENTICIO (PORRON NATURAL 50 KG INC) | H6: KG | I6: 200 | J6: 32.5 | K6: 43 | L6: 2100 | M6: 0.24418605 | N6: MXN | O6: 8600 | P6: =MONTH(C6) -> 6 | Q6: =WEEKNUM(C6) -> 26 | R6: =VLOOKUP(G6,Catalogo!A:B,2,0) -> ACIDO ACETICO GLACIAL ALIMENTICIO | S6: =(K6-J6)*I6*U6 -> 2100 | T6: =O6-S6 -> 6500 | U6: =IF(N6="USD",(O6/I6/K6),1) -> 1
A7: HMO/2026/00449 | B7: ACUAGRO | C7: 46199 | D7: Pago inmediato | E7: 46199 | F7: ILSE GARCÍA | G7: [LD012] ACIDO CITRICO WEIFANG SACO 25 KG | H7: KG | I7: 500 | J7: 22.43328 | K7: 33 | L7: 5283.36 | M7: 0.32020364 | N7: MXN | O7: 16500 | P7: =MONTH(C7) -> 6 | Q7: =WEEKNUM(C7) -> 26 | R7: =VLOOKUP(G7,Catalogo!A:B,2,0) -> ACIDO CITRICO WEIFANG | S7: =(K7-J7)*I7*U7 -> 5283.36 | T7: =O7-S7 -> 11216.64 | U7: =IF(N7="USD",(O7/I7/K7),1) -> 1
A8: HMO/2026/00448 | B8: ACUAGRO | C8: 46199 | D8: Pago inmediato | E8: 46199 | F8: ILSE GARCÍA | G8: [LD016-12] ACIDO FOSFORICO CLARIFICADO 85% (TOTE 1575 KG INC) | H8: KG | I8: 3150 | J8: 29.897692 | K8: 36.69 | L8: 21395.77 | M8: 0.18512696 | N8: MXN | O8: 115573.5 | P8: =MONTH(C8) -> 6 | Q8: =WEEKNUM(C8) -> 26 | R8: =VLOOKUP(G8,Catalogo!A:B,2,0) -> ACIDO FOSFORICO CLARIFICADO 85% | S8: =(K8-J8)*I8*U8 -> 21395.77 | T8: =O8-S8 -> 94177.73 | U8: =IF(N8="USD",(O8/I8/K8),1) -> 1
A9: HMO/2026/00448 | B9: ACUAGRO | C9: 46199 | D9: Pago inmediato | E9: 46199 | F9: ILSE GARCÍA | G9: [LD014-4] ACIDO FOSFORICO 52% VERDE (TOTE 1680 KG A/C) | H9: KG | I9: 5040 | J9: 21.0312 | K9: 23.51 | L9: 12493.152 | M9: 0.10543598 | N9: MXN | O9: 118490.4 | P9: =MONTH(C9) -> 6 | Q9: =WEEKNUM(C9) -> 26 | R9: =VLOOKUP(G9,Catalogo!A:B,2,0) -> ACIDO FOSFORICO 52% VERDE | S9: =(K9-J9)*I9*U9 -> 12493.152 | T9: =O9-S9 -> 105997.25 | U9: =IF(N9="USD",(O9/I9/K9),1) -> 1
A10: CLN/2026/00163 | B10: GRUBOSA COMERCIAL | C10: 46199 | D10: 30 Días | E10: 46229 | F10: MATEO LÓPEZ | G10: [LD073-2] LESS 70% (TAMBOR PLASTICO 170 KG INC) | H10: KG | I10: 170 | J10: 38.361235 | K10: 48 | L10: 1638.5901 | M10: 0.2008076 | N10: MXN | O10: 8160 | P10: =MONTH(C10) -> 6 | Q10: =WEEKNUM(C10) -> 26 | R10: =VLOOKUP(G10,Catalogo!A:B,2,0) -> LESS 70% | S10: =(K10-J10)*I10*U10 -> 1638.59 | T10: =O10-S10 -> 6521.41 | U10: =IF(N10="USD",(O10/I10/K10),1) -> 1
A11: HMO/2026/00447 | B11: SAUL AYON REYNA | C11: 46198 | D11: 30 Días | E11: 46198 | F11: ILSE GARCÍA | G11: [LD052-2] ESTIREN ACRILICA (TAMBOR LAMINA 180 KG INC) | H11: KG | I11: 1800 | J11: 31.879394 | K11: 39 | L11: 12817.091 | M11: 0.18257964 | N11: MXN | O11: 70200 | P11: =MONTH(C11) -> 6 | Q11: =WEEKNUM(C11) -> 26 | R11: =VLOOKUP(G11,Catalogo!A:B,2,0) -> ESTIREN ACRILICA | S11: =(K11-J11)*I11*U11 -> 12817.091 | T11: =O11-S11 -> 57382.909 | U11: =IF(N11="USD",(O11/I11/K11),1) -> 1
A12: HMO/2026/00446 | B12: JESUS ALFREDO AYON REYNA | C12: 46198 | D12: 30 Días | E12: 46228 | F12: ILSE GARCÍA | G12: [LD052-2] ESTIREN ACRILICA (TAMBOR LAMINA 180 KG INC) | H12: KG | I12: 1440 | J12: 31.879389 | K12: 42 | L12: 14573.68 | M12: 0.24096693 | N12: MXN | O12: 60480 | P12: =MONTH(C12) -> 6 | Q12: =WEEKNUM(C12) -> 26 | R12: =VLOOKUP(G12,Catalogo!A:B,2,0) -> ESTIREN ACRILICA | S12: =(K12-J12)*I12*U12 -> 14573.68 | T12: =O12-S12 -> 45906.32 | U12: =IF(N12="USD",(O12/I12/K12),1) -> 1
A13: HMO/2026/00444 | B13: JESUS FRANCISCO OLMOS CASTRO | C13: 46198 | D13: 30 Días | E13: 46228 | F13: FREDY SALAS | G13: [LD065] HIPOCLORITO DE CALCIO GRANULAR HTH SKU 30034 CUÑETE 45 KG | H13: KG | I13: 135 | J13: 61.976444 | K13: 88.1 | L13: 3526.6801 | M13: 0.29652163 | N13: MXN | O13: 11893.5 | P13: =MONTH(C13) -> 6 | Q13: =WEEKNUM(C13) -> 26 | R13: =VLOOKUP(G13,Catalogo!A:B,2,0) -> HIPOCLORITO DE CALCIO GRANULAR HTH | S13: =(K13-J13)*I13*U13 -> 3526.6801 | T13: =O13-S13 -> 8366.8199 | U13: =IF(N13="USD",(O13/I13/K13),1) -> 1
... A53: CLN/2026/00155 | B53: AGRONATURART BIO TECH | C53: 46188 | D53: 30 Días | E53: 46218 | F53: ILSE GARCÍA | G53: [LD012] ACIDO CITRICO WEIFANG SACO 25 KG | H53: KG | I53: 200 | J53: 24.3366 | K53: 36 | L53: 2332.68 | M53: 0.32398333 | N53: MXN | O53: 7200 | P53: =MONTH(C53) -> 6 | Q53: =WEEKNUM(C53) -> 25 | R53: =VLOOKUP(G53,Catalogo!A:B,2,0) -> ACIDO CITRICO WEIFANG | S53: =(K53-J53)*I53*U53 -> 2332.68 | T53: =O53-S53 -> 4867.32 | U53: =IF(N53="USD",(O53/I53/K53),1) -> 1
A54: CLN/2026/00154 | B54: OSWALDO GARCIA MARTINEZ | C54: 46188 | E54: 46188 | F54: MATEO LÓPEZ | G54: [LD065] HIPOCLORITO DE CALCIO GRANULAR HTH SKU 30034 CUÑETE 45 KG | H54: KG | I54: 225 | J54: 61.976444 | K54: 83.5 | L54: 4842.8001 | M54: 0.25776714 | N54: MXN | O54: 18787.5 | P54: =MONTH(C54) -> 6 | Q54: =WEEKNUM(C54) -> 25 | R54: =VLOOKUP(G54,Catalogo!A:B,2,0) -> HIPOCLORITO DE CALCIO GRANULAR HTH | S54: =(K54-J54)*I54*U54 -> 4842.8001 | T54: =O54-S54 -> 13944.7 | U54: =IF(N54="USD",(O54/I54/K54),1) -> 1
A55: HMO/2026/00409 | B55: AQUASTORE SUMINISTROS ACUICOLAS DEL PACIFICO | C55: 46186 | D55: 30 Días | E55: 46216 | F55: MATEO LÓPEZ | G55: [LD065] HIPOCLORITO DE CALCIO GRANULAR HTH SKU 30034 CUÑETE 45 KG | H55: KG | I55: 135 | J55: 3.565286 | K55: 5 | L55: 193.68639 | M55: 0.2869428 | N55: USD | O55: 11733.73 | P55: =MONTH(C55) -> 6 | Q55: =WEEKNUM(C55) -> 24 | R55: =VLOOKUP(G55,Catalogo!A:B,2,0) -> HIPOCLORITO DE CALCIO GRANULAR HTH | S55: =(K55-J55)*I55*U55 -> 3366.9093 | T55: =O55-S55 -> 8366.8207 | U55: =IF(N55="USD",(O55/I55/K55),1) -> 17.383304
A56: HMO/2026/00408 | B56: KESECOME ALIMENTARIA | C56: 46186 | D56: 30 Días | E56: 46216 | F56: FREDY SALAS | G56: [LD008-2] ACIDO ACETICO GLACIAL ALIMENTICIO (PORRON NATURAL 20 KG INC) | H56: KG | I56: 220 | J56: 26.250773 | K56: 43 | L56: 3684.8299 | M56: 0.38951691 | N56: MXN | O56: 9460 | P56: =MONTH(C56) -> 6 | Q56: =WEEKNUM(C56) -> 24 | R56: =VLOOKUP(G56,Catalogo!A:B,2,0) -> ACIDO ACETICO GLACIAL ALIMENTICIO | S56: =(K56-J56)*I56*U56 -> 3684.8299 | T56: =O56-S56 -> 5775.1701 | U56: =IF(N56="USD",(O56/I56/K56),1) -> 1
A57: HMO/2026/00407 | B57: AQUASTORE SUMINISTROS ACUICOLAS DEL PACIFICO | C57: 46186 | D57: 30 Días | E57: 46216 | F57: MATEO LÓPEZ | G57: [LD065] HIPOCLORITO DE CALCIO GRANULAR HTH SKU 30034 CUÑETE 45 KG | H57: KG | I57: 225 | J57: 3.558822 | K57: 5 | L57: 324.26505 | M57: 0.2882356 | N57: USD | O57: 19556.21 | P57: =MONTH(C57) -> 6 | Q57: =WEEKNUM(C57) -> 24 | R57: =VLOOKUP(G57,Catalogo!A:B,2,0) -> HIPOCLORITO DE CALCIO GRANULAR HTH | S57: =(K57-J57)*I57*U57 -> 5636.7959 | T57: =O57-S57 -> 13919.414 | U57: =IF(N57="USD",(O57/I57/K57),1) -> 17.383298
A58: CLN/2026/00153 | B58: INDUSTRIAL AGROBIOLOGICOS DEL NOROESTE | C58: 46186 | D58: 30 Días | E58: 46216 | F58: ILSE GARCÍA | G58: [LD083-6] NONIL FENOL 10 MOLES (TAMBOR PLASTICO 220 KG INC) | H58: KG | I58: 220 | J58: 52.717 | K58: 62 | L58: 2042.26 | M58: 0.14972581 | N58: MXN | O58: 13640 | P58: =MONTH(C58) -> 6 | Q58: =WEEKNUM(C58) -> 24 | R58: =VLOOKUP(G58,Catalogo!A:B,2,0) -> NONIL FENOL 10 MOLES | S58: =(K58-J58)*I58*U58 -> 2042.26 | T58: =O58-S58 -> 11597.74 | U58: =IF(N58="USD",(O58/I58/K58),1) -> 1
A59: HMO/2026/00406 | B59: "PUBLICO EN GENERAL" | C59: 46185 | D59: Pago inmediato | E59: 46185 | F59: ILSE GARCÍA | G59: [LD052-2] ESTIREN ACRILICA (TAMBOR LAMINA 180 KG INC) | H59: KG | I59: 1800 | J59: 31.486083 | K59: 39 | L59: 13525.051 | M59: 0.19266454 | N59: MXN | O59: 70200 | P59: =MONTH(C59) -> 6 | Q59: =WEEKNUM(C59) -> 24 | R59: =VLOOKUP(G59,Catalogo!A:B,2,0) -> ESTIREN ACRILICA | S59: =(K59-J59)*I59*U59 -> 13525.051 | T59: =O59-S59 -> 56674.949 | U59: =IF(N59="USD",(O59/I59/K59),1) -> 1
A60: HMO/2026/00405 | B60: GRUPO OMC DEL NOROESTE | C60: 46185 | D60: 15 Días | E60: 46215 | F60: FREDY SALAS | G60: [LD065] HIPOCLORITO DE CALCIO GRANULAR HTH SKU 30034 CUÑETE 45 KG | H60: KG | I60: 270 | J60: 3.565286 | K60: 4.6 | L60: 279.37278 | M60: 0.22493783 | N60: USD | O60: 21590.06 | P60: =MONTH(C60) -> 6 | Q60: =WEEKNUM(C60) -> 24 | R60: =VLOOKUP(G60,Catalogo!A:B,2,0) -> HIPOCLORITO DE CALCIO GRANULAR HTH | S60: =(K60-J60)*I60*U60 -> 4856.4212 | T60: =O60-S60 -> 16733.639 | U60: =IF(N60="USD",(O60/I60/K60),1) -> 17.383301
A61: HMO/2026/00404 | B61: JESUS ALFREDO AYON REYNA | C61: 46185 | D61: 30 Días | E61: 46215 | F61: ILSE GARCÍA | G61: [LD022] ALCOHOL POLIVINILICO PVOH 08850 SACO 20 KG | H61: KG | I61: 1000 | J61: 47.10633 | K61: 58 | L61: 10893.67 | M61: 0.1878219 | N61: MXN | O61: 58000 | P61: =MONTH(C61) -> 6 | Q61: =WEEKNUM(C61) -> 24 | R61: =VLOOKUP(G61,Catalogo!A:B,2,0) -> ALCOHOL POLIVINILICO PVOH 08850 | S61: =(K61-J61)*I61*U61 -> 10893.67 | T61: =O61-S61 -> 47106.33 | U61: =IF(N61="USD",(O61/I61/K61),1) -> 1
A62: HMO/2026/00403 | B62: JESUS ALFREDO AYON REYNA | C62: 46185 | D62: 30 Días | E62: 46215 | F62: ILSE GARCÍA | G62: [LD022] ALCOHOL POLIVINILICO PVOH 08850 SACO 20 KG | H62: KG | I62: 1000 | J62: 47.10633 | K62: 58 | L62: 10893.67 | M62: 0.1878219 | N62: MXN | O62: 58000 | P62: =MONTH(C62) -> 6 | Q62: =WEEKNUM(C62) -> 24 | R62: =VLOOKUP(G62,Catalogo!A:B,2,0) -> ALCOHOL POLIVINILICO PVOH 08850 | S62: =(K62-J62)*I62*U62 -> 10893.67 | T62: =O62-S62 -> 47106.33 | U62: =IF(N62="USD",(O62/I62/K62),1) -> 1
A63: HMO/2026/00402 | B63: JESUS ALFREDO AYON REYNA | C63: 46185 | D63: 30 Días | E63: 46215 | F63: ILSE GARCÍA | G63: [LD022] ALCOHOL POLIVINILICO PVOH 08850 SACO 20 KG | H63: KG | I63: 1000 | J63: 47.10633 | K63: 58 | L63: 10893.67 | M63: 0.1878219 | N63: MXN | O63: 58000 | P63: =MONTH(C63) -> 6 | Q63: =WEEKNUM(C63) -> 24 | R63: =VLOOKUP(G63,Catalogo!A:B,2,0) -> ALCOHOL POLIVINILICO PVOH 08850 | S63: =(K63-J63)*I63*U63 -> 10893.67 | T63: =O63-S63 -> 47106.33 | U63: =IF(N63="USD",(O63/I63/K63),1) -> 1
A64: HMO/2026/00401 | B64: JOCLA PRODUCTOS DE LIMPIEZA | C64: 46185 | D64: Pago inmediato | E64: 46185 | F64: MATEO LÓPEZ | G64: [LD073-2] LESS 70% (TAMBOR PLASTICO 170 KG INC) | H64: KG | I64: 340 | J64: 38.099412 | K64: 46.5 | L64: 2856.1999 | M64: 0.18065781 | N64: MXN | O64: 15810 | P64: =MONTH(C64) -> 6 | Q64: =WEEKNUM(C64) -> 24 | R64: =VLOOKUP(G64,Catalogo!A:B,2,0) -> LESS 70% | S64: =(K64-J64)*I64*U64 -> 2856.1999 | T64: =O64-S64 -> 12953.8 | U64: =IF(N64="USD",(O64/I64/K64),1) -> 1
A65: HMO/2026/00400 | B65: "PUBLICO EN GENERAL" | C65: 46185 | D65: Pago inmediato | E65: 46185 | F65: ILSE GARCÍA | G65: [LD052-2] ESTIREN ACRILICA (TAMBOR LAMINA 180 KG INC) | H65: KG | I65: 2160 | J65: 31.486083 | K65: 39 | L65: 16230.061 | M65: 0.19266454 | N65: MXN | O65: 84240 | P65: =MONTH(C65) -> 6 | Q65: =WEEKNUM(C65) -> 24 | R65: =VLOOKUP(G65,Catalogo!A:B,2,0) -> ESTIREN ACRILICA | S65: =(K65-J65)*I65*U65 -> 16230.061 | T65: =O65-S65 -> 68009.939 | U65: =IF(N65="USD",(O65/I65/K65),1) -> 1
A66: HMO/2026/00399 | B66: ADQUISICIONES PADRE KINO | C66: 46185 | D66: Pago inmediato | E66: 46185 | F66: ILSE GARCÍA | G66: [LD094] POTASA CAUSTICA EN ESCAMA CHINA SACO 25 KG | H66: KG | I66: 2000 | J66: 2.315533 | K66: 2.85 | L66: 1068.934 | M66: 0.18753228 | N66: USD | O66: 99084.81 | P66: =MONTH(C66) -> 6 | Q66: =WEEKNUM(C66) -> 24 | R66: =VLOOKUP(G66,Catalogo!A:B,2,0) -> POTASA CAUSTICA EN ESCAMA CHINA | S66: =(K66-J66)*I66*U66 -> 18581.6 | T66: =O66-S66 -> 80503.21 | U66: =IF(N66="USD",(O66/I66/K66),1) -> 17.3833
... A146: HMO/2026/00336 | B146: JUAN HERMENEGILDO OLIVAS MENDOZA | C146: 46160 | D146: Pago inmediato | E146: 46160 | F146: ILSE GARCÍA | G146: [LD052-2] ESTIREN ACRILICA (TAMBOR LAMINA 180 KG INC) | H146: KG | I146: 360 | J146: 33.561472 | K146: 45 | L146: 4117.8701 | M146: 0.25418951 | N146: MXN | O146: 16200 | P146: =MONTH(C146) -> 5 | Q146: =WEEKNUM(C146) -> 21 | R146: =VLOOKUP(G146,Catalogo!A:B,2,0) -> ESTIREN ACRILICA | S146: =(K146-J146)*I146*U146 -> 4117.8701 | T146: =O146-S146 -> 12082.13 | U146: =IF(N146="USD",(O146/I146/K146),1) -> 1
A147: CLN/2026/00129 | B147: ANTONIO ROMAN PEÑA | C147: 46160 | D147: 30 Días | E147: 46190 | F147: ILSE GARCÍA | G147: [LD065] HIPOCLORITO DE CALCIO GRANULAR HTH SKU 30034 CUÑETE 45 KG | H147: KG | I147: 810 | J147: 3.568835 | K147: 4.92 | L147: 18986.079 | M147: 0.27 | N147: USD | O147: 69134.05 | P147: =MONTH(C147) -> 5 | Q147: =WEEKNUM(C147) -> 21 | R147: =VLOOKUP(G147,Catalogo!A:B,2,0) -> HIPOCLORITO DE CALCIO GRANULAR HTH | S147: 13650.84 | T147: =O147-S147 -> 55483.21 | U147: =IF(N147="USD",(O147/I147/K147),1) -> 17.347699
A148: CLN/2026/00128 | B148: JESUS FRANCISCO OLMOS CASTRO | C148: 46160 | D148: 30 Días | E148: 46190 | F148: FREDY SALAS | G148: [LD065] HIPOCLORITO DE CALCIO GRANULAR HTH SKU 30034 CUÑETE 45 KG | H148: KG | I148: 180 | J148: 68.497778 | K148: 87 | L148: 3330.4 | M148: 0.21266922 | N148: MXN | O148: 15660 | P148: =MONTH(C148) -> 5 | Q148: =WEEKNUM(C148) -> 21 | R148: =VLOOKUP(G148,Catalogo!A:B,2,0) -> HIPOCLORITO DE CALCIO GRANULAR HTH | S148: =(K148-J148)*I148*U148 -> 3330.4 | T148: =O148-S148 -> 12329.6 | U148: =IF(N148="USD",(O148/I148/K148),1) -> 1
A149: HMO/2026/00335 | B149: SAUL AYON REYNA | C149: 46158 | D149: 30 Días | E149: 46188 | F149: ILSE GARCÍA | G149: [LD022] ALCOHOL POLIVINILICO PVOH 08850 SACO 20 KG | H149: KG | I149: 500 | J149: 47.80788 | K149: 58 | L149: 5096.06 | M149: 0.17572621 | N149: MXN | O149: 29000 | P149: =MONTH(C149) -> 5 | Q149: =WEEKNUM(C149) -> 20 | R149: =VLOOKUP(G149,Catalogo!A:B,2,0) -> ALCOHOL POLIVINILICO PVOH 08850 | S149: =(K149-J149)*I149*U149 -> 5096.06 | T149: =O149-S149 -> 23903.94 | U149: =IF(N149="USD",(O149/I149/K149),1) -> 1
A150: CLN/2026/00127 | B150: SERVICIOS Y SOLUCIONES ACUICOLAS | C150: 46158 | D150: 30 Días | E150: 46188 | F150: FREDY SALAS | G150: [LD113] TIOSULFATO DE SODIO SACO 25 KG | H150: KG | I150: 100 | J150: 29.7278 | K150: 39 | L150: 927.22 | M150: 0.23774872 | N150: MXN | O150: 3900 | P150: =MONTH(C150) -> 5 | Q150: =WEEKNUM(C150) -> 20 | R150: =VLOOKUP(G150,Catalogo!A:B,2,0) -> TIOSULFATO DE SODIO | S150: =(K150-J150)*I150*U150 -> 927.22 | T150: =O150-S150 -> 2972.78 | U150: =IF(N150="USD",(O150/I150/K150),1) -> 1
A151: HMO/2026/00334 | B151: SAUL AYON REYNA | C151: 46157 | D151: 30 Días | E151: 46187 | F151: ILSE GARCÍA | G151: [LD052-2] ESTIREN ACRILICA (TAMBOR LAMINA 180 KG INC) | H151: KG | I151: 1800 | J151: 33.066172 | K151: 41 | L151: 14280.89 | M151: 0.193508 | N151: MXN | O151: 73800 | P151: =MONTH(C151) -> 5 | Q151: =WEEKNUM(C151) -> 20 | R151: =VLOOKUP(G151,Catalogo!A:B,2,0) -> ESTIREN ACRILICA | S151: =(K151-J151)*I151*U151 -> 14280.89 | T151: =O151-S151 -> 59519.11 | U151: =IF(N151="USD",(O151/I151/K151),1) -> 1
A152: HMO/2026/00332 | B152: AGROBIOLIFE | C152: 46157 | D152: 30 Días | E152: 46187 | F152: ILSE GARCÍA | G152: [LD048] DESPUMAROL PORRON 50 KG INC | H152: KG | I152: 200 | J152: 60.2313 | K152: 68 | L152: 1553.74 | M152: 0.11424559 | N152: MXN | O152: 13600 | P152: =MONTH(C152) -> 5 | Q152: =WEEKNUM(C152) -> 20 | R152: =VLOOKUP(G152,Catalogo!A:B,2,0) -> DESPUMAROL | S152: =(K152-J152)*I152*U152 -> 1553.74 | T152: =O152-S152 -> 12046.26 | U152: =IF(N152="USD",(O152/I152/K152),1) -> 1
A153: HMO/2026/00331 | B153: AGROBIOLIFE | C153: 46157 | D153: 30 Días | E153: 46187 | F153: ILSE GARCÍA | G153: [LD097-2] PROTEINA VEGETAL PVH 11307 (SACO 25 KG) | H153: KG | I153: 1000 | J153: 65.99198 | K153: 78 | L153: 12008.02 | M153: 0.15394897 | N153: MXN | O153: 78000 | P153: =MONTH(C153) -> 5 | Q153: =WEEKNUM(C153) -> 20 | R153: =VLOOKUP(G153,Catalogo!A:B,2,0) -> PROTEINA VEGETAL PVH 11307 | S153: =(K153-J153)*I153*U153 -> 12008.02 | T153: =O153-S153 -> 65991.98 | U153: =IF(N153="USD",(O153/I153/K153),1) -> 1
A154: HMO/2026/00329 | B154: ABEL LOPEZ ROJO | C154: 46157 | D154: Pago inmediato | E154: 46157 | F154: ILSE GARCÍA | G154: [LD096] POTASA CAUSTICA EN ESCAMAS COREANA SACO 25 KG | H154: KG | I154: 75 | J154: 33.992 | K154: 48.3 | L154: 1073.1 | M154: 0.29623188 | N154: MXN | O154: 3622.5 | P154: =MONTH(C154) -> 5 | Q154: =WEEKNUM(C154) -> 20 | R154: =VLOOKUP(G154,Catalogo!A:B,2,0) -> POTASA CAUSTICA EN ESCAMAS COREANA | S154: =(K154-J154)*I154*U154 -> 1073.1 | T154: =O154-S154 -> 2549.4 | U154: =IF(N154="USD",(O154/I154/K154),1) -> 1
A155: HMO/2026/00328 | B155: KESECOME ALIMENTARIA | C155: 46157 | D155: 30 Días | E155: 46187 | F155: FREDY SALAS | G155: [LD072-2] LESS 28% (TAMBOR PLASTICO 220 KG INC) | H155: KG | I155: 220 | J155: 20.902227 | K155: 35 | L155: 3101.5101 | M155: 0.40279351 | N155: MXN | O155: 7700 | P155: =MONTH(C155) -> 5 | Q155: =WEEKNUM(C155) -> 20 | R155: =VLOOKUP(G155,Catalogo!A:B,2,0) -> LESS 28% | S155: =(K155-J155)*I155*U155 -> 3101.5101 | T155: =O155-S155 -> 4598.4899 | U155: =IF(N155="USD",(O155/I155/K155),1) -> 1
A156: HMO/2026/00327 | B156: DISTRIBUIDORA EQUINA SMC | C156: 46156 | D156: 30 Días | E156: 46186 | F156: ILSE GARCÍA | G156: [LD137-2] ACEITE MINERAL LTS (TAMBOR PLASTICO 200 L INC) | H156: L | I156: 200 | J156: 48 | K156: 58 | L156: 2000 | M156: 0.17241379 | N156: MXN | O156: 11600 | P156: =MONTH(C156) -> 5 | Q156: =WEEKNUM(C156) -> 20 | R156: =VLOOKUP(G156,Catalogo!A:B,2,0) -> ACEITE MINERAL | S156: =(K156-J156)*I156*U156 -> 2000 | T156: =O156-S156 -> 9600 | U156: =IF(N156="USD",(O156/I156/K156),1) -> 1
A157: CLN/2026/00126 | B157: MARIA DEL CARMEN RIVERA QUINTERO | C157: 46156 | D157: 30 Días | E157: 46186 | F157: FREDY SALAS | G157: [LD116] TRICLORO POLVO CUÑETE 50 KG | H157: KG | I157: 250 | J157: 45.3652 | K157: 54 | L157: 2158.7 | M157: 0.1599037 | N157: MXN | O157: 13500 | P157: =MONTH(C157) -> 5 | Q157: =WEEKNUM(C157) -> 20 | R157: =VLOOKUP(G157,Catalogo!A:B,2,0) -> TRICLORO POLVO | S157: =(K157-J157)*I157*U157 -> 2158.7 | T157: =O157-S157 -> 11341.3 | U157: =IF(N157="USD",(O157/I157/K157),1) -> 1
A158: HMO/2026/00326 | B158: ABASTECEDORA HIGIENICA DE SONORA | C158: 46155 | D158: 30 Días | E158: 46185 | F158: ILSE GARCÍA | G158: [LD016-1] ACIDO FOSFORICO CLARIFICADO 85% (PORRON NATURAL 30 KG INC) | H158: KG | I158: 270 | J158: 1.840587 | K158: 2.75 | L158: 245.54151 | M158: 0.33069564 | N158: USD | O158: 12809.61 | P158: =MONTH(C158) -> 5 | Q158: =WEEKNUM(C158) -> 20 | R158: =VLOOKUP(G158,Catalogo!A:B,2,0) -> ACIDO FOSFORICO CLARIFICADO 85% | S158: =(K158-J158)*I158*U158 -> 4236.0821 | T158: =O158-S158 -> 8573.5279 | U158: =IF(N158="USD",(O158/I158/K158),1) -> 17.252
A159: HMO/2026/00325 | B159: PINTURAS DE CAJEME | C159: 46155 | D159: 30 Días | E159: 46185 | F159: ILSE GARCÍA | G159: [LD111-2] THINNER AMERICANO (TAMBOR LAMINA 200 L INC) | H159: L | I159: 600 | J159: 26.5275 | K159: 36 | L159: 5683.5 | M159: 0.263125 | N159: MXN | O159: 21600 | P159: =MONTH(C159) -> 5 | Q159: =WEEKNUM(C159) -> 20 | R159: =VLOOKUP(G159,Catalogo!A:B,2,0) -> THINNER AMERICANO | S159: =(K159-J159)*I159*U159 -> 5683.5 | T159: =O159-S159 -> 15916.5 | U159: =IF(N159="USD",(O159/I159/K159),1) -> 1
... A212: HMO/2026/00289 | B212: ABASTECEDORA HIGIENICA DE SONORA | C212: 46139 | D212: 30 Días | E212: 46169 | F212: ILSE GARCÍA | G212: [LD137-2] ACEITE MINERAL LTS (TAMBOR PLASTICO 200 L INC) | H212: L | I212: 600 | J212: 48 | K212: 57 | L212: 5400 | M212: 0.15789474 | N212: MXN | O212: 34200 | P212: =MONTH(C212) -> 4 | Q212: =WEEKNUM(C212) -> 18 | R212: =VLOOKUP(G212,Catalogo!A:B,2,0) -> ACEITE MINERAL | S212: =(K212-J212)*I212*U212 -> 5400 | T212: =O212-S212 -> 28800 | U212: =IF(N212="USD",(O212/I212/K212),1) -> 1
A213: HMO/2026/00286 | B213: ABASTECEDORA HIGIENICA DE SONORA | C213: 46139 | D213: 30 Días | E213: 46169 | F213: ILSE GARCÍA | G213: [LD072-2] LESS 28% (TAMBOR PLASTICO 220 KG INC) | H213: KG | I213: 880 | J213: 21.675727 | K213: 29.5 | L213: 6885.3602 | M213: 0.26522959 | N213: MXN | O213: 12980 | P213: =MONTH(C213) -> 4 | Q213: =WEEKNUM(C213) -> 18 | R213: =VLOOKUP(G213,Catalogo!A:B,2,0) -> LESS 28% | S213: 3442.68 | T213: 9537.32 | U213: =IF(N213="USD",(O213/I213/K213),1) -> 1
A214: HMO/2026/00285 | B214: HECTOR SAU ESPINOZA | C214: 46139 | D214: 30 Días | E214: 46169 | F214: ILSE GARCÍA | G214: [LD065] HIPOCLORITO DE CALCIO GRANULAR HTH SKU 30034 CUÑETE 45 KG | H214: KG | I214: 315 | J214: 60.234698 | K214: 90 | L214: 9376.0701 | M214: 0.33072558 | N214: MXN | O214: 28350 | P214: =MONTH(C214) -> 4 | Q214: =WEEKNUM(C214) -> 18 | R214: =VLOOKUP(G214,Catalogo!A:B,2,0) -> HIPOCLORITO DE CALCIO GRANULAR HTH | S214: =(K214-J214)*I214*U214 -> 9376.0701 | T214: =O214-S214 -> 18973.93 | U214: =IF(N214="USD",(O214/I214/K214),1) -> 1
A215: HMO/2026/00284 | B215: ZAYDA CAMILA GARCIA GARCIA | C215: 46139 | D215: Pago inmediato | E215: 46139 | F215: ILSE GARCÍA | G215: [LD073-2] LESS 70% (TAMBOR PLASTICO 170 KG INC) | H215: KG | I215: 340 | J215: 37.248353 | K215: 48 | L215: 3655.56 | M215: 0.22399265 | N215: MXN | O215: 16320 | P215: =MONTH(C215) -> 4 | Q215: =WEEKNUM(C215) -> 18 | R215: =VLOOKUP(G215,Catalogo!A:B,2,0) -> LESS 70% | S215: =(K215-J215)*I215*U215 -> 3655.56 | T215: =O215-S215 -> 12664.44 | U215: =IF(N215="USD",(O215/I215/K215),1) -> 1
A216: HMO/2026/00283 | B216: JESUS ALEJANDRO GOMEZ ESPINOZA | C216: 46139 | D216: 30 Días | E216: 46169 | F216: ILSE GARCÍA | G216: [LD073-2] LESS 70% (TAMBOR PLASTICO 170 KG INC) | H216: KG | I216: 170 | J216: 37.248353 | K216: 48 | L216: 1827.78 | M216: 0.22399265 | N216: MXN | O216: 8160 | P216: =MONTH(C216) -> 4 | Q216: =WEEKNUM(C216) -> 18 | R216: =VLOOKUP(G216,Catalogo!A:B,2,0) -> LESS 70% | S216: =(K216-J216)*I216*U216 -> 1827.78 | T216: =O216-S216 -> 6332.22 | U216: =IF(N216="USD",(O216/I216/K216),1) -> 1
A217: CLN/2026/00112 | B217: BRAULIO ARIAS URIAS | C217: 46139 | D217: Pago inmediato | E217: 46139 | F217: MATEO LÓPEZ | G217: [LD065] HIPOCLORITO DE CALCIO GRANULAR HTH SKU 30034 CUÑETE 45 KG | H217: KG | I217: 1035 | J217: 60.234686 | K217: 79.9 | L217: 20353.6 | M217: 0.24612408 | N217: MXN | O217: 82696.5 | P217: =MONTH(C217) -> 4 | Q217: =WEEKNUM(C217) -> 18 | R217: =VLOOKUP(G217,Catalogo!A:B,2,0) -> HIPOCLORITO DE CALCIO GRANULAR HTH | S217: =(K217-J217)*I217*U217 -> 20353.6 | T217: =O217-S217 -> 62342.9 | U217: =IF(N217="USD",(O217/I217/K217),1) -> 1
A218: CLN/2026/00111 | B218: JULIO CESAR SEPULVEDA LOPEZ | C218: 46139 | D218: 30 Días | E218: 46169 | F218: FREDY SALAS | G218: [LD065] HIPOCLORITO DE CALCIO GRANULAR HTH SKU 30034 CUÑETE 45 KG | H218: KG | I218: 675 | J218: 3.47 | K218: 4.8 | L218: 897.75 | M218: 0.27708333 | N218: USD | O218: 56392.85 | P218: =MONTH(C218) -> 4 | Q218: =WEEKNUM(C218) -> 18 | R218: =VLOOKUP(G218,Catalogo!A:B,2,0) -> HIPOCLORITO DE CALCIO GRANULAR HTH | S218: =(K218-J218)*I218*U218 -> 15625.519 | T218: =O218-S218 -> 40767.331 | U218: =IF(N218="USD",(O218/I218/K218),1) -> 17.405201
A219: HMO/2026/00282 | B219: SAUL AYON REYNA | C219: 46137 | D219: 30 Días | E219: 46167 | F219: ILSE GARCÍA | G219: [LD052-2] ESTIREN ACRILICA (TAMBOR LAMINA 180 KG INC) | H219: KG | I219: 180 | J219: 31.324333 | K219: 38 | L219: 1201.6201 | M219: 0.17567545 | N219: MXN | O219: 6840 | P219: =MONTH(C219) -> 4 | Q219: =WEEKNUM(C219) -> 17 | R219: =VLOOKUP(G219,Catalogo!A:B,2,0) -> ESTIREN ACRILICA | S219: =(K219-J219)*I219*U219 -> 1201.6201 | T219: =O219-S219 -> 5638.3799 | U219: =IF(N219="USD",(O219/I219/K219),1) -> 1
A220: HMO/2026/00281 | B220: HECTOR SAU ESPINOZA | C220: 46137 | D220: 30 Días | E220: 46167 | F220: ILSE GARCÍA | G220: [LD065] HIPOCLORITO DE CALCIO GRANULAR HTH SKU 30034 CUÑETE 45 KG | H220: KG | I220: 45 | J220: 60.234667 | K220: 90 | L220: 1339.44 | M220: 0.33072592 | N220: MXN | O220: 4050 | P220: =MONTH(C220) -> 4 | Q220: =WEEKNUM(C220) -> 17 | R220: =VLOOKUP(G220,Catalogo!A:B,2,0) -> HIPOCLORITO DE CALCIO GRANULAR HTH | S220: =(K220-J220)*I220*U220 -> 1339.44 | T220: =O220-S220 -> 2710.56 | U220: =IF(N220="USD",(O220/I220/K220),1) -> 1
A221: HMO/2026/00280 | B221: INSECTICIDAS DEL PACIFICO | C221: 46137 | D221: 30 Días | E221: 46167 | F221: ILSE GARCÍA | G221: [LD012] ACIDO CITRICO WEIFANG SACO 25 KG | H221: KG | I221: 300 | J221: 1.363658 | K221: 1.87 | L221: 151.9026 | M221: 0.27077112 | N221: USD | O221: 9738.23 | P221: =MONTH(C221) -> 4 | Q221: =WEEKNUM(C221) -> 17 | R221: =VLOOKUP(G221,Catalogo!A:B,2,0) -> ACIDO CITRICO WEIFANG | S221: =(K221-J221)*I221*U221 -> 2636.8315 | T221: =O221-S221 -> 7101.3985 | U221: =IF(N221="USD",(O221/I221/K221),1) -> 17.358699
A222: HMO/2026/00279 | B222: JESUS FRANCISCO OLMOS CASTRO | C222: 46136 | D222: 30 Días | E222: 46136 | F222: FREDY SALAS | G222: [LD065] HIPOCLORITO DE CALCIO GRANULAR HTH SKU 30034 CUÑETE 45 KG | H222: KG | I222: 135 | J222: 60.130593 | K222: 83.905664 | L222: 3209.6299 | M222: 0.28335449 | N222: MXN | O222: 11327.26 | P222: =MONTH(C222) -> 4 | Q222: =WEEKNUM(C222) -> 17 | R222: =VLOOKUP(G222,Catalogo!A:B,2,0) -> HIPOCLORITO DE CALCIO GRANULAR HTH | S222: =(K222-J222)*I222*U222 -> 3209.6346 | T222: =O222-S222 -> 8117.6254 | U222: =IF(N222="USD",(O222/I222/K222),1) -> 1
A223: HMO/2026/00278 | B223: PROQUISON | C223: 46136 | D223: 30 Días | E223: 46166 | F223: FREDY SALAS | G223: [LD065] HIPOCLORITO DE CALCIO GRANULAR HTH SKU 30034 CUÑETE 45 KG | H223: KG | I223: 45 | J223: 3.464007 | K223: 4.8 | L223: 60.119685 | M223: 0.27833188 | N223: USD | O223: 3749.48 | P223: =MONTH(C223) -> 4 | Q223: =WEEKNUM(C223) -> 17 | R223: =VLOOKUP(G223,Catalogo!A:B,2,0) -> HIPOCLORITO DE CALCIO GRANULAR HTH | S223: =(K223-J223)*I223*U223 -> 1043.5998 | T223: =O223-S223 -> 2705.8802 | U223: =IF(N223="USD",(O223/I223/K223),1) -> 17.358704
A224: HMO/2026/00277 | B224: PAPAS RAYGOZA DE CAJEME | C224: 46136 | D224: Pago inmediato | E224: 46136 | F224: FREDY SALAS | G224: [LD065] HIPOCLORITO DE CALCIO GRANULAR HTH SKU 30034 CUÑETE 45 KG | H224: KG | I224: 90 | J224: 60.130556 | K224: 96 | L224: 3228.25 | M224: 0.37364004 | N224: MXN | O224: 8640 | P224: =MONTH(C224) -> 4 | Q224: =WEEKNUM(C224) -> 17 | R224: =VLOOKUP(G224,Catalogo!A:B,2,0) -> HIPOCLORITO DE CALCIO GRANULAR HTH | S224: =(K224-J224)*I224*U224 -> 3228.25 | T224: =O224-S224 -> 5411.75 | U224: =IF(N224="USD",(O224/I224/K224),1) -> 1
A225: HMO/2026/00276 | B225: QMX4 | C225: 46136 | D225: 30 Días | E225: 46166 | F225: FREDY SALAS | G225: [LD065] HIPOCLORITO DE CALCIO GRANULAR HTH SKU 30034 CUÑETE 45 KG | H225: KG | I225: 1035 | J225: 3.469279 | K225: 4.28 | L225: 839.09623 | M225: 0.18942079 | N225: USD | O225: 76895.57 | P225: =MONTH(C225) -> 4 | Q225: =WEEKNUM(C225) -> 17 | R225: =VLOOKUP(G225,Catalogo!A:B,2,0) -> HIPOCLORITO DE CALCIO GRANULAR HTH | S225: =(K225-J225)*I225*U225 -> 14565.62 | T225: =O225-S225 -> 62329.95 | U225: =IF(N225="USD",(O225/I225/K225),1) -> 17.3587
... A237: HMO/2026/00268 | B237: PINTURAS DE CAJEME | C237: 46135 | D237: 30 Días | E237: 46165 | F237: ILSE GARCÍA | G237: [LD122-2] XILOL (TAMBOR LAMINA 200 L INC) | H237: L | I237: 200 | J237: 31.9225 | K237: 38 | L237: 1215.5 | M237: 0.15993421 | N237: MXN | O237: 7600 | P237: =MONTH(C237) -> 4 | Q237: =WEEKNUM(C237) -> 17 | R237: =VLOOKUP(G237,Catalogo!A:B,2,0) -> XILOL | S237: =(K237-J237)*I237*U237 -> 1215.5 | T237: =O237-S237 -> 6384.5 | U237: =IF(N237="USD",(O237/I237/K237),1) -> 1
A238: HMO/2026/00267 | B238: ABASTECEDORA HIGIENICA DE SONORA | C238: 46135 | D238: 30 Días | E238: 46165 | F238: ILSE GARCÍA | G238: [LD072-2] LESS 28% (TAMBOR PLASTICO 220 KG INC) | H238: KG | I238: 880 | J238: 21.675727 | K238: 29.5 | L238: 6885.3602 | M238: 0.26522959 | N238: MXN | O238: 12980 | P238: =MONTH(C238) -> 4 | Q238: =WEEKNUM(C238) -> 17 | R238: =VLOOKUP(G238,Catalogo!A:B,2,0) -> LESS 28% | S238: 3442.68 | T238: 9537.32 | U238: =IF(N238="USD",(O238/I238/K238),1) -> 1
A239: CLN/2026/00107 | B239: CARLOS ROMAN ESQUIVEL | C239: 46135 | D239: 30 Días | E239: 46135 | F239: MATEO LÓPEZ | G239: [LD109] SULFATO DE ZINC (ZN) SACO 25 KG | H239: KG | I239: 1000 | J239: 32.12696 | K239: 41 | L239: 8873.04 | M239: 0.21641561 | N239: MXN | O239: 41000 | P239: =MONTH(C239) -> 4 | Q239: =WEEKNUM(C239) -> 17 | R239: =VLOOKUP(G239,Catalogo!A:B,2,0) -> SULFATO DE ZINC | S239: =(K239-J239)*I239*U239 -> 8873.04 | T239: =O239-S239 -> 32126.96 | U239: =IF(N239="USD",(O239/I239/K239),1) -> 1
A240: HMO/2026/00266 | B240: PORCICULTORES DE CAJEME | C240: 46134 | D240: 30 Días | E240: 46164 | F240: FREDY SALAS | G240: [LD117] TRICLORO TABLETA 3" CUÑETE 50 KG | H240: KG | I240: 50 | J240: 45.3414 | K240: 57 | L240: 582.93 | M240: 0.20453684 | N240: MXN | O240: 2850 | P240: =MONTH(C240) -> 4 | Q240: =WEEKNUM(C240) -> 17 | R240: =VLOOKUP(G240,Catalogo!A:B,2,0) -> TRICLORO TABLETA 3" | S240: =(K240-J240)*I240*U240 -> 582.93 | T240: =O240-S240 -> 2267.07 | U240: =IF(N240="USD",(O240/I240/K240),1) -> 1
A241: HMO/2026/00265 | B241: PINTURAS DE CAJEME | C241: 46134 | D241: 30 Días | E241: 46164 | F241: ILSE GARCÍA | G241: [LD111-2] THINNER AMERICANO (TAMBOR LAMINA 200 L INC) | H241: L | I241: 400 | J241: 26.5275 | K241: 31 | L241: 1789 | M241: 0.14427419 | N241: MXN | O241: 12400 | P241: =MONTH(C241) -> 4 | Q241: =WEEKNUM(C241) -> 17 | R241: =VLOOKUP(G241,Catalogo!A:B,2,0) -> THINNER AMERICANO | S241: =(K241-J241)*I241*U241 -> 1789 | T241: =O241-S241 -> 10611 | U241: =IF(N241="USD",(O241/I241/K241),1) -> 1
A242: HMO/2026/00264 | B242: AGROBIOLIFE | C242: 46134 | D242: 30 Días | E242: 46164 | F242: ILSE GARCÍA | G242: [LD122-2] XILOL (TAMBOR LAMINA 200 L INC) | H242: L | I242: 200 | J242: 31.9225 | K242: 44 | L242: 2415.5 | M242: 0.27448864 | N242: MXN | O242: 8800 | P242: =MONTH(C242) -> 4 | Q242: =WEEKNUM(C242) -> 17 | R242: =VLOOKUP(G242,Catalogo!A:B,2,0) -> XILOL | S242: =(K242-J242)*I242*U242 -> 2415.5 | T242: =O242-S242 -> 6384.5 | U242: =IF(N242="USD",(O242/I242/K242),1) -> 1
A243: CLN/2026/00106 | B243: GRUBOSA COMERCIAL | C243: 46134 | D243: 30 Días | E243: 46164 | F243: MATEO LÓPEZ | G243: [LD073-2] LESS 70% (TAMBOR PLASTICO 170 KG INC) | H243: KG | I243: 170 | J243: 37.248353 | K243: 46.5 | L243: 1572.78 | M243: 0.19896015 | N243: MXN | O243: 7905 | P243: =MONTH(C243) -> 4 | Q243: =WEEKNUM(C243) -> 17 | R243: =VLOOKUP(G243,Catalogo!A:B,2,0) -> LESS 70% | S243: =(K243-J243)*I243*U243 -> 1572.78 | T243: =O243-S243 -> 6332.22 | U243: =IF(N243="USD",(O243/I243/K243),1) -> 1
A244: HMO/2026/00263 | B244: JESUS ALFREDO AYON REYNA | C244: 46133 | D244: 30 Días | E244: 46163 | F244: ILSE GARCÍA | G244: [LD022] ALCOHOL POLIVINILICO PVOH 08850 SACO 20 KG | H244: KG | I244: 1000 | J244: 39.5106 | K244: 49.75 | L244: 10239.4 | M244: 0.20581709 | N244: MXN | O244: 49750 | P244: =MONTH(C244) -> 4 | Q244: =WEEKNUM(C244) -> 17 | R244: =VLOOKUP(G244,Catalogo!A:B,2,0) -> ALCOHOL POLIVINILICO PVOH 08850 | S244: =(K244-J244)*I244*U244 -> 10239.4 | T244: =O244-S244 -> 39510.6 | U244: =IF(N244="USD",(O244/I244/K244),1) -> 1
A245: HMO/2026/00262 | B245: YERALDIN CASTRO CADENA | C245: 46133 | D245: 30 Días | E245: 46163 | F245: ILSE GARCÍA | G245: [LD082] NITRATO DE SODIO CHILENO SACO 25 KG | H245: KG | I245: 150 | J245: 58.183533 | K245: 68 | L245: 1472.47 | M245: 0.14435981 | N245: MXN | O245: 10200 | P245: =MONTH(C245) -> 4 | Q245: =WEEKNUM(C245) -> 17 | R245: =VLOOKUP(G245,Catalogo!A:B,2,0) -> NITRATO DE SODIO CHILENO SACO 25 KG | S245: =(K245-J245)*I245*U245 -> 1472.4701 | T245: =O245-S245 -> 8727.53 | U245: =IF(N245="USD",(O245/I245/K245),1) -> 1
A246: HMO/2026/00261 | B246: ZAYDA CAMILA GARCIA GARCIA | C246: 46133 | D246: Pago inmediato | E246: 46133 | F246: ILSE GARCÍA | G246: [LD073-2] LESS 70% (TAMBOR PLASTICO 170 KG INC) | H246: KG | I246: 340 | J246: 37.248353 | K246: 48 | L246: 3655.56 | M246: 0.22399265 | N246: MXN | O246: 16320 | P246: =MONTH(C246) -> 4 | Q246: =WEEKNUM(C246) -> 17 | R246: =VLOOKUP(G246,Catalogo!A:B,2,0) -> LESS 70% | S246: =(K246-J246)*I246*U246 -> 3655.56 | T246: =O246-S246 -> 12664.44 | U246: =IF(N246="USD",(O246/I246/K246),1) -> 1
A247: CLN/2026/00104 | B247: AGRO PRODUCTOS BALEY | C247: 46133 | D247: 30 Días | E247: 46163 | F247: MATEO LÓPEZ | G247: [LD023-2] ALCOHOL TRIDECILICO 8 MOLES (TAMBOR LAMINA 200 KG INC) | H247: KG | I247: 400 | J247: 60.2003 | K247: 68 | L247: 3119.88 | M247: 0.11470147 | N247: MXN | O247: 27200 | P247: =MONTH(C247) -> 4 | Q247: =WEEKNUM(C247) -> 17 | R247: =VLOOKUP(G247,Catalogo!A:B,2,0) -> ALCOHOL TRIDECILICO 8 MOLES | S247: =(K247-J247)*I247*U247 -> 3119.88 | T247: =O247-S247 -> 24080.12 | U247: =IF(N247="USD",(O247/I247/K247),1) -> 1
A248: CLN/2026/00103 | B248: AQUA DUX DE MEXICO | C248: 46133 | D248: 30 Días | E248: 46163 | F248: FREDY SALAS | G248: [LD030-1] BICARBONATO DE SODIO USP (SACO 25 KG) | H248: KG | I248: 500 | J248: 1.057032 | K248: 1.12 | L248: 31.484 | M248: 0.056221429 | N248: USD | O248: 9699.2 | P248: =MONTH(C248) -> 4 | Q248: =WEEKNUM(C248) -> 17 | R248: =VLOOKUP(G248,Catalogo!A:B,2,0) -> BICARBONATO DE SODIO USP | S248: =(K248-J248)*I248*U248 -> 545.30288 | T248: =O248-S248 -> 9153.8971 | U248: =IF(N248="USD",(O248/I248/K248),1) -> 17.32
A249: HMO/2026/00260 | B249: EULALIO MOLINA TERAN | C249: 46132 | D249: 30 Días | E249: 46162 | F249: ILSE GARCÍA | G249: [LD052-2] ESTIREN ACRILICA (TAMBOR LAMINA 180 KG INC) | H249: KG | I249: 720 | J249: 31.572486 | K249: 38 | L249: 4627.8101 | M249: 0.16914511 | N249: MXN | O249: 27360 | P249: =MONTH(C249) -> 4 | Q249: =WEEKNUM(C249) -> 17 | R249: =VLOOKUP(G249,Catalogo!A:B,2,0) -> ESTIREN ACRILICA | S249: =(K249-J249)*I249*U249 -> 4627.8101 | T249: =O249-S249 -> 22732.19 | U249: =IF(N249="USD",(O249/I249/K249),1) -> 1
A250: CLN/2026/00101 | B250: AQUASTORE SUMINISTROS ACUICOLAS DEL PACIFICO | C250: 46132 | D250: Pago inmediato | E250: 46162 | F250: MATEO LÓPEZ | G250: [LD051] EDTA SACO 25 KG | H250: KG | I250: 200 | J250: 48.2862 | K250: 63 | L250: 2942.76 | M250: 0.23355238 | N250: MXN | O250: 12600 | P250: =MONTH(C250) -> 4 | Q250: =WEEKNUM(C250) -> 17 | R250: =VLOOKUP(G250,Catalogo!A:B,2,0) -> EDTA | S250: =(K250-J250)*I250*U250 -> 2942.76 | T250: =O250-S250 -> 9657.24 | U250: =IF(N250="USD",(O250/I250/K250),1) -> 1
... A294: HMO/2026/00224 | B294: YERALDIN CASTRO CADENA | C294: 46119 | D294: 30 Días | E294: 46149 | F294: ILSE GARCÍA | G294: [LD010] ACIDO ASCORBICO CAJA 25 KG | H294: KG | I294: 300 | J294: 58.7259 | K294: 90 | L294: 9382.23 | M294: 0.34749 | N294: MXN | O294: 27000 | P294: =MONTH(C294) -> 4 | Q294: =WEEKNUM(C294) -> 15 | R294: =VLOOKUP(G294,Catalogo!A:B,2,0) -> ACIDO ASCORBICO | S294: =(K294-J294)*I294*U294 -> 9382.23 | T294: =O294-S294 -> 17617.77 | U294: =IF(N294="USD",(O294/I294/K294),1) -> 1
A295: HMO/2026/00223 | B295: YERALDIN CASTRO CADENA | C295: 46119 | D295: 30 Días | E295: 46149 | F295: ILSE GARCÍA | G295: [LD065] HIPOCLORITO DE CALCIO GRANULAR HTH SKU 30034 CUÑETE 45 KG | H295: KG | I295: 675 | J295: 3.483024 | K295: 4.8 | L295: =15817.43/17.7932 -> 888.95927 | M295: 0.27437013 | N295: USD | O295: 57649.97 | P295: =MONTH(C295) -> 4 | Q295: =WEEKNUM(C295) -> 15 | R295: =VLOOKUP(G295,Catalogo!A:B,2,0) -> HIPOCLORITO DE CALCIO GRANULAR HTH | S295: =(K295-J295)*I295*U295 -> 15817.422 | T295: =O295-S295 -> 41832.548 | U295: =IF(N295="USD",(O295/I295/K295),1) -> 17.793201
A296: HMO/2026/00222 | B296: ORBEX CHEMICAL | C296: 46119 | D296: 30 Días | E296: 46149 | F296: ILSE GARCÍA | G296: [LD065] HIPOCLORITO DE CALCIO GRANULAR HTH SKU 30034 CUÑETE 45 KG | H296: KG | I296: 1800 | J296: 3.483024 | K296: 4.6 | L296: 2010.5568 | M296: 0.24282087 | N296: USD | O296: 147327.7 | P296: =MONTH(C296) -> 4 | Q296: =WEEKNUM(C296) -> 15 | R296: =VLOOKUP(G296,Catalogo!A:B,2,0) -> HIPOCLORITO DE CALCIO GRANULAR HTH | S296: =(K296-J296)*I296*U296 -> 35774.24 | T296: =O296-S296 -> 111553.46 | U296: =IF(N296="USD",(O296/I296/K296),1) -> 17.7932
A297: HMO/2026/00221 | B297: YERALDIN CASTRO CADENA | C297: 46118 | D297: 30 Días | E297: 46148 | F297: ILSE GARCÍA | G297: [LD082] NITRATO DE SODIO CHILENO SACO 25 KG | H297: KG | I297: 175 | J297: 58.177143 | K297: 68 | L297: 1719 | M297: 0.14445378 | N297: MXN | O297: 11900 | P297: =MONTH(C297) -> 4 | Q297: =WEEKNUM(C297) -> 15 | R297: =VLOOKUP(G297,Catalogo!A:B,2,0) -> NITRATO DE SODIO CHILENO SACO 25 KG | S297: =(K297-J297)*I297*U297 -> 1719 | T297: =O297-S297 -> 10181 | U297: =IF(N297="USD",(O297/I297/K297),1) -> 1
A298: HMO/2026/00220 | B298: DAVID FRANCISCO MIRAMONTES IRIBE | C298: 46118 | D298: Pago inmediato | E298: 46118 | F298: ILSE GARCÍA | G298: [LD072-5] LESS 28% (PORRON 50 KG INC) | H298: KG | I298: 300 | J298: 20.460333 | K298: 23.5 | L298: 911.9001 | M298: 0.12934753 | N298: MXN | O298: 7050 | P298: =MONTH(C298) -> 4 | Q298: =WEEKNUM(C298) -> 15 | R298: =VLOOKUP(G298,Catalogo!A:B,2,0) -> LESS 28% | S298: =(K298-J298)*I298*U298 -> 911.9001 | T298: =O298-S298 -> 6138.0999 | U298: =IF(N298="USD",(O298/I298/K298),1) -> 1
A299: HMO/2026/00219 | B299: KESECOME ALIMENTARIA | C299: 46118 | D299: 30 Días | E299: 46148 | F299: FREDY SALAS | G299: [LD008-2] ACIDO ACETICO GLACIAL ALIMENTICIO (PORRON NATURAL 20 KG INC) | H299: KG | I299: 220 | J299: 26.250773 | K299: 43 | L299: 3684.8299 | M299: 0.38951691 | N299: MXN | O299: 9460 | P299: =MONTH(C299) -> 4 | Q299: =WEEKNUM(C299) -> 15 | R299: =VLOOKUP(G299,Catalogo!A:B,2,0) -> ACIDO ACETICO GLACIAL ALIMENTICIO | S299: =(K299-J299)*I299*U299 -> 3684.8299 | T299: =O299-S299 -> 5775.1701 | U299: =IF(N299="USD",(O299/I299/K299),1) -> 1
A300: HMO/2026/00218 | B300: CESAR AUGUSTO VEGA MADRID | C300: 46118 | D300: 30 Días | E300: 46148 | F300: ILSE GARCÍA | G300: [LD065] HIPOCLORITO DE CALCIO GRANULAR HTH SKU 30034 CUÑETE 45 KG | H300: KG | I300: 1440 | J300: 3.479406 | K300: 4.6 | L300: 1613.6554 | M300: 0.24360739 | N300: USD | O300: 117984.7 | P300: =MONTH(C300) -> 4 | Q300: =WEEKNUM(C300) -> 15 | R300: =VLOOKUP(G300,Catalogo!A:B,2,0) -> HIPOCLORITO DE CALCIO GRANULAR HTH | S300: =(K300-J300)*I300*U300 -> 28741.945 | T300: =O300-S300 -> 89242.755 | U300: =IF(N300="USD",(O300/I300/K300),1) -> 17.8117
A301: HMO/2026/00217 | B301: SAUL AYON REYNA | C301: 46118 | D301: 30 Días | E301: 46148 | F301: ILSE GARCÍA | G301: [LD052-2] ESTIREN ACRILICA (TAMBOR LAMINA 180 KG INC) | H301: KG | I301: 360 | J301: 31.150056 | K301: 38 | L301: 2465.9798 | M301: 0.18026168 | N301: MXN | O301: 13680 | P301: =MONTH(C301) -> 4 | Q301: =WEEKNUM(C301) -> 15 | R301: =VLOOKUP(G301,Catalogo!A:B,2,0) -> ESTIREN ACRILICA | S301: =(K301-J301)*I301*U301 -> 2465.9798 | T301: =O301-S301 -> 11214.02 | U301: =IF(N301="USD",(O301/I301/K301),1) -> 1
A302: CLN/2026/00090 | B302: BRAULIO ARIAS URIAS | C302: 46118 | D302: Pago inmediato | E302: 46118 | F302: MATEO LÓPEZ | G302: [LD065] HIPOCLORITO DE CALCIO GRANULAR HTH SKU 30034 CUÑETE 45 KG | H302: KG | I302: 1035 | J302: 61.974135 | K302: 78.37 | L302: 16969.72 | M302: 0.20921099 | N302: MXN | O302: 81112.95 | P302: =MONTH(C302) -> 4 | Q302: =WEEKNUM(C302) -> 15 | R302: =VLOOKUP(G302,Catalogo!A:B,2,0) -> HIPOCLORITO DE CALCIO GRANULAR HTH | S302: =(K302-J302)*I302*U302 -> 16969.72 | T302: =O302-S302 -> 64143.23 | U302: =IF(N302="USD",(O302/I302/K302),1) -> 1
A303: CLN/2026/00089 | B303: MARIA DEL CARMEN RIVERA QUINTERO | C303: 46118 | D303: 30 Días | E303: 46148 | F303: FREDY SALAS | G303: [LD116] TRICLORO POLVO CUÑETE 50 KG | H303: KG | I303: 250 | J303: 45.48812 | K303: 54 | L303: 2127.97 | M303: 0.15762741 | N303: MXN | O303: 13500 | P303: =MONTH(C303) -> 4 | Q303: =WEEKNUM(C303) -> 15 | R303: =VLOOKUP(G303,Catalogo!A:B,2,0) -> TRICLORO POLVO | S303: =(K303-J303)*I303*U303 -> 2127.97 | T303: =O303-S303 -> 11372.03 | U303: =IF(N303="USD",(O303/I303/K303),1) -> 1
A304: CLN/2026/00088 | B304: JESUS ESTEBAN CHAVEZ PRECIADO | C304: 46118 | D304: 30 Días | E304: 46148 | F304: MATEO LÓPEZ | G304: [LD073-2] LESS 70% (TAMBOR PLASTICO 170 KG INC) | H304: KG | I304: 170 | J304: 34.988824 | K304: 41.5 | L304: 1106.8999 | M304: 0.15689581 | N304: MXN | O304: 7055 | P304: =MONTH(C304) -> 4 | Q304: =WEEKNUM(C304) -> 15 | R304: =VLOOKUP(G304,Catalogo!A:B,2,0) -> LESS 70% | S304: =(K304-J304)*I304*U304 -> 1106.8999 | T304: =O304-S304 -> 5948.1001 | U304: =IF(N304="USD",(O304/I304/K304),1) -> 1
A305: HMO/2026/00216 | B305: AQUASTORE SUMINISTROS ACUICOLAS DEL PACIFICO | C305: 46113 | D305: Pago inmediato | E305: 46143 | F305: MATEO LÓPEZ | G305: [LD065] HIPOCLORITO DE CALCIO GRANULAR HTH SKU 30034 CUÑETE 45 KG | H305: KG | I305: 135 | J305: 3.442377 | K305: 4.6 | L305: 156.2791 | M305: 0.25165717 | N305: USD | O305: 11180.05 | P305: =MONTH(C305) -> 4 | Q305: =WEEKNUM(C305) -> 14 | R305: =VLOOKUP(G305,Catalogo!A:B,2,0) -> HIPOCLORITO DE CALCIO GRANULAR HTH | S305: =(K305-J305)*I305*U305 -> 2813.5398 | T305: =O305-S305 -> 8366.5102 | U305: =IF(N305="USD",(O305/I305/K305),1) -> 18.003301
A306: HMO/2026/00215 | B306: PROGENMAR | C306: 46113 | D306: 30 Días | E306: 46143 | F306: ILSE GARCÍA | G306: [LD107] SULFATO DE COBRE PENOLES SACO 25 KG | H306: KG | I306: 1150 | J306: 64.489035 | K306: 77 | L306: 14387.61 | M306: 0.16248006 | N306: MXN | O306: 88550 | P306: =MONTH(C306) -> 4 | Q306: =WEEKNUM(C306) -> 14 | R306: =VLOOKUP(G306,Catalogo!A:B,2,0) -> SULFATO DE COBRE PEÑOLES | S306: =(K306-J306)*I306*U306 -> 14387.61 | T306: =O306-S306 -> 74162.39 | U306: =IF(N306="USD",(O306/I306/K306),1) -> 1
A307: HMO/2026/00214 | B307: COMERCIALIZADORA COSTA BELLA | C307: 46112 | D307: 30 Días | E307: 46142 | F307: ILSE GARCÍA | G307: [LD018-2] ADBS (TAMBOR PLASTICO 200 KG INC) | H307: KG | I307: 200 | J307: 34.8578 | K307: 63 | L307: 5628.44 | M307: 0.44670159 | N307: MXN | O307: 12600 | P307: =MONTH(C307) -> 3 | Q307: =WEEKNUM(C307) -> 14 | R307: =VLOOKUP(G307,Catalogo!A:B,2,0) -> ADBS | S307: =(K307-J307)*I307*U307 -> 5628.44 | T307: =O307-S307 -> 6971.56 | U307: =IF(N307="USD",(O307/I307/K307),1) -> 1
... A590: HMO/2026/00001 | B590: ORBEX CHEMICAL | C590: 46024 | D590: 30 Días | E590: 46054 | F590: ILSE GARCÍA | G590: [LD065] HIPOCLORITO DE CALCIO GRANULAR HTH SKU 30034 CUÑETE 45 KG | H590: KG | I590: 1350 | J590: 3.555103 | K590: 4.2 | L590: 870.61095 | M590: 0.1535469 | N590: USD | O590: 102066.8 | P590: =MONTH(C590) -> 1 | Q590: =WEEKNUM(C590) -> 1 | R590: =VLOOKUP(G590,Catalogo!A:B,2,0) -> HIPOCLORITO DE CALCIO GRANULAR HTH | S590: =(K590-J590)*I590*U590 -> 15672.041 | T590: =O590-S590 -> 86394.759 | U590: =IF(N590="USD",(O590/I590/K590),1) -> 18.001199

Sheet Ventas
D1: Fecha corte | E1: 46199 | J1: Vendedor | K1: (Todas)
D2: Semana | E2: =WEEKNUM(E1) -> 26
A3: Vendedor / Cliente / Producto | B3: Cantidad | C3: Ut. Unit. | D3: Venta MN | E3: Ut Bruta MN. | F3: Margen% | G3: =GETPIVOTDATA("Ut Bruta MN.",$A$3)/GETPIVOTDATA("Venta MN",$A$3) -> 0.20952055 | J3: Producto / Cliente | K3: Cantidad | L3: Ut. Unit. | M3: Venta MN | N3: Ut Bruta MN | O3: Margen % | Q3: Cliente / Producto | R3: Cantidad | S3: Ut. Unit. | T3: Venta MN | U3: Ut Bruta MN | W3: Vendedor / Producto | X3: Cantidad | Y3: Ut. Unit. | Z3: Venta MN | AA3: Ut Bruta MN. | AB3: Margen% | AC3: =GETPIVOTDATA("Ut Bruta MN.",$A$3)/GETPIVOTDATA("Venta MN",$A$3) -> 0.20952055
A4: ILSE GARCÍA | B4: 63255 | C4: 10.036367 | D4: 3070157.4 | E4: 634850.37 | F4: 0.20678105 | J4: HIPOCLORITO DE CALCIO GRANULAR HTH | K4: 21015 | L4: 17.782982 | M4: 1651308.4 | N4: 373709.37 | O4: 0.22631107 | Q4: ADQUISICIONES PADRE KINO | R4: 12350 | S4: 7.4655939 | T4: 520526.67 | U4: 92200.085 | W4: ILSE GARCÍA | X4: 63255 | Y4: 10.036367 | Z4: 3070157.4 | AA4: 634850.37 | AB4: 0.20678105
A5: FREDY SALAS | B5: 8890 | C5: 14.964042 | D5: 618700.63 | E5: 133030.34 | F5: 0.21501568 | J5: ESTIREN ACRILICA | K5: 10980 | L5: 7.4537111 | M5: 423990 | N5: 81841.748 | O5: 0.19302754 | Q5: ACUAGRO | R5: 12000 | S5: 6.554086 | T5: 361401.2 | U5: 78649.032 | W5: FREDY SALAS | X5: 8890 | Y5: 14.964042 | Z5: 618700.63 | AA5: 133030.34 | AB5: 0.21501568
A6: MATEO LÓPEZ | B6: 8497 | C6: 14.654596 | D6: 570393.98 | E6: 124520.1 | F6: 0.21830542 | J6: TRIETANOLAMINA | K6: 10350 | L6: 7.5925922 | M6: 427256.25 | N6: 78583.329 | O6: 0.18392552 | Q6: JESUS ALFREDO AYON REYNA | R6: 7500 | S6: 8.5601745 | T6: 322630 | U6: 64201.309 | W6: MATEO LÓPEZ | X6: 8497 | Y6: 14.654596 | Z6: 570393.98 | AA6: 124520.1 | AB6: 0.21830542
A7: Total general | B7: 80642 | C7: 11.066204 | D7: 4259252 | E7: 892400.81 | F7: 0.20952055 | J7: POTASA CAUSTICA EN ESCAMA CHINA | K7: 3400 | L7: 12.783293 | M7: 178270.42 | N7: 43463.196 | O7: 0.24380487 | Q7: NRW CHEMIE MEXICANA | R7: 4500 | S7: 12.671851 | T7: 328079.43 | U7: 57023.33 | W7: Total general | X7: 80642 | Y7: 11.066204 | Z7: 4259252 | AA7: 892400.81 | AB7: 0.20952055
J8: LESS 70% | K8: 3230 | L8: 9.2902288 | M8: 149260 | N8: 30007.439 | O8: 0.2010414 | Q8: ORBEX CHEMICAL | R8: 2700 | S8: 19.693946 | T8: 219428.7 | U8: 53173.654
J9: ALCOHOL POLIVINILICO PVOH 08850 | K9: 3000 | L9: 9.7107733 | M9: 147310 | N9: 29132.32 | O9: 0.197762 | Q9: YERALDIN CASTRO CADENA | R9: 2250 | S9: 21.420872 | T9: 176140.45 | U9: 48196.962
J10: SULFATO DE COBRE PEÑOLES | K10: 2800 | L10: 10.314536 | M10: 209450 | N10: 28880.7 | O10: 0.13788828 | Q10: AQUASTORE SUMINISTROS ACUICOLAS DEL PACIFICO | R10: 2425 | S10: 18.505013 | T10: 187414.58 | U10: 44874.656
J11: ACIDO FOSFORICO 52% VERDE | K11: 8400 | L11: 3.28418 | M11: 165001.2 | N11: 27587.112 | O11: 0.1671934 | Q11: BRAULIO ARIAS URIAS | R11: 2070 | S11: 18.03059 | T11: 163809.45 | U11: 37323.32
J12: HEXAMETAFOSFATO DE SODIO POLVO TECNICO | K12: 1000 | L12: 22.61324 | M12: 60000 | N12: 22613.24 | O12: 0.37688733 | Q12: SAUL AYON REYNA | R12: 5220 | S12: 6.8928733 | T12: 198360 | U12: 35980.799
J13: ACIDO ASCORBICO | K13: 850 | L13: 23.418071 | M13: 73350 | N13: 19905.36 | O13: 0.27137505 | Q13: MAXICHEMICAL | R13: 2250 | S13: 15.934662 | T13: 171851.13 | U13: 35852.989
J14: CARBONATO DE POTASIO LIGERO ROT | K14: 2000 | L14: 8.55571 | M14: 110000 | N14: 17111.42 | O14: 0.15555836 | Q14: CESAR AUGUSTO VEGA MADRID | R14: 1440 | S14: 19.959684 | T14: 117984.7 | U14: 28741.945
J15: ACIDO FOSFORICO CLARIFICADO 85% | K15: 1150 | L15: 13.719647 | M15: 49516.83 | N15: 15777.595 | O15: 0.31863095 | Q15: ECOTERRA N.V. | R15: 1000 | S15: 25.77917 | T15: 65000 | U15: 25779.17
J16: EXXSOL D-40 | K16: 800 | L16: 16.083494 | M16: 55983.36 | N16: 12866.796 | O16: 0.2298325 | Q16: ABASTECEDORA HIGIENICA DE SONORA | R16: 3220 | S16: 7.0291894 | T16: 115400 | U16: 22633.99
J17: LESS 28% | K17: 2500 | L17: 4.469068 | M17: 45990 | N17: 11172.67 | O17: 0.24293694 | Q17: QMX4 | R17: 1440 | S17: 13.637488 | T17: 106986.18 | U17: 19637.983
J18: NONIL FENOL 10 MOLES | K18: 880 | L18: 11.955272 | M18: 53680 | N18: 10520.64 | O18: 0.19598807 | Q18: LABORATORIOS AEQ | R18: 1710 | S18: 9.6712238 | T18: 126239.7 | U18: 16537.793
J19: EDTA | K19: 475 | L19: 19.844274 | M19: 32650 | N19: 9426.03 | O19: 0.28869923 | Q19: ABQUIM | R19: 720 | S19: 22.815306 | T19: 59796 | U19: 16427.02
... J41: Total general | K41: 80642 | L41: 11.066204 | M41: 4259252 | N41: 892400.81 | O41: 0.20952055 | Q41: LUCINA YARLIN OCHOA QUIÑONEZ | R41: 340 | S41: 12.011176 | T41: 15980 | U41: 4083.7998
Q42: KESECOME ALIMENTARIA | R42: 220 | S42: 16.749227 | T42: 9460 | U42: 3684.8299
Q43: PAPAS RAYGOZA DE CAJEME | R43: 90 | S43: 35.869444 | T43: 8640 | U43: 3228.25
Q44: JESUS FRANCISCO OLMOS CASTRO | R44: 135 | S44: 23.775071 | T44: 11327.26 | U44: 3209.6346
Q45: AGRO PRODUCTOS BALEY | R45: 400 | S45: 7.7997 | T45: 27200 | U45: 3119.88
Q46: INSECTICIDAS DEL PACIFICO | R46: 300 | S46: 8.7894382 | T46: 9738.23 | U46: 2636.8315
Q47: AGROBIOLIFE | R47: 200 | S47: 12.0775 | T47: 8800 | U47: 2415.5
Q48: JESUS ANTONIO PACHECO NIEBLAS | R48: 220 | S48: 10.230545 | T48: 13200 | U48: 2250.7199
Q49: JIMMY JAVIER VITE QUIMIZ | R49: 100 | S49: 21.1492 | T49: 6400 | U49: 2114.92
Q50: ACUICOLA BOCA | R50: 90 | S50: 23.255889 | T50: 7670.7 | U50: 2093.03
Q51: GENITECH | R51: 42 | S51: 48.257143 | T51: 18270 | U51: 2026.8
Q52: JUAN HERMENEGILDO OLIVAS MENDOZA | R52: 180 | S52: 10.69 | T52: 7470 | U52: 1924.2
Q53: JESUS ALEJANDRO GOMEZ ESPINOZA | R53: 170 | S53: 10.751647 | T53: 8160 | U53: 1827.78
... Q63: Total general | R63: 80642 | S63: 11.066204 | T63: 4259252 | U63: 892400.81

Sheet BD Cobranza
A1: Fecha de factura | B1: Número | C1: Cliente | D1: Importe | E1: IVA | F1: Total | G1: Fecha de vencimiento | H1: Estatus | I1: Estado de pago | J1: Fecha último pago | K1: Semana | L1: Vendedor | M1: Términos de pago | N1: Mes | O1: Semana | Q1: SE BAJA TODO EL MES | S1: ILSE GARCIA | U1: CREDITO
A2: 46199 | B2: HMO/2026/00454 | C2: "PUBLICO EN GENERAL" | D2: 70200 | E2: 11232 | F2: 81432 | G2: 46199 | H2: Vigente | I2: Pagado | J2: 46199 | K2: Semana 4 | L2: ILSE GARCÍA | M2: Contado | N2: =MONTH(J2) -> 6 | O2: =WEEKNUM(J2) -> 26
A3: 46199 | B3: HMO/2026/00453 | C3: "PUBLICO EN GENERAL" | D3: 70200 | E3: 11232 | F3: 81432 | G3: 46199 | H3: Vigente | I3: Pagado | J3: 46199 | K3: Semana 4 | L3: ILSE GARCÍA | M3: Contado | N3: =MONTH(J3) -> 6 | O3: =WEEKNUM(J3) -> 26
A4: 46199 | B4: HMO/2026/00452 | C4: "PUBLICO EN GENERAL" | D4: 35100 | E4: 5616 | F4: 40716 | G4: 46199 | H4: Vigente | I4: Pagado | J4: 46199 | K4: Semana 4 | L4: ILSE GARCÍA | M4: Contado | N4: =MONTH(J4) -> 6 | O4: =WEEKNUM(J4) -> 26
A5: 46199 | B5: HMO/2026/00451 | C5: "PUBLICO EN GENERAL" | D5: 58000 | E5: 9280 | F5: 67280 | G5: 46199 | H5: Vigente | I5: Pagado | J5: 46199 | K5: Semana 4 | L5: ILSE GARCÍA | M5: Contado | N5: =MONTH(J5) -> 6 | O5: =WEEKNUM(J5) -> 26
A6: 46198 | B6: HMO/2026/00447 | C6: SAUL AYON REYNA | D6: 70200 | E6: 11232 | F6: 81432 | G6: 46198 | H6: Vigente | I6: Pagado | J6: 46198 | K6: Semana 4 | L6: ILSE GARCÍA | M6: Contado | N6: =MONTH(J6) -> 6 | O6: =WEEKNUM(J6) -> 26
A7: 46198 | B7: HMO/2026/00445 | C7: ELIA GABRIELA GARCIA MORALES | D7: 59910 | F7: 59910 | G7: 46198 | H7: Vigente | I7: Pagado | J7: 46198 | K7: Semana 4 | L7: ILSE GARCÍA | M7: Contado | N7: =MONTH(J7) -> 6 | O7: =WEEKNUM(J7) -> 26
A8: 46198 | B8: HMO/2026/00444 | C8: JESUS FRANCISCO OLMOS CASTRO | D8: 11893.5 | E8: 1902.96 | F8: 13796.46 | G8: 46228 | H8: Vigente | I8: Pagado | J8: 46198 | K8: Semana 4 | L8: FREDY SALAS | M8: Crédito | N8: =MONTH(J8) -> 6 | O8: =WEEKNUM(J8) -> 26
A9: 46198 | B9: HMO/2026/00441 | C9: ABEL DANIEL MONTENEGRO IZAGUIRRE | D9: 14866.2 | E9: 2378.59 | F9: 17244.79 | G9: 46198 | H9: Vigente | I9: Pagado | J9: 46198 | K9: Semana 4 | L9: ILSE GARCÍA | M9: Contado | N9: =MONTH(J9) -> 6 | O9: =WEEKNUM(J9) -> 26
A10: 46197 | B10: CLN/2026/00161 | C10: "PUBLICO EN GENERAL" | D10: 2500 | E10: 400 | F10: 2900 | G10: 46197 | H10: Vigente | I10: Pagado | J10: 46196 | K10: Semana 4 | L10: MATEO LÓPEZ | M10: Contado | N10: =MONTH(J10) -> 6 | O10: =WEEKNUM(J10) -> 26
A11: 46197 | B11: CLN/2026/00160 | C11: "PUBLICO EN GENERAL" | D11: 2750 | E11: 440 | F11: 3190 | G11: 46197 | H11: Vigente | I11: Pagado | J11: 46195 | K11: Semana 4 | L11: FREDY SALAS | M11: Contado | N11: =MONTH(J11) -> 6 | O11: =WEEKNUM(J11) -> 26
A12: 46196 | B12: CLN/2026/00159 | C12: ACUICOLA MOREMAR | D12: 11407.5 | E12: 1825.2 | F12: 13232.7 | G12: 46196 | H12: Vigente | I12: Pagado | J12: 46196 | K12: Semana 4 | L12: MATEO LÓPEZ | M12: Contado | N12: =MONTH(J12) -> 6 | O12: =WEEKNUM(J12) -> 26
A13: 46196 | B13: CLN/2026/00158 | C13: GRANJA ACUICOLA MAYA | D13: 11407.5 | E13: 1825.2 | F13: 13232.7 | G13: 46196 | H13: Vigente | I13: Pagado | J13: 46196 | K13: Semana 4 | L13: MATEO LÓPEZ | M13: Contado | N13: =MONTH(J13) -> 6 | O13: =WEEKNUM(J13) -> 26
A14: 46195 | B14: HMO/2026/00432 | C14: ZAYDA CAMILA GARCIA GARCIA | D14: 16320 | E14: 2611.2 | F14: 18931.2 | G14: 46195 | H14: Vigente | I14: Pagado | J14: 46195 | K14: Semana 4 | L14: ILSE GARCÍA | M14: Contado | N14: =MONTH(J14) -> 6 | O14: =WEEKNUM(J14) -> 26
A15: 46192 | B15: HMO/2026/00431 | C15: SAUL AYON REYNA | D15: 35100 | E15: 5616 | F15: 40716 | G15: 46222 | H15: Vigente | I15: Pagado | J15: 46192 | K15: Semana 3 | L15: ILSE GARCÍA | M15: Crédito | N15: =MONTH(J15) -> 6 | O15: =WEEKNUM(J15) -> 25
A16: 46192 | B16: HMO/2026/00430 | C16: "PUBLICO EN GENERAL" | D16: 70200 | E16: 11232 | F16: 81432 | G16: 46192 | H16: Vigente | I16: Pagado | J16: 46192 | K16: Semana 3 | L16: ILSE GARCÍA | M16: Contado | N16: =MONTH(J16) -> 6 | O16: =WEEKNUM(J16) -> 25
A17: 46192 | B17: HMO/2026/00429 | C17: "PUBLICO EN GENERAL" | D17: 70200 | E17: 11232 | F17: 81432 | G17: 46192 | H17: Vigente | I17: Pagado | J17: 46192 | K17: Semana 3 | L17: ILSE GARCÍA | M17: Contado | N17: =MONTH(J17) -> 6 | O17: =WEEKNUM(J17) -> 25
A18: 46192 | B18: HMO/2026/00428 | C18: SAUL AYON REYNA | D18: 63180 | E18: 10108.8 | F18: 73288.8 | G18: 46192 | H18: Vigente | I18: Pagado | J18: 46192 | K18: Semana 3 | L18: ILSE GARCÍA | M18: Contado | N18: =MONTH(J18) -> 6 | O18: =WEEKNUM(J18) -> 25
A19: 46190 | B19: HMO/2026/00420 | C19: ABEL DANIEL MONTENEGRO IZAGUIRRE | D19: 7433.1 | E19: 1189.3 | F19: 8622.4 | G19: 46190 | H19: Vigente | I19: Pagado | J19: 46190 | K19: Semana 3 | L19: ILSE GARCÍA | M19: Contado | N19: =MONTH(J19) -> 6 | O19: =WEEKNUM(J19) -> 25
... A74: 46150 | B74: CLN/2026/00122 | C74: RENACER 2001 | D74: 112200 | E74: 17952 | F74: 130152 | G74: 46180 | H74: Vigente | I74: Pagado | J74: 46192 | K74: Semana 3 | L74: ILSE GARCÍA | M74: Crédito | N74: =MONTH(J74) -> 6 | O74: =WEEKNUM(J74) -> 25
A75: 46149 | B75: HMO/2026/00320 | C75: AGROPECUARIA MONTE SINAI | D75: 20000 | F75: 20000 | G75: 46179 | H75: Vigente | I75: Pagado | J75: 46188 | K75: Semana 3 | L75: ILSE GARCÍA | M75: Crédito | N75: =MONTH(J75) -> 6 | O75: =WEEKNUM(J75) -> 25
A76: 46149 | B76: HMO/2026/00319 | C76: AGROPECUARIA MONTE SINAI | D76: 4600 | F76: 4600 | G76: 46179 | H76: Vigente | I76: Pagado | J76: 46188 | K76: Semana 3 | L76: ILSE GARCÍA | M76: Crédito | N76: =MONTH(J76) -> 6 | O76: =WEEKNUM(J76) -> 25
A77: 46149 | B77: CLN/2026/00121 | C77: JESUS ESTEBAN CHAVEZ PRECIADO | D77: 30600 | E77: 4896 | F77: 35496 | G77: 46179 | H77: Vigente | I77: Pagado | J77: 46188 | K77: Semana 3 | L77: MATEO LÓPEZ | M77: Crédito | N77: =MONTH(J77) -> 6 | O77: =WEEKNUM(J77) -> 25
A78: 46148 | B78: HMO/2026/00316 | C78: QMX4 | D78: 38940 | E78: 6230.4 | F78: 45170.4 | G78: 46178 | H78: Vigente | I78: Pagado | J78: 46192 | K78: Semana 3 | L78: FREDY SALAS | M78: Crédito | N78: =MONTH(J78) -> 6 | O78: =WEEKNUM(J78) -> 25
A79: 46147 | B79: HMO/2026/00312 | C79: JESUS ALFREDO AYON REYNA | D79: 68400 | E79: 10944 | F79: 79344 | G79: 46177 | H79: Vigente | I79: Pagado | J79: 46177 | K79: Semana 1 | L79: ILSE GARCÍA | M79: Crédito | N79: =MONTH(J79) -> 6 | O79: =WEEKNUM(J79) -> 23
A80: 46147 | B80: CLN/2026/00119 | C80: SEILSIN/PROVELIM | D80: 17050 | E80: 2728 | F80: 19778 | G80: 46177 | H80: Vigente | I80: Pagado | J80: 46192 | K80: Semana 3 | L80: ILSE GARCÍA | M80: Crédito | N80: =MONTH(J80) -> 6 | O80: =WEEKNUM(J80) -> 25
A81: 46146 | B81: HMO/2026/00305 | C81: AGROPECUARIA MONTE SINAI | D81: 12608.5 | F81: 12608.5 | G81: 46176 | H81: Vigente | I81: Pagado | J81: 46189 | K81: Semana 3 | L81: ILSE GARCÍA | M81: Crédito | N81: =MONTH(J81) -> 6 | O81: =WEEKNUM(J81) -> 25
A82: 46141 | B82: HMO/2026/00300 | C82: EDITH CABRERA GARCIA | D82: 9000 | E82: 1440 | F82: 10440 | G82: 46171 | H82: vencido | I82: Pagado | J82: 46189 | K82: Semana 3 | L82: ILSE GARCÍA | M82: Crédito | N82: =MONTH(J82) -> 6 | O82: =WEEKNUM(J82) -> 25
A83: 46140 | B83: HMO/2026/00291 | C83: LABORATORIOS AEQ | D83: 11264.7 | E83: 1802.35 | F83: 13067.05 | G83: 46170 | H83: vencido | I83: Pagado | J83: 46178 | K83: Semana 1 | L83: ILSE GARCÍA | M83: Crédito | N83: =MONTH(J83) -> 6 | O83: =WEEKNUM(J83) -> 23
A84: 46140 | B84: CLN/2026/00113 | C84: JESUS ESTEBAN CHAVEZ PRECIADO | D84: 30600 | E84: 4896 | F84: 35496 | G84: 46170 | H84: vencido | I84: Pagado | J84: 46181 | K84: Semana 2 | L84: MATEO LÓPEZ | M84: Crédito | N84: =MONTH(J84) -> 6 | O84: =WEEKNUM(J84) -> 24
A85: 46139 | B85: HMO/2026/00283 | C85: JESUS ALEJANDRO GOMEZ ESPINOZA | D85: 8160 | E85: 1305.6 | F85: 9465.6 | G85: 46169 | H85: vencido | I85: Pagado | J85: 46175 | K85: Semana 1 | L85: ILSE GARCÍA | M85: Crédito | N85: =MONTH(J85) -> 6 | O85: =WEEKNUM(J85) -> 23
A86: 46136 | B86: HMO/2026/00278 | C86: PROQUISON | D86: 3749.48 | E86: 599.92 | F86: 4349.4 | G86: 46166 | H86: vencido | I86: Pagado | J86: 46177 | K86: Semana 1 | L86: FREDY SALAS | M86: Crédito | N86: =MONTH(J86) -> 6 | O86: =WEEKNUM(J86) -> 23
A87: 46136 | B87: HMO/2026/00273 | C87: PROQUISON | D87: 3195 | E87: 511.2 | F87: 3706.2 | G87: 46166 | H87: vencido | I87: Pagado | J87: 46177 | K87: Semana 1 | L87: FREDY SALAS | M87: Crédito | N87: =MONTH(J87) -> 6 | O87: =WEEKNUM(J87) -> 23
A88: 46134 | B88: HMO/2026/00265 | C88: PINTURAS DE CAJEME | D88: 12400 | E88: 1984 | F88: 14384 | G88: 46164 | H88: vencido | I88: Pagado | J88: 46177 | K88: Semana 1 | L88: ILSE GARCÍA | M88: Crédito | N88: =MONTH(J88) -> 6 | O88: =WEEKNUM(J88) -> 23
A89: 46132 | B89: HMO/2026/00260 | C89: EULALIO MOLINA TERAN | D89: 27360 | E89: 4377.6 | F89: 31737.6 | G89: 46162 | H89: vencido | I89: Pagado | J89: 46183 | K89: Semana 2 | L89: ILSE GARCÍA | M89: Crédito | N89: =MONTH(J89) -> 6 | O89: =WEEKNUM(J89) -> 24
A90: 46121 | B90: CLN/2026/00093 | C90: AQUASTORE SUMINISTROS ACUICOLAS DEL PACIFICO | D90: 36050.5 | E90: 5768.08 | F90: 41818.58 | G90: 46151 | H90: vencido | I90: Pagado | J90: 46178 | K90: Semana 1 | L90: MATEO LÓPEZ | M90: Crédito | N90: =MONTH(J90) -> 6 | O90: =WEEKNUM(J90) -> 23
A91: 46108 | B91: HMO/2026/00195 | C91: EULALIO MOLINA TERAN | D91: 4750 | E91: 760 | F91: 5510 | G91: 46138 | H91: vencido | I91: Pagado | J91: 46183 | K91: Semana 2 | L91: ILSE GARCÍA | M91: Crédito | N91: =MONTH(J91) -> 6 | O91: =WEEKNUM(J91) -> 24
A92: 46094 | B92: HMO/2026/00167 | C92: EULALIO MOLINA TERAN | D92: 27360 | E92: 4377.6 | F92: 31737.6 | G92: 46124 | H92: vencido | I92: Pagado | J92: 46183 | K92: Semana 2 | L92: ILSE GARCÍA | M92: Crédito | N92: =MONTH(J92) -> 6 | O92: =WEEKNUM(J92) -> 24
A93: 45814 | B93: CLN/2025/00282 | C93: JESUS FRANCISCO OLMOS CASTRO | D93: 19012.5 | E93: 3042 | F93: 22054.5 | G93: 45844 | H93: vencido | I93: Pagado | J93: 46198 | K93: Semana 4 | L93: FREDY SALAS | M93: Crédito | N93: =MONTH(J93) -> 6 | O93: =WEEKNUM(J93) -> 26
... A107: 46162 | B107: HMO/2026/00344 | C107: ALBA CIRA APODACA SOLIS | D107: 8330 | E107: 1332.8 | F107: 9662.8 | G107: 46162 | H107: Vigente | I107: Pagado | J107: 46161 | K107: Semana 3 | L107: ILSE GARCÍA | M107: Contado | N107: =MONTH(J107) -> 5 | O107: =WEEKNUM(J107) -> 21
A108: 46162 | B108: HMO/2026/00343 | C108: ACUAGRO | D108: 75264 | F108: 75264 | G108: 46162 | H108: Vigente | I108: Pagado | J108: 46170 | K108: Semana 4 | L108: ILSE GARCÍA | M108: Contado | N108: =MONTH(J108) -> 5 | O108: =WEEKNUM(J108) -> 22
A109: 46161 | B109: HMO/2026/00341 | C109: ACUAGRO | D109: 57000 | F109: 57000 | G109: 46161 | H109: Vigente | I109: Pagado | J109: 46170 | K109: Semana 4 | L109: ILSE GARCÍA | M109: Contado | N109: =MONTH(J109) -> 5 | O109: =WEEKNUM(J109) -> 22
A110: 46161 | B110: HMO/2026/00340 | C110: LABORATORIOS ARDSON | D110: 10200 | E110: 1632 | F110: 11832 | G110: 46191 | H110: Vigente | I110: Pagado | J110: 46163 | K110: Semana 3 | L110: ILSE GARCÍA | M110: Crédito | N110: =MONTH(J110) -> 5 | O110: =WEEKNUM(J110) -> 21
A111: 46161 | B111: CLN/2026/00130 | C111: ALKEM INDUSTRIAS | D111: 38908.8 | E111: 6225.41 | F111: 45134.21 | G111: 46161 | H111: Vigente | I111: Pagado | J111: 46162 | K111: Semana 3 | L111: MATEO LÓPEZ | M111: Contado | N111: =MONTH(J111) -> 5 | O111: =WEEKNUM(J111) -> 21
A112: 46160 | B112: HMO/2026/00339 | C112: ZAYDA CAMILA GARCIA GARCIA | D112: 16320 | E112: 2611.2 | F112: 18931.2 | G112: 46160 | H112: Vigente | I112: Pagado | J112: 46160 | K112: Semana 3 | L112: ILSE GARCÍA | M112: Contado | N112: =MONTH(J112) -> 5 | O112: =WEEKNUM(J112) -> 21
A113: 46160 | B113: HMO/2026/00336 | C113: JUAN HERMENEGILDO OLIVAS MENDOZA | D113: 16200 | E113: 2592 | F113: 18792 | G113: 46160 | H113: Vigente | I113: Pagado | J113: 46171 | K113: Semana 4 | L113: ILSE GARCÍA | M113: Contado | N113: =MONTH(J113) -> 5 | O113: =WEEKNUM(J113) -> 22
A114: 46160 | B114: CLN/2026/00128 | C114: JESUS FRANCISCO OLMOS CASTRO | D114: 15660 | E114: 2505.6 | F114: 18165.6 | G114: 46190 | H114: Vigente | I114: Pagado | J114: 46160 | K114: Semana 3 | L114: FREDY SALAS | M114: Crédito | N114: =MONTH(J114) -> 5 | O114: =WEEKNUM(J114) -> 21
A115: 46157 | B115: HMO/2026/00329 | C115: ABEL LOPEZ ROJO | D115: 3622.5 | E115: 579.6 | F115: 4202.1 | G115: 46157 | H115: Vigente | I115: Pagado | J115: 46155 | K115: Semana 2 | L115: ILSE GARCÍA | M115: Contado | N115: =MONTH(J115) -> 5 | O115: =WEEKNUM(J115) -> 20
A116: 46155 | B116: HMO/2026/00326 | C116: ABASTECEDORA HIGIENICA DE SONORA | D116: 12809.61 | E116: 2049.54 | F116: 14859.15 | G116: 46185 | H116: Vigente | I116: Pagado | J116: 46168 | K116: Semana 4 | L116: ILSE GARCÍA | M116: Crédito | N116: =MONTH(J116) -> 5 | O116: =WEEKNUM(J116) -> 22
A117: 46155 | B117: HMO/2026/00325 | C117: PINTURAS DE CAJEME | D117: 40000 | E117: 6400 | F117: 46400 | G117: 46185 | H117: Vigente | I117: Pagado | J117: 46155 | K117: Semana 2 | L117: ILSE GARCÍA | M117: Crédito | N117: =MONTH(J117) -> 5 | O117: =WEEKNUM(J117) -> 20
A118: 46155 | B118: HMO/2026/00323 | C118: ZAYDA CAMILA GARCIA GARCIA | D118: 16320 | E118: 2611.2 | F118: 18931.2 | G118: 46155 | H118: Vigente | I118: Pagado | J118: 46153 | K118: Semana 2 | L118: ILSE GARCÍA | M118: Contado | N118: =MONTH(J118) -> 5 | O118: =WEEKNUM(J118) -> 20
A119: 46154 | B119: CLN/2026/00125 | C119: ALKEM INDUSTRIAS | D119: 38679.3 | E119: 6188.69 | F119: 44867.99 | G119: 46154 | H119: Vigente | I119: Pagado | J119: 46154 | K119: Semana 2 | L119: MATEO LÓPEZ | M119: Contado | N119: =MONTH(J119) -> 5 | O119: =WEEKNUM(J119) -> 20
A120: 46150 | B120: HMO/2026/00322 | C120: SAUL AYON REYNA | D120: 59040 | E120: 9446.4 | F120: 68486.4 | G120: 46180 | H120: Vigente | I120: Pagado | J120: 46169 | K120: Semana 4 | L120: ILSE GARCÍA | M120: Crédito | N120: =MONTH(J120) -> 5 | O120: =WEEKNUM(J120) -> 22
A121: 46150 | B121: HMO/2026/00321 | C121: ABASTECEDORA HIGIENICA DE SONORA | D121: 12980 | E121: 2076.8 | F121: 15056.8 | G121: 46180 | H121: Vigente | I121: Pagado | J121: 46168 | K121: Semana 4 | L121: ILSE GARCÍA | M121: Crédito | N121: =MONTH(J121) -> 5 | O121: =WEEKNUM(J121) -> 22
... A128: 46146 | B128: CLN/2026/00118 | C128: JIMMY JAVIER VITE QUIMIZ | D128: 3150 | E128: 504 | F128: 3654 | G128: 46146 | H128: Vigente | I128: Pagado | J128: 46154 | K128: Semana 2 | L128: MATEO LÓPEZ | M128: Contado | N128: =MONTH(J128) -> 5 | O128: =WEEKNUM(J128) -> 20
A129: 46146 | B129: CLN/2026/00117 | C129: ELIA GABRIELA GARCIA MORALES | D129: 709944 | F129: 709944 | G129: 46146 | H129: Vigente | I129: Revertido | J129: 46146 | K129: Semana 1 | L129: ILSE GARCÍA | M129: Contado | N129: =MONTH(J129) -> 5 | O129: =WEEKNUM(J129) -> 19
A130: 46142 | B130: HMO/2026/00304 | C130: SAUL AYON REYNA | D130: 54720 | E130: 8755.2 | F130: 63475.2 | G130: 46172 | H130: Vigente | I130: Pagado | J130: 46165 | K130: Semana 4 | L130: ILSE GARCÍA | M130: Crédito | N130: =MONTH(J130) -> 5 | O130: =WEEKNUM(J130) -> 21
A131: 46142 | B131: CLN/2026/00116 | C131: WALBRO LOS MOCHIS | D131: 55983.36 | E131: 8957.34 | F131: 64940.7 | G131: 46172 | H131: Vigente | I131: Pagado | J131: 46171 | K131: Semana 4 | L131: ILSE GARCÍA | M131: Crédito | N131: =MONTH(J131) -> 5 | O131: =WEEKNUM(J131) -> 22
A132: 46141 | B132: HMO/2026/00303 | C132: JESUS ALFREDO AYON REYNA | D132: 48780 | E132: 7804.8 | F132: 56584.8 | G132: 46171 | H132: Vigente | I132: Pagado | J132: 46157 | K132: Semana 2 | L132: ILSE GARCÍA | M132: Crédito | N132: =MONTH(J132) -> 5 | O132: =WEEKNUM(J132) -> 20
A133: 46141 | B133: HMO/2026/00297 | C133: ABASTECEDORA HIGIENICA DE SONORA | D133: 55240 | E133: 8838.4 | F133: 64078.4 | G133: 46171 | H133: Vigente | I133: Pagado | J133: 46168 | K133: Semana 4 | L133: ILSE GARCÍA | M133: Crédito | N133: =MONTH(J133) -> 5 | O133: =WEEKNUM(J133) -> 22
A134: 46140 | B134: HMO/2026/00292 | C134: MARIA DEL CARMEN RIVERA QUINTERO | D134: 13500 | E134: 2160 | F134: 15660 | G134: 46170 | H134: Vigente | I134: Pagado | J134: 46169 | K134: Semana 4 | L134: FREDY SALAS | M134: Crédito | N134: =MONTH(J134) -> 5 | O134: =WEEKNUM(J134) -> 22
A135: 46140 | B135: HMO/2026/00290 | C135: ABQUIM | D135: 59796 | E135: 9567.36 | F135: 69363.36 | G135: 46155 | H135: Vigente | I135: Pagado | J135: 46171 | K135: Semana 4 | L135: FREDY SALAS | M135: Crédito | N135: =MONTH(J135) -> 5 | O135: =WEEKNUM(J135) -> 22
A136: 46139 | B136: HMO/2026/00289 | C136: ABASTECEDORA HIGIENICA DE SONORA | D136: 34200 | E136: 5472 | F136: 39672 | G136: 46169 | H136: Vigente | I136: Pagado | J136: 46168 | K136: Semana 4 | L136: ILSE GARCÍA | M136: Crédito | N136: =MONTH(J136) -> 5 | O136: =WEEKNUM(J136) -> 22
A137: 46139 | B137: CLN/2026/00111 | C137: JULIO CESAR SEPULVEDA LOPEZ | D137: 56392.85 | E137: 9022.86 | F137: 65415.71 | G137: 46169 | H137: Vigente | I137: Pagado | J137: 46171 | K137: Semana 4 | L137: FREDY SALAS | M137: Crédito | N137: =MONTH(J137) -> 5 | O137: =WEEKNUM(J137) -> 22
A138: 46137 | B138: HMO/2026/00282 | C138: SAUL AYON REYNA | D138: 6840 | E138: 1094.4 | F138: 7934.4 | G138: 46167 | H138: Vigente | I138: Pagado | J138: 46160 | K138: Semana 3 | L138: ILSE GARCÍA | M138: Crédito | N138: =MONTH(J138) -> 5 | O138: =WEEKNUM(J138) -> 21
A139: 46137 | B139: HMO/2026/00281 | C139: HECTOR SAU ESPINOZA | D139: 4050 | E139: 648 | F139: 4698 | G139: 46167 | H139: Vigente | I139: Pagado | J139: 46170 | K139: Semana 4 | L139: ILSE GARCÍA | M139: Crédito | N139: =MONTH(J139) -> 5 | O139: =WEEKNUM(J139) -> 22
A140: 46137 | B140: HMO/2026/00280 | C140: INSECTICIDAS DEL PACIFICO | D140: 9738.23 | E140: 1558.12 | F140: 11296.35 | G140: 46167 | H140: Vigente | I140: Pagado | J140: 46169 | K140: Semana 4 | L140: ILSE GARCÍA | M140: Crédito | N140: =MONTH(J140) -> 5 | O140: =WEEKNUM(J140) -> 22
A141: 46136 | B141: CLN/2026/00108 | C141: AQUASTORE SUMINISTROS ACUICOLAS DEL PACIFICO | D141: 12600 | E141: 2016 | F141: 14616 | G141: 46166 | H141: Vigente | I141: Pagado | J141: 46171 | K141: Semana 4 | L141: MATEO LÓPEZ | M141: Crédito | N141: =MONTH(J141) -> 5 | O141: =WEEKNUM(J141) -> 22
... A148: 46132 | B148: CLN/2026/00101 | C148: AQUASTORE SUMINISTROS ACUICOLAS DEL PACIFICO | D148: 12600 | E148: 2016 | F148: 14616 | G148: 46162 | H148: Vigente | I148: Pagado | J148: 46169 | K148: Semana 4 | L148: MATEO LÓPEZ | M148: Crédito | N148: =MONTH(J148) -> 5 | O148: =WEEKNUM(J148) -> 22
A149: 46130 | B149: HMO/2026/00259 | C149: AGROPECUARIA MONTE SINAI | D149: 13904.2 | F149: 13904.2 | G149: 46160 | H149: Vigente | I149: Pagado | J149: 46162 | K149: Semana 3 | L149: ILSE GARCÍA | M149: Crédito | N149: =MONTH(J149) -> 5 | O149: =WEEKNUM(J149) -> 21
A150: 46129 | B150: HMO/2026/00255 | C150: JESUS ALFREDO AYON REYNA | D150: 48780 | E150: 7804.8 | F150: 56584.8 | G150: 46159 | H150: Vigente | I150: Pagado | J150: 46147 | K150: Semana 1 | L150: ILSE GARCÍA | M150: Crédito | N150: =MONTH(J150) -> 5 | O150: =WEEKNUM(J150) -> 19
A151: 46129 | B151: HMO/2026/00254 | C151: FERRO MATERIALES CABANILLAS | D151: 4318.08 | E151: 690.89 | F151: 5008.97 | G151: 46159 | H151: Vigente | I151: Pagado | J151: 46167 | K151: Semana 4 | L151: ILSE GARCÍA | M151: Crédito | N151: =MONTH(J151) -> 5 | O151: =WEEKNUM(J151) -> 22
A152: 46129 | B152: HMO/2026/00253 | C152: PORCICULTORES DE CAJEME | D152: 25560 | E152: 4089.6 | F152: 29649.6 | G152: 46159 | H152: Vigente | I152: Pagado | J152: 46160 | K152: Semana 3 | L152: FREDY SALAS | M152: Crédito | N152: =MONTH(J152) -> 5 | O152: =WEEKNUM(J152) -> 21
A153: 46128 | B153: HMO/2026/00252 | C153: ECOTERRA N.V. | D153: 65000 | F153: 65000 | G153: 46158 | H153: Vigente | I153: Pagado | J153: 46165 | K153: Semana 4 | L153: ILSE GARCÍA | M153: Crédito | N153: =MONTH(J153) -> 5 | O153: =WEEKNUM(J153) -> 21
A154: 46128 | B154: HMO/2026/00251 | C154: FERRO MATERIALES CABANILLAS | D154: 7740 | E154: 1238.4 | F154: 8978.4 | G154: 46158 | H154: Vigente | I154: Pagado | J154: 46167 | K154: Semana 4 | L154: ILSE GARCÍA | M154: Crédito | N154: =MONTH(J154) -> 5 | O154: =WEEKNUM(J154) -> 22
A155: 46128 | B155: HMO/2026/00250 | C155: SAUL AYON REYNA | D155: 61560 | E155: 9849.6 | F155: 71409.6 | G155: 46158 | H155: Vigente | I155: Pagado | J155: 46160 | K155: Semana 3 | L155: ILSE GARCÍA | M155: Crédito | N155: =MONTH(J155) -> 5 | O155: =WEEKNUM(J155) -> 21
A156: 46128 | B156: HMO/2026/00249 | C156: AGROPECUARIA MONTE SINAI | D156: 13896.15 | F156: 13896.15 | G156: 46158 | H156: Vigente | I156: Pagado | J156: 46162 | K156: Semana 3 | L156: ILSE GARCÍA | M156: Crédito | N156: =MONTH(J156) -> 5 | O156: =WEEKNUM(J156) -> 21
A157: 46126 | B157: HMO/2026/00244 | C157: LUCINA YARLIN OCHOA QUIÑONEZ | D157: 15980 | E157: 2556.8 | F157: 18536.8 | G157: 46156 | H157: Vigente | I157: Pagado | J157: 46156 | K157: Semana 2 | L157: FREDY SALAS | M157: Crédito | N157: =MONTH(J157) -> 5 | O157: =WEEKNUM(J157) -> 20
A158: 46126 | B158: CLN/2026/00100 | C158: JESUS ESTEBAN CHAVEZ PRECIADO | D158: 30600 | E158: 4896 | F158: 35496 | G158: 46156 | H158: Vigente | I158: Pagado | J158: 46154 | K158: Semana 2 | L158: MATEO LÓPEZ | M158: Crédito | N158: =MONTH(J158) -> 5 | O158: =WEEKNUM(J158) -> 20
A159: 46125 | B159: HMO/2026/00242 | C159: LABORATORIOS AEQ | D159: 114975 | E159: 18396 | F159: 133371 | G159: 46155 | H159: Vigente | I159: Pagado | J159: 46155 | K159: Semana 2 | L159: ILSE GARCÍA | M159: Crédito | N159: =MONTH(J159) -> 5 | O159: =WEEKNUM(J159) -> 20
A160: 46122 | B160: HMO/2026/00239 | C160: SALSAS CASTILLO | D160: 21716.48 | E160: 3474.64 | F160: 25191.12 | G160: 46152 | H160: Vigente | I160: Pagado | J160: 46157 | K160: Semana 2 | L160: ILSE GARCÍA | M160: Crédito | N160: =MONTH(J160) -> 5 | O160: =WEEKNUM(J160) -> 20
A161: 46122 | B161: HMO/2026/00238 | C161: JESUS ANTONIO PACHECO NIEBLAS | D161: 13200 | E161: 2112 | F161: 15312 | G161: 46152 | H161: Vigente | I161: Pagado | J161: 46162 | K161: Semana 3 | L161: ILSE GARCÍA | M161: Crédito | N161: =MONTH(J161) -> 5 | O161: =WEEKNUM(J161) -> 21
A162: 46121 | B162: HMO/2026/00234 | C162: ACUICOLA BOCA | D162: 7670.7 | E162: 1227.31 | F162: 8898.01 | G162: 46151 | H162: Vigente | I162: Pagado | J162: 46150 | K162: Semana 1 | L162: FREDY SALAS | M162: Crédito | N162: =MONTH(J162) -> 5 | O162: =WEEKNUM(J162) -> 19
A163: 46121 | B163: HMO/2026/00232 | C163: ORBEX CHEMICAL | D163: 72101 | E163: 11536.16 | F163: 83637.16 | G163: 46151 | H163: Vigente | I163: Pagado | J163: 46157 | K163: Semana 2 | L163: FREDY SALAS | M163: Crédito | N163: =MONTH(J163) -> 5 | O163: =WEEKNUM(J163) -> 20
A164: 46121 | B164: HMO/2026/00229 | C164: SAUL AYON REYNA | D164: 61560 | E164: 9849.6 | F164: 71409.6 | G164: 46151 | H164: Vigente | I164: Pagado | J164: 46151 | K164: Semana 2 | L164: ILSE GARCÍA | M164: Crédito | N164: =MONTH(J164) -> 5 | O164: =WEEKNUM(J164) -> 19
A165: 46121 | B165: CLN/2026/00094 | C165: SEILSIN/PROVELIM | D165: 12980 | E165: 2076.8 | F165: 15056.8 | G165: 46151 | H165: Vigente | I165: Pagado | J165: 46164 | K165: Semana 3 | L165: ILSE GARCÍA | M165: Crédito | N165: =MONTH(J165) -> 5 | O165: =WEEKNUM(J165) -> 21
A166: 46120 | B166: HMO/2026/00225 | C166: GENITECH | D166: 18270 | F166: 18270 | G166: 46150 | H166: Vigente | I166: Pagado | J166: 46163 | K166: Semana 3 | L166: ILSE GARCÍA | M166: Crédito | N166: =MONTH(J166) -> 5 | O166: =WEEKNUM(J166) -> 21
A167: 46120 | B167: CLN/2026/00092 | C167: ERIC DE JESUS SAAVEDRA BARRON | D167: 2000 | E167: 320 | F167: 2320 | G167: 46150 | H167: Vigente | I167: Pagado | J167: 46150 | K167: Semana 1 | L167: MATEO LÓPEZ | M167: Crédito | N167: =MONTH(J167) -> 5 | O167: =WEEKNUM(J167) -> 19
A168: 46119 | B168: HMO/2026/00224 | C168: YERALDIN CASTRO CADENA | D168: 27000 | E168: 4320 | F168: 31320 | G168: 46149 | H168: Vigente | I168: Pagado | J168: 46155 | K168: Semana 2 | L168: ILSE GARCÍA | M168: Crédito | N168: =MONTH(J168) -> 5 | O168: =WEEKNUM(J168) -> 20
A169: 46119 | B169: HMO/2026/00223 | C169: YERALDIN CASTRO CADENA | D169: 57649.97 | E169: 9224 | F169: 66873.97 | G169: 46149 | H169: Vigente | I169: Pagado | J169: 46156 | K169: Semana 2 | L169: ILSE GARCÍA | M169: Crédito | N169: =MONTH(J169) -> 5 | O169: =WEEKNUM(J169) -> 20
A170: 46118 | B170: HMO/2026/00221 | C170: YERALDIN CASTRO CADENA | D170: 11900 | E170: 1904 | F170: 13804 | G170: 46148 | H170: Vigente | I170: Pagado | J170: 46155 | K170: Semana 2 | L170: ILSE GARCÍA | M170: Crédito | N170: =MONTH(J170) -> 5 | O170: =WEEKNUM(J170) -> 20
A171: 46118 | B171: HMO/2026/00219 | C171: KESECOME ALIMENTARIA | D171: 9460 | E171: 1513.6 | F171: 10973.6 | G171: 46148 | H171: Vigente | I171: Pagado | J171: 46156 | K171: Semana 2 | L171: FREDY SALAS | M171: Crédito | N171: =MONTH(J171) -> 5 | O171: =WEEKNUM(J171) -> 20
A172: 46118 | B172: HMO/2026/00218 | C172: CESAR AUGUSTO VEGA MADRID | D172: 117984.7 | E172: 18877.55 | F172: 136862.25 | G172: 46148 | H172: Vigente | I172: Pagado | J172: 46156 | K172: Semana 2 | L172: ILSE GARCÍA | M172: Crédito | N172: =MONTH(J172) -> 5 | O172: =WEEKNUM(J172) -> 20
A173: 46118 | B173: HMO/2026/00217 | C173: SAUL AYON REYNA | D173: 13680 | E173: 2188.8 | F173: 15868.8 | G173: 46148 | H173: Vigente | I173: Pagado | J173: 46148 | K173: Semana 1 | L173: ILSE GARCÍA | M173: Crédito | N173: =MONTH(J173) -> 5 | O173: =WEEKNUM(J173) -> 19
A174: 46118 | B174: CLN/2026/00089 | C174: MARIA DEL CARMEN RIVERA QUINTERO | D174: 13500 | E174: 2160 | F174: 15660 | G174: 46148 | H174: Vigente | I174: Pagado | J174: 46153 | K174: Semana 2 | L174: FREDY SALAS | M174: Crédito | N174: =MONTH(J174) -> 5 | O174: =WEEKNUM(J174) -> 20
A175: 46118 | B175: CLN/2026/00088 | C175: JESUS ESTEBAN CHAVEZ PRECIADO | D175: 7055 | E175: 1128.8 | F175: 8183.8 | G175: 46148 | H175: Vigente | I175: Pagado | J175: 46154 | K175: Semana 2 | L175: MATEO LÓPEZ | M175: Crédito | N175: =MONTH(J175) -> 5 | O175: =WEEKNUM(J175) -> 20
A176: 46113 | B176: HMO/2026/00216 | C176: AQUASTORE SUMINISTROS ACUICOLAS DEL PACIFICO | D176: 11180.05 | E176: 1788.81 | F176: 12968.86 | G176: 46143 | H176: Vigente | I176: Pagado | J176: 46170 | K176: Semana 4 | L176: MATEO LÓPEZ | M176: Crédito | N176: =MONTH(J176) -> 5 | O176: =WEEKNUM(J176) -> 22
A177: 46113 | B177: HMO/2026/00215 | C177: PROGENMAR | D177: 88550 | F177: 88550 | G177: 46143 | H177: Vigente | I177: Pagado | J177: 46162 | K177: Semana 3 | L177: ILSE GARCÍA | M177: Crédito | N177: =MONTH(J177) -> 5 | O177: =WEEKNUM(J177) -> 21
A178: 46112 | B178: HMO/2026/00214 | C178: COMERCIALIZADORA COSTA BELLA | D178: 12600 | E178: 2016 | F178: 14616 | G178: 46142 | H178: Vencido | I178: Pagado | J178: 46146 | K178: Semana 1 | L178: ILSE GARCÍA | M178: Crédito | N178: =MONTH(J178) -> 5 | O178: =WEEKNUM(J178) -> 19
A179: 46112 | B179: HMO/2026/00213 | C179: YERALDIN CASTRO CADENA | D179: 9000 | E179: 1440 | F179: 10440 | G179: 46142 | H179: Vencido | I179: Pagado | J179: 46155 | K179: Semana 2 | L179: ILSE GARCÍA | M179: Crédito | N179: =MONTH(J179) -> 5 | O179: =WEEKNUM(J179) -> 20
...

Sheet BD Cartera
A1: Fecha de factura | B1: Número | C1: Clientes | D1: Importe | E1: IVA | F1: Total | G1: Total pendiente | H1: Importe pendiente | I1: Fecha de vencimiento | J1: Estatus | K1: Estado de pago | L1: Vendedor | M1: Términos de pago | N1: Fecha | O1: Mes | P1: Semana | Q1: Dias vencido | R1: Vencido 0-30 días | S1: Vencido 31-60 días | T1: Vencido 61-90 días | U1: Vencido >90 días | V1: Por vencer | W1: Vigente | Y1: ILSE GARCIA | AA1: CRÉDITO
A2: 46199 | B2: CLN/2026/00163 | C2: GRUBOSA COMERCIAL | D2: 8160 | E2: 1305.6 | F2: 9465.6 | G2: 9465.6 | H2: =D2 -> 8160 | I2: 46229 | J2: Vigente | K2: Sin pagar | L2: MATEO LÓPEZ | M2: Crédito | N2: 46199 | O2: =MONTH(N2) -> 6 | P2: =WEEKNUM(N2) -> 26 | Q2: =IF(J2="Vencido",N2-I2+1,0) -> 0 | R2: =IF(Q2>0,IF(Q2<31,H2,0),0) -> 0 | S2: =IF(Q2>30,IF(Q2<61,H2,0),0) -> 0 | T2: =IF(Q2>60,IF(Q2<91,H2,0),0) -> 0 | U2: =IF(Q2>90,H2,0) -> 0 | V2: =IF(J2="Por vencer",H2,0) -> 0 | W2: =IF(J2="Vigente",H2,0) -> 8160
A3: 46198 | B3: HMO/2026/00446 | C3: JESUS ALFREDO AYON REYNA | D3: 60480 | E3: 9676.8 | F3: 70156.8 | G3: 70156.8 | H3: =D3 -> 60480 | I3: 46228 | J3: Vigente | K3: Sin pagar | L3: ILSE GARCÍA | M3: Crédito | N3: 46199 | O3: =MONTH(N3) -> 6 | P3: =WEEKNUM(N3) -> 26 | Q3: =IF(J3="Vencido",N3-I3+1,0) -> 0 | R3: =IF(Q3>0,IF(Q3<31,H3,0),0) -> 0 | S3: =IF(Q3>30,IF(Q3<61,H3,0),0) -> 0 | T3: =IF(Q3>60,IF(Q3<91,H3,0),0) -> 0 | U3: =IF(Q3>90,H3,0) -> 0 | V3: =IF(J3="Por vencer",H3,0) -> 0 | W3: =IF(J3="Vigente",H3,0) -> 60480
A4: 46198 | B4: HMO/2026/00442 | C4: ALTERA PUBLICIDAD | D4: 83689.2 | E4: 13390.27 | F4: 97079.47 | G4: 97079.47 | H4: =D4 -> 83689.2 | I4: 46243 | J4: Vigente | K4: Sin pagar | L4: ILSE GARCÍA | M4: Crédito | N4: 46199 | O4: =MONTH(N4) -> 6 | P4: =WEEKNUM(N4) -> 26 | Q4: =IF(J4="Vencido",N4-I4+1,0) -> 0 | R4: =IF(Q4>0,IF(Q4<31,H4,0),0) -> 0 | S4: =IF(Q4>30,IF(Q4<61,H4,0),0) -> 0 | T4: =IF(Q4>60,IF(Q4<91,H4,0),0) -> 0 | U4: =IF(Q4>90,H4,0) -> 0 | V4: =IF(J4="Por vencer",H4,0) -> 0 | W4: =IF(J4="Vigente",H4,0) -> 83689.2
A5: 46198 | B5: CLN/2026/00162 | C5: AGRO PRODUCTOS BALEY | D5: 13600 | E5: 2176 | F5: 15776 | G5: 15776 | H5: =D5 -> 13600 | I5: 46228 | J5: Vigente | K5: Sin pagar | L5: MATEO LÓPEZ | M5: Crédito | N5: 46199 | O5: =MONTH(N5) -> 6 | P5: =WEEKNUM(N5) -> 26 | Q5: =IF(J5="Vencido",N5-I5+1,0) -> 0 | R5: =IF(Q5>0,IF(Q5<31,H5,0),0) -> 0 | S5: =IF(Q5>30,IF(Q5<61,H5,0),0) -> 0 | T5: =IF(Q5>60,IF(Q5<91,H5,0),0) -> 0 | U5: =IF(Q5>90,H5,0) -> 0 | V5: =IF(J5="Por vencer",H5,0) -> 0 | W5: =IF(J5="Vigente",H5,0) -> 13600
A6: 46196 | B6: HMO/2026/00440 | C6: PROQUISON | D6: 3195 | E6: 511.2 | F6: 3706.2 | G6: 3706.2 | H6: =D6 -> 3195 | I6: 46226 | J6: Vigente | K6: Sin pagar | L6: FREDY SALAS | M6: Crédito | N6: 46199 | O6: =MONTH(N6) -> 6 | P6: =WEEKNUM(N6) -> 26 | Q6: =IF(J6="Vencido",N6-I6+1,0) -> 0 | R6: =IF(Q6>0,IF(Q6<31,H6,0),0) -> 0 | S6: =IF(Q6>30,IF(Q6<61,H6,0),0) -> 0 | T6: =IF(Q6>60,IF(Q6<91,H6,0),0) -> 0 | U6: =IF(Q6>90,H6,0) -> 0 | V6: =IF(J6="Por vencer",H6,0) -> 0 | W6: =IF(J6="Vigente",H6,0) -> 3195
A7: 46196 | B7: HMO/2026/00439 | C7: JESUS ALFREDO AYON REYNA | D7: 58500 | E7: 9360 | F7: 67860 | G7: 67860 | H7: =D7 -> 58500 | I7: 46226 | J7: Vigente | K7: Sin pagar | L7: ILSE GARCÍA | M7: Crédito | N7: 46199 | O7: =MONTH(N7) -> 6 | P7: =WEEKNUM(N7) -> 26 | Q7: =IF(J7="Vencido",N7-I7+1,0) -> 0 | R7: =IF(Q7>0,IF(Q7<31,H7,0),0) -> 0 | S7: =IF(Q7>30,IF(Q7<61,H7,0),0) -> 0 | T7: =IF(Q7>60,IF(Q7<91,H7,0),0) -> 0 | U7: =IF(Q7>90,H7,0) -> 0 | V7: =IF(J7="Por vencer",H7,0) -> 0 | W7: =IF(J7="Vigente",H7,0) -> 58500
A8: 46196 | B8: HMO/2026/00438 | C8: JESUS ALFREDO AYON REYNA | D8: 58000 | E8: 9280 | F8: 67280 | G8: 67280 | H8: =D8 -> 58000 | I8: 46226 | J8: Vigente | K8: Sin pagar | L8: ILSE GARCÍA | M8: Crédito | N8: 46199 | O8: =MONTH(N8) -> 6 | P8: =WEEKNUM(N8) -> 26 | Q8: =IF(J8="Vencido",N8-I8+1,0) -> 0 | R8: =IF(Q8>0,IF(Q8<31,H8,0),0) -> 0 | S8: =IF(Q8>30,IF(Q8<61,H8,0),0) -> 0 | T8: =IF(Q8>60,IF(Q8<91,H8,0),0) -> 0 | U8: =IF(Q8>90,H8,0) -> 0 | V8: =IF(J8="Por vencer",H8,0) -> 0 | W8: =IF(J8="Vigente",H8,0) -> 58000
A9: 46196 | B9: HMO/2026/00437 | C9: JESUS ALFREDO AYON REYNA | D9: 58000 | E9: 9280 | F9: 67280 | G9: 67280 | H9: =D9 -> 58000 | I9: 46226 | J9: Vigente | K9: Sin pagar | L9: ILSE GARCÍA | M9: Crédito | N9: 46199 | O9: =MONTH(N9) -> 6 | P9: =WEEKNUM(N9) -> 26 | Q9: =IF(J9="Vencido",N9-I9+1,0) -> 0 | R9: =IF(Q9>0,IF(Q9<31,H9,0),0) -> 0 | S9: =IF(Q9>30,IF(Q9<61,H9,0),0) -> 0 | T9: =IF(Q9>60,IF(Q9<91,H9,0),0) -> 0 | U9: =IF(Q9>90,H9,0) -> 0 | V9: =IF(J9="Por vencer",H9,0) -> 0 | W9: =IF(J9="Vigente",H9,0) -> 58000
A10: 46196 | B10: HMO/2026/00436 | C10: JESUS ALFREDO AYON REYNA | D10: 58000 | E10: 9280 | F10: 67280 | G10: 67280 | H10: =D10 -> 58000 | I10: 46226 | J10: Vigente | K10: Sin pagar | L10: ILSE GARCÍA | M10: Crédito | N10: 46199 | O10: =MONTH(N10) -> 6 | P10: =WEEKNUM(N10) -> 26 | Q10: =IF(J10="Vencido",N10-I10+1,0) -> 0 | R10: =IF(Q10>0,IF(Q10<31,H10,0),0) -> 0 | S10: =IF(Q10>30,IF(Q10<61,H10,0),0) -> 0 | T10: =IF(Q10>60,IF(Q10<91,H10,0),0) -> 0 | U10: =IF(Q10>90,H10,0) -> 0 | V10: =IF(J10="Por vencer",H10,0) -> 0 | W10: =IF(J10="Vigente",H10,0) -> 58000
A11: 46196 | B11: HMO/2026/00435 | C11: SEILSIN/PROVELIM | D11: 19470 | E11: 3115.2 | F11: 22585.2 | G11: 22585.2 | H11: =D11 -> 19470 | I11: 46226 | J11: Vigente | K11: Sin pagar | L11: ILSE GARCÍA | M11: Crédito | N11: 46199 | O11: =MONTH(N11) -> 6 | P11: =WEEKNUM(N11) -> 26 | Q11: =IF(J11="Vencido",N11-I11+1,0) -> 0 | R11: =IF(Q11>0,IF(Q11<31,H11,0),0) -> 0 | S11: =IF(Q11>30,IF(Q11<61,H11,0),0) -> 0 | T11: =IF(Q11>60,IF(Q11<91,H11,0),0) -> 0 | U11: =IF(Q11>90,H11,0) -> 0 | V11: =IF(J11="Por vencer",H11,0) -> 0 | W11: =IF(J11="Vigente",H11,0) -> 19470
A12: 46195 | B12: HMO/2026/00433 | C12: EDITH CABRERA GARCIA | D12: 6750 | E12: 1080 | F12: 7830 | G12: 7830 | H12: =D12 -> 6750 | I12: 46225 | J12: Vigente | K12: Sin pagar | L12: ILSE GARCÍA | M12: Crédito | N12: 46199 | O12: =MONTH(N12) -> 6 | P12: =WEEKNUM(N12) -> 26 | Q12: =IF(J12="Vencido",N12-I12+1,0) -> 0 | R12: =IF(Q12>0,IF(Q12<31,H12,0),0) -> 0 | S12: =IF(Q12>30,IF(Q12<61,H12,0),0) -> 0 | T12: =IF(Q12>60,IF(Q12<91,H12,0),0) -> 0 | U12: =IF(Q12>90,H12,0) -> 0 | V12: =IF(J12="Por vencer",H12,0) -> 0 | W12: =IF(J12="Vigente",H12,0) -> 6750
A13: 46192 | B13: HMO/2026/00426 | C13: YERALDIN CASTRO CADENA | D13: 15631.92 | E13: 2501.11 | F13: 18133.03 | G13: 18133.03 | H13: =D13 -> 15631.92 | I13: 46222 | J13: Vigente | K13: Sin pagar | L13: ILSE GARCÍA | M13: Crédito | N13: 46199 | O13: =MONTH(N13) -> 6 | P13: =WEEKNUM(N13) -> 26 | Q13: =IF(J13="Vencido",N13-I13+1,0) -> 0 | R13: =IF(Q13>0,IF(Q13<31,H13,0),0) -> 0 | S13: =IF(Q13>30,IF(Q13<61,H13,0),0) -> 0 | T13: =IF(Q13>60,IF(Q13<91,H13,0),0) -> 0 | U13: =IF(Q13>90,H13,0) -> 0 | V13: =IF(J13="Por vencer",H13,0) -> 0 | W13: =IF(J13="Vigente",H13,0) -> 15631.92
... A45: 46174 | B45: HMO/2026/00369 | C45: "PUBLICO EN GENERAL" | D45: 8000 | E45: 1280 | F45: 9280 | G45: 9280 | H45: =D45 -> 8000 | I45: 46174 | J45: Vencido | K45: Sin pagar | L45: ILSE GARCÍA | M45: Contado | N45: 46199 | O45: =MONTH(N45) -> 6 | P45: =WEEKNUM(N45) -> 26 | Q45: =IF(J45="Vencido",N45-I45+1,0) -> 26 | R45: =IF(Q45>0,IF(Q45<31,H45,0),0) -> 8000 | S45: =IF(Q45>30,IF(Q45<61,H45,0),0) -> 0 | T45: =IF(Q45>60,IF(Q45<91,H45,0),0) -> 0 | U45: =IF(Q45>90,H45,0) -> 0 | V45: =IF(J45="Por vencer",H45,0) -> 0 | W45: =IF(J45="Vigente",H45,0) -> 0
A46: 46171 | B46: CLN/2026/00143 | C46: WALBRO LOS MOCHIS | D46: 381068.6 | E46: 60970.98 | F46: 442039.58 | G46: 2511.59 | H46: =G46/1.16 -> 2165.1638 | I46: 46201 | J46: Por vencer | K46: Pagado parcialmente | L46: ILSE GARCÍA | M46: Crédito | N46: 46199 | O46: =MONTH(N46) -> 6 | P46: =WEEKNUM(N46) -> 26 | Q46: =IF(J46="Vencido",N46-I46+1,0) -> 0 | R46: =IF(Q46>0,IF(Q46<31,H46,0),0) -> 0 | S46: =IF(Q46>30,IF(Q46<61,H46,0),0) -> 0 | T46: =IF(Q46>60,IF(Q46<91,H46,0),0) -> 0 | U46: =IF(Q46>90,H46,0) -> 0 | V46: =IF(J46="Por vencer",H46,0) -> 2165.1638 | W46: =IF(J46="Vigente",H46,0) -> 0
A47: 46170 | B47: HMO/2026/00362 | C47: EULALIO MOLINA TERAN | D47: 42750 | E47: 6840 | F47: 49590 | G47: 49590 | H47: =D47 -> 42750 | I47: 46200 | J47: Por vencer | K47: Sin pagar | L47: ILSE GARCÍA | M47: Crédito | N47: 46199 | O47: =MONTH(N47) -> 6 | P47: =WEEKNUM(N47) -> 26 | Q47: =IF(J47="Vencido",N47-I47+1,0) -> 0 | R47: =IF(Q47>0,IF(Q47<31,H47,0),0) -> 0 | S47: =IF(Q47>30,IF(Q47<61,H47,0),0) -> 0 | T47: =IF(Q47>60,IF(Q47<91,H47,0),0) -> 0 | U47: =IF(Q47>90,H47,0) -> 0 | V47: =IF(J47="Por vencer",H47,0) -> 42750 | W47: =IF(J47="Vigente",H47,0) -> 0
A48: 46170 | B48: CLN/2026/00141 | C48: JESUS ESTEBAN CHAVEZ PRECIADO | D48: 46680 | E48: 7468.8 | F48: 54148.8 | G48: 54148.8 | H48: =D48 -> 46680 | I48: 46200 | J48: Por vencer | K48: Sin pagar | L48: MATEO LÓPEZ | M48: Crédito | N48: 46199 | O48: =MONTH(N48) -> 6 | P48: =WEEKNUM(N48) -> 26 | Q48: =IF(J48="Vencido",N48-I48+1,0) -> 0 | R48: =IF(Q48>0,IF(Q48<31,H48,0),0) -> 0 | S48: =IF(Q48>30,IF(Q48<61,H48,0),0) -> 0 | T48: =IF(Q48>60,IF(Q48<91,H48,0),0) -> 0 | U48: =IF(Q48>90,H48,0) -> 0 | V48: =IF(J48="Por vencer",H48,0) -> 46680 | W48: =IF(J48="Vigente",H48,0) -> 0
A49: 46169 | B49: HMO/2026/00360 | C49: AGROPECUARIA MONTE SINAI | D49: 7015.9 | F49: 7015.9 | G49: 7015.9 | H49: =D49 -> 7015.9 | I49: 46199 | J49: Vencido | K49: Sin pagar | L49: ILSE GARCÍA | M49: Crédito | N49: 46199 | O49: =MONTH(N49) -> 6 | P49: =WEEKNUM(N49) -> 26 | Q49: =IF(J49="Vencido",N49-I49+1,0) -> 1 | R49: =IF(Q49>0,IF(Q49<31,H49,0),0) -> 7015.9 | S49: =IF(Q49>30,IF(Q49<61,H49,0),0) -> 0 | T49: =IF(Q49>60,IF(Q49<91,H49,0),0) -> 0 | U49: =IF(Q49>90,H49,0) -> 0 | V49: =IF(J49="Por vencer",H49,0) -> 0 | W49: =IF(J49="Vigente",H49,0) -> 0
A50: 46169 | B50: HMO/2026/00359 | C50: AGROPECUARIA MONTE SINAI | D50: 20000 | F50: 20000 | G50: 20000 | H50: =D50 -> 20000 | I50: 46199 | J50: Vencido | K50: Sin pagar | L50: ILSE GARCÍA | M50: Crédito | N50: 46199 | O50: =MONTH(N50) -> 6 | P50: =WEEKNUM(N50) -> 26 | Q50: =IF(J50="Vencido",N50-I50+1,0) -> 1 | R50: =IF(Q50>0,IF(Q50<31,H50,0),0) -> 20000 | S50: =IF(Q50>30,IF(Q50<61,H50,0),0) -> 0 | T50: =IF(Q50>60,IF(Q50<91,H50,0),0) -> 0 | U50: =IF(Q50>90,H50,0) -> 0 | V50: =IF(J50="Por vencer",H50,0) -> 0 | W50: =IF(J50="Vigente",H50,0) -> 0
A51: 46169 | B51: CLN/2026/00140 | C51: AGRO PRODUCTOS BALEY | D51: 27200 | E51: 4352 | F51: 31552 | G51: 31552 | H51: =D51 -> 27200 | I51: 46199 | J51: Vencido | K51: Sin pagar | L51: MATEO LÓPEZ | M51: Crédito | N51: 46199 | O51: =MONTH(N51) -> 6 | P51: =WEEKNUM(N51) -> 26 | Q51: =IF(J51="Vencido",N51-I51+1,0) -> 1 | R51: =IF(Q51>0,IF(Q51<31,H51,0),0) -> 27200 | S51: =IF(Q51>30,IF(Q51<61,H51,0),0) -> 0 | T51: =IF(Q51>60,IF(Q51<91,H51,0),0) -> 0 | U51: =IF(Q51>90,H51,0) -> 0 | V51: =IF(J51="Por vencer",H51,0) -> 0 | W51: =IF(J51="Vigente",H51,0) -> 0
A52: 46167 | B52: HMO/2026/00348 | C52: EDITH CABRERA GARCIA | D52: 9000 | E52: 1440 | F52: 10440 | G52: 10440 | H52: =D52 -> 9000 | I52: 46197 | J52: Vencido | K52: Sin pagar | L52: ILSE GARCÍA | M52: Crédito | N52: 46199 | O52: =MONTH(N52) -> 6 | P52: =WEEKNUM(N52) -> 26 | Q52: =IF(J52="Vencido",N52-I52+1,0) -> 3 | R52: =IF(Q52>0,IF(Q52<31,H52,0),0) -> 9000 | S52: =IF(Q52>30,IF(Q52<61,H52,0),0) -> 0 | T52: =IF(Q52>60,IF(Q52<91,H52,0),0) -> 0 | U52: =IF(Q52>90,H52,0) -> 0 | V52: =IF(J52="Por vencer",H52,0) -> 0 | W52: =IF(J52="Vigente",H52,0) -> 0
A53: 46164 | B53: HMO/2026/00347 | C53: NRW CHEMIE MEXICANA | D53: 66167.85 | E53: 10586.86 | F53: 76754.71 | G53: 76754.71 | H53: =D53 -> 66167.85 | I53: 46194 | J53: Vencido | K53: Sin pagar | L53: ILSE GARCÍA | M53: Crédito | N53: 46199 | O53: =MONTH(N53) -> 6 | P53: =WEEKNUM(N53) -> 26 | Q53: =IF(J53="Vencido",N53-I53+1,0) -> 6 | R53: =IF(Q53>0,IF(Q53<31,H53,0),0) -> 66167.85 | S53: =IF(Q53>30,IF(Q53<61,H53,0),0) -> 0 | T53: =IF(Q53>60,IF(Q53<91,H53,0),0) -> 0 | U53: =IF(Q53>90,H53,0) -> 0 | V53: =IF(J53="Por vencer",H53,0) -> 0 | W53: =IF(J53="Vigente",H53,0) -> 0
A54: 46164 | B54: CLN/2026/00134 | C54: QMX4 | D54: 46200 | E54: 7392 | F54: 53592 | G54: 52839.16 | H54: =G54/1.16 -> 45551 | I54: 46194 | J54: Vencido | K54: Pagado parcialmente | L54: FREDY SALAS | M54: Crédito | N54: 46199 | O54: =MONTH(N54) -> 6 | P54: =WEEKNUM(N54) -> 26 | Q54: =IF(J54="Vencido",N54-I54+1,0) -> 6 | R54: =IF(Q54>0,IF(Q54<31,H54,0),0) -> 45551 | S54: =IF(Q54>30,IF(Q54<61,H54,0),0) -> 0 | T54: =IF(Q54>60,IF(Q54<91,H54,0),0) -> 0 | U54: =IF(Q54>90,H54,0) -> 0 | V54: =IF(J54="Por vencer",H54,0) -> 0 | W54: =IF(J54="Vigente",H54,0) -> 0
A55: 46163 | B55: HMO/2026/00345 | C55: BIOMA FORMULACIONES | D55: 110611.14 | E55: 17697.78 | F55: 128308.92 | G55: 128308.92 | H55: =D55 -> 110611.14 | I55: 46193 | J55: Vencido | K55: Sin pagar | L55: ILSE GARCÍA | M55: Crédito | N55: 46199 | O55: =MONTH(N55) -> 6 | P55: =WEEKNUM(N55) -> 26 | Q55: =IF(J55="Vencido",N55-I55+1,0) -> 7 | R55: =IF(Q55>0,IF(Q55<31,H55,0),0) -> 110611.14 | S55: =IF(Q55>30,IF(Q55<61,H55,0),0) -> 0 | T55: =IF(Q55>60,IF(Q55<91,H55,0),0) -> 0 | U55: =IF(Q55>90,H55,0) -> 0 | V55: =IF(J55="Por vencer",H55,0) -> 0 | W55: =IF(J55="Vigente",H55,0) -> 0
A56: 46162 | B56: CLN/2026/00131 | C56: AQUA DUX DE MEXICO | D56: 12000 | E56: 1920 | F56: 13920 | G56: 13920 | H56: =D56 -> 12000 | I56: 46192 | J56: Vencido | K56: Sin pagar | L56: FREDY SALAS | M56: Crédito | N56: 46199 | O56: =MONTH(N56) -> 6 | P56: =WEEKNUM(N56) -> 26 | Q56: =IF(J56="Vencido",N56-I56+1,0) -> 8 | R56: =IF(Q56>0,IF(Q56<31,H56,0),0) -> 12000 | S56: =IF(Q56>30,IF(Q56<61,H56,0),0) -> 0 | T56: =IF(Q56>60,IF(Q56<91,H56,0),0) -> 0 | U56: =IF(Q56>90,H56,0) -> 0 | V56: =IF(J56="Por vencer",H56,0) -> 0 | W56: =IF(J56="Vigente",H56,0) -> 0
A57: 46158 | B57: CLN/2026/00127 | C57: SERVICIOS Y SOLUCIONES ACUICOLAS | D57: 3900 | E57: 624 | F57: 4524 | G57: 4524 | H57: =D57 -> 3900 | I57: 46188 | J57: Vencido | K57: Sin pagar | L57: FREDY SALAS | M57: Crédito | N57: 46199 | O57: =MONTH(N57) -> 6 | P57: =WEEKNUM(N57) -> 26 | Q57: =IF(J57="Vencido",N57-I57+1,0) -> 12 | R57: =IF(Q57>0,IF(Q57<31,H57,0),0) -> 3900 | S57: =IF(Q57>30,IF(Q57<61,H57,0),0) -> 0 | T57: =IF(Q57>60,IF(Q57<91,H57,0),0) -> 0 | U57: =IF(Q57>90,H57,0) -> 0 | V57: =IF(J57="Por vencer",H57,0) -> 0 | W57: =IF(J57="Vigente",H57,0) -> 0
A58: 46147 | B58: HMO/2026/00314 | C58: SERVICIOS Y SOLUCIONES ACUICOLAS | D58: 14000 | E58: 2240 | F58: 16240 | G58: 16240 | H58: =D58 -> 14000 | I58: 46177 | J58: Vencido | K58: Sin pagar | L58: FREDY SALAS | M58: Crédito | N58: 46199 | O58: =MONTH(N58) -> 6 | P58: =WEEKNUM(N58) -> 26 | Q58: =IF(J58="Vencido",N58-I58+1,0) -> 23 | R58: =IF(Q58>0,IF(Q58<31,H58,0),0) -> 14000 | S58: =IF(Q58>30,IF(Q58<61,H58,0),0) -> 0 | T58: =IF(Q58>60,IF(Q58<91,H58,0),0) -> 0 | U58: =IF(Q58>90,H58,0) -> 0 | V58: =IF(J58="Por vencer",H58,0) -> 0 | W58: =IF(J58="Vigente",H58,0) -> 0
A59: 46147 | B59: HMO/2026/00313 | C59: SERVICIOS Y SOLUCIONES ACUICOLAS | D59: 14400 | E59: 2304 | F59: 16704 | G59: 16704 | H59: =D59 -> 14400 | I59: 46177 | J59: Vencido | K59: Sin pagar | L59: FREDY SALAS | M59: Crédito | N59: 46199 | O59: =MONTH(N59) -> 6 | P59: =WEEKNUM(N59) -> 26 | Q59: =IF(J59="Vencido",N59-I59+1,0) -> 23 | R59: =IF(Q59>0,IF(Q59<31,H59,0),0) -> 14400 | S59: =IF(Q59>30,IF(Q59<61,H59,0),0) -> 0 | T59: =IF(Q59>60,IF(Q59<91,H59,0),0) -> 0 | U59: =IF(Q59>90,H59,0) -> 0 | V59: =IF(J59="Por vencer",H59,0) -> 0 | W59: =IF(J59="Vigente",H59,0) -> 0
A60: 46146 | B60: HMO/2026/00306 | C60: KESECOME ALIMENTARIA | D60: 9460 | E60: 1513.6 | F60: 10973.6 | G60: 10973.6 | H60: =D60 -> 9460 | I60: 46176 | J60: Vencido | K60: Sin pagar | L60: FREDY SALAS | M60: Crédito | N60: 46199 | O60: =MONTH(N60) -> 6 | P60: =WEEKNUM(N60) -> 26 | Q60: =IF(J60="Vencido",N60-I60+1,0) -> 24 | R60: =IF(Q60>0,IF(Q60<31,H60,0),0) -> 9460 | S60: =IF(Q60>30,IF(Q60<61,H60,0),0) -> 0 | T60: =IF(Q60>60,IF(Q60<91,H60,0),0) -> 0 | U60: =IF(Q60>90,H60,0) -> 0 | V60: =IF(J60="Por vencer",H60,0) -> 0 | W60: =IF(J60="Vigente",H60,0) -> 0
A61: 46140 | B61: HMO/2026/00294 | C61: SERVICIOS Y SOLUCIONES ACUICOLAS | D61: 7200 | E61: 1152 | F61: 8352 | G61: 8352 | H61: =D61 -> 7200 | I61: 46170 | J61: Vencido | K61: Sin pagar | L61: FREDY SALAS | M61: Crédito | N61: 46199 | O61: =MONTH(N61) -> 6 | P61: =WEEKNUM(N61) -> 26 | Q61: =IF(J61="Vencido",N61-I61+1,0) -> 30 | R61: =IF(Q61>0,IF(Q61<31,H61,0),0) -> 7200 | S61: =IF(Q61>30,IF(Q61<61,H61,0),0) -> 0 | T61: =IF(Q61>60,IF(Q61<91,H61,0),0) -> 0 | U61: =IF(Q61>90,H61,0) -> 0 | V61: =IF(J61="Por vencer",H61,0) -> 0 | W61: =IF(J61="Vigente",H61,0) -> 0
A62: 46140 | B62: HMO/2026/00293 | C62: SERVICIOS Y SOLUCIONES ACUICOLAS | D62: 10350 | E62: 1656 | F62: 12006 | G62: 12006 | H62: =D62 -> 10350 | I62: 46170 | J62: Vencido | K62: Sin pagar | L62: FREDY SALAS | M62: Crédito | N62: 46199 | O62: =MONTH(N62) -> 6 | P62: =WEEKNUM(N62) -> 26 | Q62: =IF(J62="Vencido",N62-I62+1,0) -> 30 | R62: =IF(Q62>0,IF(Q62<31,H62,0),0) -> 10350 | S62: =IF(Q62>30,IF(Q62<61,H62,0),0) -> 0 | T62: =IF(Q62>60,IF(Q62<91,H62,0),0) -> 0 | U62: =IF(Q62>90,H62,0) -> 0 | V62: =IF(J62="Por vencer",H62,0) -> 0 | W62: =IF(J62="Vigente",H62,0) -> 0
A63: 46136 | B63: CLN/2026/00110 | C63: AQUASTORE SUMINISTROS ACUICOLAS DEL PACIFICO | D63: 114984.03 | E63: 18397.44 | F63: 133381.47 | G63: 73452.47 | H63: =G63/1.16 -> 63321.095 | I63: 46166 | J63: Vencido | K63: Pagado parcialmente | L63: MATEO LÓPEZ | M63: Crédito | N63: 46199 | O63: =MONTH(N63) -> 6 | P63: =WEEKNUM(N63) -> 26 | Q63: =IF(J63="Vencido",N63-I63+1,0) -> 34 | R63: =IF(Q63>0,IF(Q63<31,H63,0),0) -> 0 | S63: =IF(Q63>30,IF(Q63<61,H63,0),0) -> 63321.095 | T63: =IF(Q63>60,IF(Q63<91,H63,0),0) -> 0 | U63: =IF(Q63>90,H63,0) -> 0 | V63: =IF(J63="Por vencer",H63,0) -> 0 | W63: =IF(J63="Vigente",H63,0) -> 0
A64: 46120 | B64: HMO/2026/00226 | C64: SERVICIOS Y SOLUCIONES ACUICOLAS | D64: 11047.05 | E64: 1767.53 | F64: 12814.58 | G64: 12814.58 | H64: =D64 -> 11047.05 | I64: 46150 | J64: Vencido | K64: Sin pagar | L64: FREDY SALAS | M64: Crédito | N64: 46199 | O64: =MONTH(N64) -> 6 | P64: =WEEKNUM(N64) -> 26 | Q64: =IF(J64="Vencido",N64-I64+1,0) -> 50 | R64: =IF(Q64>0,IF(Q64<31,H64,0),0) -> 0 | S64: =IF(Q64>30,IF(Q64<61,H64,0),0) -> 11047.05 | T64: =IF(Q64>60,IF(Q64<91,H64,0),0) -> 0 | U64: =IF(Q64>90,H64,0) -> 0 | V64: =IF(J64="Por vencer",H64,0) -> 0 | W64: =IF(J64="Vigente",H64,0) -> 0
A65: 46083 | B65: CLN/2026/00057 | C65: SERVICIOS Y SOLUCIONES ACUICOLAS | D65: 14257.8 | E65: 2281.25 | F65: 16539.05 | G65: 16539.05 | H65: =D65 -> 14257.8 | I65: 46113 | J65: Vencido | K65: Sin pagar | L65: FREDY SALAS | M65: Crédito | N65: 46199 | O65: =MONTH(N65) -> 6 | P65: =WEEKNUM(N65) -> 26 | Q65: =IF(J65="Vencido",N65-I65+1,0) -> 87 | R65: =IF(Q65>0,IF(Q65<31,H65,0),0) -> 0 | S65: =IF(Q65>30,IF(Q65<61,H65,0),0) -> 0 | T65: =IF(Q65>60,IF(Q65<91,H65,0),0) -> 14257.8 | U65: =IF(Q65>90,H65,0) -> 0 | V65: =IF(J65="Por vencer",H65,0) -> 0 | W65: =IF(J65="Vigente",H65,0) -> 0
A66: 46077 | B66: CLN/2026/00052 | C66: DALILA GUADALUPE VALDEZ RENDON | D66: 12825 | E66: 2052 | F66: 14877 | G66: 14877 | H66: =D66 -> 12825 | I66: 46107 | J66: Vencido | K66: Sin pagar | L66: FREDY SALAS | M66: Crédito | N66: 46199 | O66: =MONTH(N66) -> 6 | P66: =WEEKNUM(N66) -> 26 | Q66: =IF(J66="Vencido",N66-I66+1,0) -> 93 | R66: =IF(Q66>0,IF(Q66<31,H66,0),0) -> 0 | S66: =IF(Q66>30,IF(Q66<61,H66,0),0) -> 0 | T66: =IF(Q66>60,IF(Q66<91,H66,0),0) -> 0 | U66: =IF(Q66>90,H66,0) -> 12825 | V66: =IF(J66="Por vencer",H66,0) -> 0 | W66: =IF(J66="Vigente",H66,0) -> 0
A67: 46076 | B67: CLN/2026/00050 | C67: DALILA GUADALUPE VALDEZ RENDON | D67: 12825 | E67: 2052 | F67: 14877 | G67: 14877 | H67: =D67 -> 12825 | I67: 46106 | J67: Vencido | K67: Sin pagar | L67: FREDY SALAS | M67: Crédito | N67: 46199 | O67: =MONTH(N67) -> 6 | P67: =WEEKNUM(N67) -> 26 | Q67: =IF(J67="Vencido",N67-I67+1,0) -> 94 | R67: =IF(Q67>0,IF(Q67<31,H67,0),0) -> 0 | S67: =IF(Q67>30,IF(Q67<61,H67,0),0) -> 0 | T67: =IF(Q67>60,IF(Q67<91,H67,0),0) -> 0 | U67: =IF(Q67>90,H67,0) -> 12825 | V67: =IF(J67="Por vencer",H67,0) -> 0 | W67: =IF(J67="Vigente",H67,0) -> 0
A68: 46072 | B68: CLN/2026/00045 | C68: SERVICIOS Y SOLUCIONES ACUICOLAS | D68: 35478.14 | E68: 5676.5 | F68: 41154.64 | G68: 41154.64 | H68: =D68 -> 35478.14 | I68: 46102 | J68: Vencido | K68: Sin pagar | L68: FREDY SALAS | M68: Crédito | N68: 46199 | O68: =MONTH(N68) -> 6 | P68: =WEEKNUM(N68) -> 26 | Q68: =IF(J68="Vencido",N68-I68+1,0) -> 98 | R68: =IF(Q68>0,IF(Q68<31,H68,0),0) -> 0 | S68: =IF(Q68>30,IF(Q68<61,H68,0),0) -> 0 | T68: =IF(Q68>60,IF(Q68<91,H68,0),0) -> 0 | U68: =IF(Q68>90,H68,0) -> 35478.14 | V68: =IF(J68="Por vencer",H68,0) -> 0 | W68: =IF(J68="Vigente",H68,0) -> 0
A69: 46071 | B69: CLN/2026/00043 | C69: DALILA GUADALUPE VALDEZ RENDON | D69: 8550 | E69: 1368 | F69: 9918 | G69: 9918 | H69: =D69 -> 8550 | I69: 46101 | J69: Vencido | K69: Sin pagar | L69: FREDY SALAS | M69: Crédito | N69: 46199 | O69: =MONTH(N69) -> 6 | P69: =WEEKNUM(N69) -> 26 | Q69: =IF(J69="Vencido",N69-I69+1,0) -> 99 | R69: =IF(Q69>0,IF(Q69<31,H69,0),0) -> 0 | S69: =IF(Q69>30,IF(Q69<61,H69,0),0) -> 0 | T69: =IF(Q69>60,IF(Q69<91,H69,0),0) -> 0 | U69: =IF(Q69>90,H69,0) -> 8550 | V69: =IF(J69="Por vencer",H69,0) -> 0 | W69: =IF(J69="Vigente",H69,0) -> 0
A70: 46069 | B70: CLN/2026/00042 | C70: DALILA GUADALUPE VALDEZ RENDON | D70: 8550 | E70: 1368 | F70: 9918 | G70: 9918 | H70: =D70 -> 8550 | I70: 46099 | J70: Vencido | K70: Sin pagar | L70: FREDY SALAS | M70: Crédito | N70: 46199 | O70: =MONTH(N70) -> 6 | P70: =WEEKNUM(N70) -> 26 | Q70: =IF(J70="Vencido",N70-I70+1,0) -> 101 | R70: =IF(Q70>0,IF(Q70<31,H70,0),0) -> 0 | S70: =IF(Q70>30,IF(Q70<61,H70,0),0) -> 0 | T70: =IF(Q70>60,IF(Q70<91,H70,0),0) -> 0 | U70: =IF(Q70>90,H70,0) -> 8550 | V70: =IF(J70="Por vencer",H70,0) -> 0 | W70: =IF(J70="Vigente",H70,0) -> 0
A71: 46069 | B71: CLN/2026/00041 | C71: SERVICIOS Y SOLUCIONES ACUICOLAS | D71: 7112.44 | E71: 1137.99 | F71: 8250.43 | G71: 8250.43 | H71: =D71 -> 7112.44 | I71: 46099 | J71: Vencido | K71: Sin pagar | L71: FREDY SALAS | M71: Crédito | N71: 46199 | O71: =MONTH(N71) -> 6 | P71: =WEEKNUM(N71) -> 26 | Q71: =IF(J71="Vencido",N71-I71+1,0) -> 101 | R71: =IF(Q71>0,IF(Q71<31,H71,0),0) -> 0 | S71: =IF(Q71>30,IF(Q71<61,H71,0),0) -> 0 | T71: =IF(Q71>60,IF(Q71<91,H71,0),0) -> 0 | U71: =IF(Q71>90,H71,0) -> 7112.44 | V71: =IF(J71="Por vencer",H71,0) -> 0 | W71: =IF(J71="Vigente",H71,0) -> 0
A72: 46037 | B72: CLN/2026/00016 | C72: DALILA GUADALUPE VALDEZ RENDON | D72: 44390 | E72: 7102.4 | F72: 51492.4 | G72: 51492.4 | H72: =D72 -> 44390 | I72: 46067 | J72: Vencido | K72: Sin pagar | L72: FREDY SALAS | M72: Crédito | N72: 46199 | O72: =MONTH(N72) -> 6 | P72: =WEEKNUM(N72) -> 26 | Q72: =IF(J72="Vencido",N72-I72+1,0) -> 133 | R72: =IF(Q72>0,IF(Q72<31,H72,0),0) -> 0 | S72: =IF(Q72>30,IF(Q72<61,H72,0),0) -> 0 | T72: =IF(Q72>60,IF(Q72<91,H72,0),0) -> 0 | U72: =IF(Q72>90,H72,0) -> 44390 | V72: =IF(J72="Por vencer",H72,0) -> 0 | W72: =IF(J72="Vigente",H72,0) -> 0
A73: 46037 | B73: CLN/2026/00015 | C73: SERVICIOS Y SOLUCIONES ACUICOLAS | D73: 17638.53 | E73: 2822.16 | F73: 20460.69 | G73: 20460.69 | H73: =D73 -> 17638.53 | I73: 46067 | J73: Vencido | K73: Sin pagar | L73: FREDY SALAS | M73: Crédito | N73: 46199 | O73: =MONTH(N73) -> 6 | P73: =WEEKNUM(N73) -> 26 | Q73: =IF(J73="Vencido",N73-I73+1,0) -> 133 | R73: =IF(Q73>0,IF(Q73<31,H73,0),0) -> 0 | S73: =IF(Q73>30,IF(Q73<61,H73,0),0) -> 0 | T73: =IF(Q73>60,IF(Q73<91,H73,0),0) -> 0 | U73: =IF(Q73>90,H73,0) -> 17638.53 | V73: =IF(J73="Por vencer",H73,0) -> 0 | W73: =IF(J73="Vigente",H73,0) -> 0
A74: 46017 | B74: CLN/2025/00525 | C74: DALILA GUADALUPE VALDEZ RENDON | D74: 42000 | E74: 6720 | F74: 48720 | G74: 31860 | H74: =G74/1.16 -> 27465.517 | I74: 46047 | J74: Vencido | K74: Pagado parcialmente | L74: FREDY SALAS | M74: Crédito | N74: 46199 | O74: =MONTH(N74) -> 6 | P74: =WEEKNUM(N74) -> 26 | Q74: =IF(J74="Vencido",N74-I74+1,0) -> 153 | R74: =IF(Q74>0,IF(Q74<31,H74,0),0) -> 0 | S74: =IF(Q74>30,IF(Q74<61,H74,0),0) -> 0 | T74: =IF(Q74>60,IF(Q74<91,H74,0),0) -> 0 | U74: =IF(Q74>90,H74,0) -> 27465.517 | V74: =IF(J74="Por vencer",H74,0) -> 0 | W74: =IF(J74="Vigente",H74,0) -> 0
A75: 45953 | B75: CLN/2025/00474 | C75: RAUL IVAN VAZQUEZ ALVAREZ | D75: 19694.4 | E75: 3151.1 | F75: 22845.5 | G75: 2429.5 | H75: =G75/1.16 -> 2094.3966 | I75: 45968 | J75: Vencido | K75: Pagado parcialmente | L75: FREDY SALAS | M75: Crédito | N75: 46199 | O75: =MONTH(N75) -> 6 | P75: =WEEKNUM(N75) -> 26 | Q75: =IF(J75="Vencido",N75-I75+1,0) -> 232 | R75: =IF(Q75>0,IF(Q75<31,H75,0),0) -> 0 | S75: =IF(Q75>30,IF(Q75<61,H75,0),0) -> 0 | T75: =IF(Q75>60,IF(Q75<91,H75,0),0) -> 0 | U75: =IF(Q75>90,H75,0) -> 2094.3966 | V75: =IF(J75="Por vencer",H75,0) -> 0 | W75: =IF(J75="Vigente",H75,0) -> 0
A76: 45944 | B76: CLN/2025/00465 | C76: SERVICIOS Y SOLUCIONES ACUICOLAS | D76: 14295.42 | E76: 2287.27 | F76: 16582.69 | G76: 7355.32 | H76: =G76/1.16 -> 6340.7931 | I76: 45974 | J76: Vencido | K76: Pagado parcialmente | L76: FREDY SALAS | M76: Crédito | N76: 46199 | O76: =MONTH(N76) -> 6 | P76: =WEEKNUM(N76) -> 26 | Q76: =IF(J76="Vencido",N76-I76+1,0) -> 226 | R76: =IF(Q76>0,IF(Q76<31,H76,0),0) -> 0 | S76: =IF(Q76>30,IF(Q76<61,H76,0),0) -> 0 | T76: =IF(Q76>60,IF(Q76<91,H76,0),0) -> 0 | U76: =IF(Q76>90,H76,0) -> 6340.7931 | V76: =IF(J76="Por vencer",H76,0) -> 0 | W76: =IF(J76="Vigente",H76,0) -> 0
A77: 45915 | B77: HMO/2025/00727 | C77: GUADALUPE BALVANEDA CORRAL FELIX | D77: 7125 | E77: 1140 | F77: 8265 | G77: 8265 | H77: =D77 -> 7125 | I77: 45945 | J77: Vencido | K77: Sin pagar | L77: ILSE GARCÍA | M77: Crédito | N77: 46199 | O77: =MONTH(N77) -> 6 | P77: =WEEKNUM(N77) -> 26 | Q77: =IF(J77="Vencido",N77-I77+1,0) -> 255 | R77: =IF(Q77>0,IF(Q77<31,H77,0),0) -> 0 | S77: =IF(Q77>30,IF(Q77<61,H77,0),0) -> 0 | T77: =IF(Q77>60,IF(Q77<91,H77,0),0) -> 0 | U77: =IF(Q77>90,H77,0) -> 7125 | V77: =IF(J77="Por vencer",H77,0) -> 0 | W77: =IF(J77="Vigente",H77,0) -> 0
A78: 45896 | B78: HMO/2025/00683 | C78: GUADALUPE BALVANEDA CORRAL FELIX | D78: 4375 | E78: 700 | F78: 5075 | G78: 5075 | H78: =D78 -> 4375 | I78: 45926 | J78: Vencido | K78: Sin pagar | L78: ILSE GARCÍA | M78: Crédito | N78: 46199 | O78: =MONTH(N78) -> 6 | P78: =WEEKNUM(N78) -> 26 | Q78: =IF(J78="Vencido",N78-I78+1,0) -> 274 | R78: =IF(Q78>0,IF(Q78<31,H78,0),0) -> 0 | S78: =IF(Q78>30,IF(Q78<61,H78,0),0) -> 0 | T78: =IF(Q78>60,IF(Q78<91,H78,0),0) -> 0 | U78: =IF(Q78>90,H78,0) -> 4375 | V78: =IF(J78="Por vencer",H78,0) -> 0 | W78: =IF(J78="Vigente",H78,0) -> 0
A79: 45895 | B79: CLN/2025/00385 | C79: HENKO DISTRIBUCION QUIMICA | D79: 22364.16 | F79: 22364.16 | G79: 22364.16 | H79: =D79 -> 22364.16 | I79: 45925 | J79: Vencido | K79: Sin pagar | L79: EMILY MEZA | M79: Crédito | N79: 46199 | O79: =MONTH(N79) -> 6 | P79: =WEEKNUM(N79) -> 26 | Q79: =IF(J79="Vencido",N79-I79+1,0) -> 275 | R79: =IF(Q79>0,IF(Q79<31,H79,0),0) -> 0 | S79: =IF(Q79>30,IF(Q79<61,H79,0),0) -> 0 | T79: =IF(Q79>60,IF(Q79<91,H79,0),0) -> 0 | U79: =IF(Q79>90,H79,0) -> 22364.16 | V79: =IF(J79="Por vencer",H79,0) -> 0 | W79: =IF(J79="Vigente",H79,0) -> 0
A80: 45876 | B80: CLN/2025/00356 | C80: HENKO DISTRIBUCION QUIMICA | D80: 22343.04 | F80: 22343.04 | G80: 22343.04 | H80: =D80 -> 22343.04 | I80: 45906 | J80: Vencido | K80: Sin pagar | L80: EMILY MEZA | M80: Crédito | N80: 46199 | O80: =MONTH(N80) -> 6 | P80: =WEEKNUM(N80) -> 26 | Q80: =IF(J80="Vencido",N80-I80+1,0) -> 294 | R80: =IF(Q80>0,IF(Q80<31,H80,0),0) -> 0 | S80: =IF(Q80>30,IF(Q80<61,H80,0),0) -> 0 | T80: =IF(Q80>60,IF(Q80<91,H80,0),0) -> 0 | U80: =IF(Q80>90,H80,0) -> 22343.04 | V80: =IF(J80="Por vencer",H80,0) -> 0 | W80: =IF(J80="Vigente",H80,0) -> 0
A81: 45869 | B81: CLN/2025/00350 | C81: 3Q GLOBAL SOLUTIONS | D81: 761801.88 | E81: 121888.3 | F81: 883690.18 | G81: 203429.86 | H81: =G81/1.16 -> 175370.57 | I81: 45884 | J81: Vencido | K81: Pagado parcialmente | L81: FREDY SALAS | M81: Crédito | N81: 46199 | O81: =MONTH(N81) -> 6 | P81: =WEEKNUM(N81) -> 26 | Q81: =IF(J81="Vencido",N81-I81+1,0) -> 316 | R81: =IF(Q81>0,IF(Q81<31,H81,0),0) -> 0 | S81: =IF(Q81>30,IF(Q81<61,H81,0),0) -> 0 | T81: =IF(Q81>60,IF(Q81<91,H81,0),0) -> 0 | U81: =IF(Q81>90,H81,0) -> 175370.57 | V81: =IF(J81="Por vencer",H81,0) -> 0 | W81: =IF(J81="Vigente",H81,0) -> 0
A82: 45840 | B82: CLN/2025/00317 | C82: JESUS FRANCISCO OLMOS CASTRO | D82: 14940 | E82: 2390.4 | F82: 17330.4 | G82: 17330.4 | H82: =D82 -> 14940 | I82: 45870 | J82: Vencido | K82: Sin pagar | L82: EMILY MEZA | M82: Crédito | N82: 46199 | O82: =MONTH(N82) -> 6 | P82: =WEEKNUM(N82) -> 26 | Q82: =IF(J82="Vencido",N82-I82+1,0) -> 330 | R82: =IF(Q82>0,IF(Q82<31,H82,0),0) -> 0 | S82: =IF(Q82>30,IF(Q82<61,H82,0),0) -> 0 | T82: =IF(Q82>60,IF(Q82<91,H82,0),0) -> 0 | U82: =IF(Q82>90,H82,0) -> 14940 | V82: =IF(J82="Por vencer",H82,0) -> 0 | W82: =IF(J82="Vigente",H82,0) -> 0
A83: 45827 | B83: CLN/2025/00296 | C83: JESUS FRANCISCO OLMOS CASTRO | D83: 22410 | E83: 3585.6 | F83: 25995.6 | G83: 22884.76 | H83: =G83/1.16 -> 19728.241 | I83: 45857 | J83: Vencido | K83: Pagado parcialmente | L83: EMILY MEZA | M83: Crédito | N83: 46199 | O83: =MONTH(N83) -> 6 | P83: =WEEKNUM(N83) -> 26 | Q83: =IF(J83="Vencido",N83-I83+1,0) -> 343 | R83: =IF(Q83>0,IF(Q83<31,H83,0),0) -> 0 | S83: =IF(Q83>30,IF(Q83<61,H83,0),0) -> 0 | T83: =IF(Q83>60,IF(Q83<91,H83,0),0) -> 0 | U83: =IF(Q83>90,H83,0) -> 19728.241 | V83: =IF(J83="Por vencer",H83,0) -> 0 | W83: =IF(J83="Vigente",H83,0) -> 0
A84: 45799 | B84: CLN/2025/00256 | C84: RITA MARIA OLGUIN SERRANO | D84: 3477.15 | E84: 556.34 | F84: 4033.49 | G84: 4033.49 | H84: =D84 -> 3477.15 | I84: 45829 | J84: Vencido | K84: Sin pagar | L84: EMILY MEZA | M84: Crédito | N84: 46199 | O84: =MONTH(N84) -> 6 | P84: =WEEKNUM(N84) -> 26 | Q84: =IF(J84="Vencido",N84-I84+1,0) -> 371 | R84: =IF(Q84>0,IF(Q84<31,H84,0),0) -> 0 | S84: =IF(Q84>30,IF(Q84<61,H84,0),0) -> 0 | T84: =IF(Q84>60,IF(Q84<91,H84,0),0) -> 0 | U84: =IF(Q84>90,H84,0) -> 3477.15 | V84: =IF(J84="Por vencer",H84,0) -> 0 | W84: =IF(J84="Vigente",H84,0) -> 0
A85: 45792 | B85: CLN/2025/00253 | C85: RITA MARIA OLGUIN SERRANO | D85: 162680 | E85: 26028.8 | F85: 188708.8 | G85: 188708.8 | H85: =D85 -> 162680 | I85: 45822 | J85: Vencido | K85: Sin pagar | L85: EMILY MEZA | M85: Crédito | N85: 46199 | O85: =MONTH(N85) -> 6 | P85: =WEEKNUM(N85) -> 26 | Q85: =IF(J85="Vencido",N85-I85+1,0) -> 378 | R85: =IF(Q85>0,IF(Q85<31,H85,0),0) -> 0 | S85: =IF(Q85>30,IF(Q85<61,H85,0),0) -> 0 | T85: =IF(Q85>60,IF(Q85<91,H85,0),0) -> 0 | U85: =IF(Q85>90,H85,0) -> 162680 | V85: =IF(J85="Por vencer",H85,0) -> 0 | W85: =IF(J85="Vigente",H85,0) -> 0
A86: 45792 | B86: CLN/2025/00250 | C86: RITA MARIA OLGUIN SERRANO | D86: 6970.68 | E86: 1115.31 | F86: 8085.99 | G86: 8085.99 | H86: =D86 -> 6970.68 | I86: 45822 | J86: Vencido | K86: Sin pagar | L86: EMILY MEZA | M86: Crédito | N86: 46199 | O86: =MONTH(N86) -> 6 | P86: =WEEKNUM(N86) -> 26 | Q86: =IF(J86="Vencido",N86-I86+1,0) -> 378 | R86: =IF(Q86>0,IF(Q86<31,H86,0),0) -> 0 | S86: =IF(Q86>30,IF(Q86<61,H86,0),0) -> 0 | T86: =IF(Q86>60,IF(Q86<91,H86,0),0) -> 0 | U86: =IF(Q86>90,H86,0) -> 6970.68 | V86: =IF(J86="Por vencer",H86,0) -> 0 | W86: =IF(J86="Vigente",H86,0) -> 0
A87: 45790 | B87: CLN/2025/00246 | C87: RITA MARIA OLGUIN SERRANO | D87: 20992.5 | E87: 3358.8 | F87: 24351.3 | G87: 24351.3 | H87: =D87 -> 20992.5 | I87: 45820 | J87: Vencido | K87: Sin pagar | L87: EMILY MEZA | M87: Crédito | N87: 46199 | O87: =MONTH(N87) -> 6 | P87: =WEEKNUM(N87) -> 26 | Q87: =IF(J87="Vencido",N87-I87+1,0) -> 380 | R87: =IF(Q87>0,IF(Q87<31,H87,0),0) -> 0 | S87: =IF(Q87>30,IF(Q87<61,H87,0),0) -> 0 | T87: =IF(Q87>60,IF(Q87<91,H87,0),0) -> 0 | U87: =IF(Q87>90,H87,0) -> 20992.5 | V87: =IF(J87="Por vencer",H87,0) -> 0 | W87: =IF(J87="Vigente",H87,0) -> 0
A88: 45784 | B88: CLN/2025/00237 | C88: RITA MARIA OLGUIN SERRANO | D88: 5250 | E88: 840 | F88: 6090 | G88: 6090 | H88: =D88 -> 5250 | I88: 45814 | J88: Vencido | K88: Sin pagar | L88: EMILY MEZA | M88: Crédito | N88: 46199 | O88: =MONTH(N88) -> 6 | P88: =WEEKNUM(N88) -> 26 | Q88: =IF(J88="Vencido",N88-I88+1,0) -> 386 | R88: =IF(Q88>0,IF(Q88<31,H88,0),0) -> 0 | S88: =IF(Q88>30,IF(Q88<61,H88,0),0) -> 0 | T88: =IF(Q88>60,IF(Q88<91,H88,0),0) -> 0 | U88: =IF(Q88>90,H88,0) -> 5250 | V88: =IF(J88="Por vencer",H88,0) -> 0 | W88: =IF(J88="Vigente",H88,0) -> 0
A89: 45772 | B89: CLN/2025/00223 | C89: RITA MARIA OLGUIN SERRANO | D89: 45500 | E89: 7280 | F89: 52780 | G89: 52780 | H89: =D89 -> 45500 | I89: 45802 | J89: Vencido | K89: Sin pagar | L89: EMILY MEZA | M89: Crédito | N89: 46199 | O89: =MONTH(N89) -> 6 | P89: =WEEKNUM(N89) -> 26 | Q89: =IF(J89="Vencido",N89-I89+1,0) -> 398 | R89: =IF(Q89>0,IF(Q89<31,H89,0),0) -> 0 | S89: =IF(Q89>30,IF(Q89<61,H89,0),0) -> 0 | T89: =IF(Q89>60,IF(Q89<91,H89,0),0) -> 0 | U89: =IF(Q89>90,H89,0) -> 45500 | V89: =IF(J89="Por vencer",H89,0) -> 0 | W89: =IF(J89="Vigente",H89,0) -> 0
A90: 45720 | B90: CLN/2025/00143 | C90: RITA MARIA OLGUIN SERRANO | D90: 31483.63 | E90: 5037.38 | F90: 36521.01 | G90: 5816.12 | H90: =G90/1.16 -> 5013.8966 | I90: 45750 | J90: Vencido | K90: Pagado parcialmente | L90: EMILY MEZA | M90: Crédito | N90: 46199 | O90: =MONTH(N90) -> 6 | P90: =WEEKNUM(N90) -> 26 | Q90: =IF(J90="Vencido",N90-I90+1,0) -> 450 | R90: =IF(Q90>0,IF(Q90<31,H90,0),0) -> 0 | S90: =IF(Q90>30,IF(Q90<61,H90,0),0) -> 0 | T90: =IF(Q90>60,IF(Q90<91,H90,0),0) -> 0 | U90: =IF(Q90>90,H90,0) -> 5013.8966 | V90: =IF(J90="Por vencer",H90,0) -> 0 | W90: =IF(J90="Vigente",H90,0) -> 0
A91: 45709 | B91: CLN/2025/00127 | C91: RITA MARIA OLGUIN SERRANO | D91: 23609.5 | E91: 2595.6 | F91: 26205.1 | G91: 26205.1 | H91: =D91 -> 23609.5 | I91: 45784 | J91: Vencido | K91: Sin pagar | L91: EMILY MEZA | M91: Crédito | N91: 46199 | O91: =MONTH(N91) -> 6 | P91: =WEEKNUM(N91) -> 26 | Q91: =IF(J91="Vencido",N91-I91+1,0) -> 416 | R91: =IF(Q91>0,IF(Q91<31,H91,0),0) -> 0 | S91: =IF(Q91>30,IF(Q91<61,H91,0),0) -> 0 | T91: =IF(Q91>60,IF(Q91<91,H91,0),0) -> 0 | U91: =IF(Q91>90,H91,0) -> 23609.5 | V91: =IF(J91="Por vencer",H91,0) -> 0 | W91: =IF(J91="Vigente",H91,0) -> 0
A92: 45699 | B92: CLN/2025/00101 | C92: PEDRO CASTAÑEDA SALAZAR | D92: 1230 | F92: 1230 | G92: 1230 | H92: =D92 -> 1230 | I92: 45714 | J92: Vencido | K92: Sin pagar | L92: EMILY MEZA | M92: Crédito | N92: 46199 | O92: =MONTH(N92) -> 6 | P92: =WEEKNUM(N92) -> 26 | Q92: =IF(J92="Vencido",N92-I92+1,0) -> 486 | R92: =IF(Q92>0,IF(Q92<31,H92,0),0) -> 0 | S92: =IF(Q92>30,IF(Q92<61,H92,0),0) -> 0 | T92: =IF(Q92>60,IF(Q92<91,H92,0),0) -> 0 | U92: =IF(Q92>90,H92,0) -> 1230 | V92: =IF(J92="Por vencer",H92,0) -> 0 | W92: =IF(J92="Vigente",H92,0) -> 0
A93: 45610 | B93: HMO/2024/00987 | C93: MARIA GUADALUPE OLGUIN SIQUEIROS | D93: 2369.29 | E93: 379.09 | F93: 2748.38 | G93: 360.54 | H93: =G93/1.16 -> 310.81034 | I93: 45640 | J93: Vencido | K93: Pagado parcialmente | L93: GALO CASTRO | M93: Crédito | N93: 46199 | O93: =MONTH(N93) -> 6 | P93: =WEEKNUM(N93) -> 26 | Q93: =IF(J93="Vencido",N93-I93+1,0) -> 560 | R93: =IF(Q93>0,IF(Q93<31,H93,0),0) -> 0 | S93: =IF(Q93>30,IF(Q93<61,H93,0),0) -> 0 | T93: =IF(Q93>60,IF(Q93<91,H93,0),0) -> 0 | U93: =IF(Q93>90,H93,0) -> 310.81034 | V93: =IF(J93="Por vencer",H93,0) -> 0 | W93: =IF(J93="Vigente",H93,0) -> 0
A94: 45582 | B94: HMO/2024/00910 | C94: MARIA GUADALUPE OLGUIN SIQUEIROS | D94: 21120 | E94: 3379.2 | F94: 24499.2 | G94: 24499.2 | H94: =D94 -> 21120 | I94: 45612 | J94: Vencido | K94: Sin pagar | L94: GALO CASTRO | M94: Crédito | N94: 46199 | O94: =MONTH(N94) -> 6 | P94: =WEEKNUM(N94) -> 26 | Q94: =IF(J94="Vencido",N94-I94+1,0) -> 588 | R94: =IF(Q94>0,IF(Q94<31,H94,0),0) -> 0 | S94: =IF(Q94>30,IF(Q94<61,H94,0),0) -> 0 | T94: =IF(Q94>60,IF(Q94<91,H94,0),0) -> 0 | U94: =IF(Q94>90,H94,0) -> 21120 | V94: =IF(J94="Por vencer",H94,0) -> 0 | W94: =IF(J94="Vigente",H94,0) -> 0
A95: 45519 | B95: CLN/2024/00680 | C95: MARIA ALICIA VIRIDIANA TOSCANO GAMBOA | D95: 2475 | E95: 396 | F95: 2871 | G95: 2871 | H95: =D95 -> 2475 | I95: 45549 | J95: Vencido | K95: Sin pagar | L95: ERIC SAAVEDRA | M95: Crédito | N95: 46199 | O95: =MONTH(N95) -> 6 | P95: =WEEKNUM(N95) -> 26 | Q95: =IF(J95="Vencido",N95-I95+1,0) -> 651 | R95: =IF(Q95>0,IF(Q95<31,H95,0),0) -> 0 | S95: =IF(Q95>30,IF(Q95<61,H95,0),0) -> 0 | T95: =IF(Q95>60,IF(Q95<91,H95,0),0) -> 0 | U95: =IF(Q95>90,H95,0) -> 2475 | V95: =IF(J95="Por vencer",H95,0) -> 0 | W95: =IF(J95="Vigente",H95,0) -> 0
A96: 45498 | B96: CLN/2024/00600 | C96: MARIA ALICIA VIRIDIANA TOSCANO GAMBOA | D96: 2475 | E96: 396 | F96: 2871 | G96: 2378 | H96: =G96/1.16 -> 2050 | I96: 45528 | J96: Vencido | K96: Pagado parcialmente | L96: ERIC SAAVEDRA | M96: Crédito | N96: 46199 | O96: =MONTH(N96) -> 6 | P96: =WEEKNUM(N96) -> 26 | Q96: =IF(J96="Vencido",N96-I96+1,0) -> 672 | R96: =IF(Q96>0,IF(Q96<31,H96,0),0) -> 0 | S96: =IF(Q96>30,IF(Q96<61,H96,0),0) -> 0 | T96: =IF(Q96>60,IF(Q96<91,H96,0),0) -> 0 | U96: =IF(Q96>90,H96,0) -> 2050 | V96: =IF(J96="Por vencer",H96,0) -> 0 | W96: =IF(J96="Vigente",H96,0) -> 0
A97: 45491 | B97: HMO/2024/00568 | C97: JULIO CESAR DUEÑAS LEYVA | D97: 16588 | E97: 2654.08 | F97: 19242.08 | G97: 19242.08 | H97: =D97 -> 16588 | I97: 45521 | J97: Vencido | K97: Sin pagar | L97: ILSE GARCÍA | M97: Crédito | N97: 46199 | O97: =MONTH(N97) -> 6 | P97: =WEEKNUM(N97) -> 26 | Q97: =IF(J97="Vencido",N97-I97+1,0) -> 679 | R97: =IF(Q97>0,IF(Q97<31,H97,0),0) -> 0 | S97: =IF(Q97>30,IF(Q97<61,H97,0),0) -> 0 | T97: =IF(Q97>60,IF(Q97<91,H97,0),0) -> 0 | U97: =IF(Q97>90,H97,0) -> 16588 | V97: =IF(J97="Por vencer",H97,0) -> 0 | W97: =IF(J97="Vigente",H97,0) -> 0
A98: 45352 | B98: CLN/2024/00057 | C98: ELVIA GRACIELA REYNA LIMAS | D98: 8800 | E98: 1408 | F98: 10208 | G98: 10208 | H98: =D98 -> 8800 | I98: 45382 | J98: Vencido | K98: Sin pagar | L98: GUADALUPE PARRA | M98: Crédito | N98: 46199 | O98: =MONTH(N98) -> 6 | P98: =WEEKNUM(N98) -> 26 | Q98: =IF(J98="Vencido",N98-I98+1,0) -> 818 | R98: =IF(Q98>0,IF(Q98<31,H98,0),0) -> 0 | S98: =IF(Q98>30,IF(Q98<61,H98,0),0) -> 0 | T98: =IF(Q98>60,IF(Q98<91,H98,0),0) -> 0 | U98: =IF(Q98>90,H98,0) -> 8800 | V98: =IF(J98="Por vencer",H98,0) -> 0 | W98: =IF(J98="Vigente",H98,0) -> 0
A99: 46192 | B99: HMO/2026/00426 | C99: YERALDIN CASTRO CADENA | D99: 15631.92 | E99: 2501.11 | F99: 18133.03 | G99: 18133.03 | H99: =D99 -> 15631.92 | I99: 46222 | J99: Vigente | K99: Sin pagar | L99: ILSE GARCÍA | M99: Crédito | N99: 46192 | O99: =MONTH(N99) -> 6 | P99: =WEEKNUM(N99) -> 25 | Q99: =IF(J99="Vencido",N99-I99+1,0) -> 0 | R99: =IF(Q99>0,IF(Q99<31,H99,0),0) -> 0 | S99: =IF(Q99>30,IF(Q99<61,H99,0),0) -> 0 | T99: =IF(Q99>60,IF(Q99<91,H99,0),0) -> 0 | U99: =IF(Q99>90,H99,0) -> 0 | V99: =IF(J99="Por vencer",H99,0) -> 0 | W99: =IF(J99="Vigente",H99,0) -> 15631.92
A100: 46192 | B100: HMO/2026/00425 | C100: YERALDIN CASTRO CADENA | D100: 1750 | E100: 280 | F100: 2030 | G100: 2030 | H100: =D100 -> 1750 | I100: 46222 | J100: Vigente | K100: Sin pagar | L100: ILSE GARCÍA | M100: Crédito | N100: 46192 | O100: =MONTH(N100) -> 6 | P100: =WEEKNUM(N100) -> 25 | Q100: =IF(J100="Vencido",N100-I100+1,0) -> 0 | R100: =IF(Q100>0,IF(Q100<31,H100,0),0) -> 0 | S100: =IF(Q100>30,IF(Q100<61,H100,0),0) -> 0 | T100: =IF(Q100>60,IF(Q100<91,H100,0),0) -> 0 | U100: =IF(Q100>90,H100,0) -> 0 | V100: =IF(J100="Por vencer",H100,0) -> 0 | W100: =IF(J100="Vigente",H100,0) -> 1750
A101: 46191 | B101: HMO/2026/00424 | C101: YERALDIN CASTRO CADENA | D101: 7000 | E101: 1120 | F101: 8120 | G101: 8120 | H101: =D101 -> 7000 | I101: 46221 | J101: Vigente | K101: Sin pagar | L101: ILSE GARCÍA | M101: Crédito | N101: 46192 | O101: =MONTH(N101) -> 6 | P101: =WEEKNUM(N101) -> 25 | Q101: =IF(J101="Vencido",N101-I101+1,0) -> 0 | R101: =IF(Q101>0,IF(Q101<31,H101,0),0) -> 0 | S101: =IF(Q101>30,IF(Q101<61,H101,0),0) -> 0 | T101: =IF(Q101>60,IF(Q101<91,H101,0),0) -> 0 | U101: =IF(Q101>90,H101,0) -> 0 | V101: =IF(J101="Por vencer",H101,0) -> 0 | W101: =IF(J101="Vigente",H101,0) -> 7000
A102: 46191 | B102: HMO/2026/00423 | C102: HECTOR SAU ESPINOZA | D102: 3867.57 | E102: 618.81 | F102: 4486.38 | G102: 4486.38 | H102: =D102 -> 3867.57 | I102: 46221 | J102: Vigente | K102: Sin pagar | L102: ILSE GARCÍA | M102: Crédito | N102: 46192 | O102: =MONTH(N102) -> 6 | P102: =WEEKNUM(N102) -> 25 | Q102: =IF(J102="Vencido",N102-I102+1,0) -> 0 | R102: =IF(Q102>0,IF(Q102<31,H102,0),0) -> 0 | S102: =IF(Q102>30,IF(Q102<61,H102,0),0) -> 0 | T102: =IF(Q102>60,IF(Q102<91,H102,0),0) -> 0 | U102: =IF(Q102>90,H102,0) -> 0 | V102: =IF(J102="Por vencer",H102,0) -> 0 | W102: =IF(J102="Vigente",H102,0) -> 3867.57
A103: 46191 | B103: CLN/2026/00157 | C103: JESUS ESTEBAN CHAVEZ PRECIADO | D103: 31280 | E103: 5004.8 | F103: 36284.8 | G103: 36284.8 | H103: =D103 -> 31280 | I103: 46221 | J103: Vigente | K103: Sin pagar | L103: MATEO LÓPEZ | M103: Crédito | N103: 46192 | O103: =MONTH(N103) -> 6 | P103: =WEEKNUM(N103) -> 25 | Q103: =IF(J103="Vencido",N103-I103+1,0) -> 0 | R103: =IF(Q103>0,IF(Q103<31,H103,0),0) -> 0 | S103: =IF(Q103>30,IF(Q103<61,H103,0),0) -> 0 | T103: =IF(Q103>60,IF(Q103<91,H103,0),0) -> 0 | U103: =IF(Q103>90,H103,0) -> 0 | V103: =IF(J103="Por vencer",H103,0) -> 0 | W103: =IF(J103="Vigente",H103,0) -> 31280
A104: 46190 | B104: HMO/2026/00421 | C104: FERRO MATERIALES CABANILLAS | D104: 10475 | E104: 1676 | F104: 12151 | G104: 12151 | H104: =D104 -> 10475 | I104: 46220 | J104: Vigente | K104: Sin pagar | L104: ILSE GARCÍA | M104: Crédito | N104: 46192 | O104: =MONTH(N104) -> 6 | P104: =WEEKNUM(N104) -> 25 | Q104: =IF(J104="Vencido",N104-I104+1,0) -> 0 | R104: =IF(Q104>0,IF(Q104<31,H104,0),0) -> 0 | S104: =IF(Q104>30,IF(Q104<61,H104,0),0) -> 0 | T104: =IF(Q104>60,IF(Q104<91,H104,0),0) -> 0 | U104: =IF(Q104>90,H104,0) -> 0 | V104: =IF(J104="Por vencer",H104,0) -> 0 | W104: =IF(J104="Vigente",H104,0) -> 10475
A105: 46190 | B105: HMO/2026/00418 | C105: HECTOR SAU ESPINOZA | D105: 7741.04 | E105: 1238.57 | F105: 8979.61 | G105: 8979.61 | H105: =D105 -> 7741.04 | I105: 46220 | J105: Vigente | K105: Sin pagar | L105: ILSE GARCÍA | M105: Crédito | N105: 46192 | O105: =MONTH(N105) -> 6 | P105: =WEEKNUM(N105) -> 25 | Q105: =IF(J105="Vencido",N105-I105+1,0) -> 0 | R105: =IF(Q105>0,IF(Q105<31,H105,0),0) -> 0 | S105: =IF(Q105>30,IF(Q105<61,H105,0),0) -> 0 | T105: =IF(Q105>60,IF(Q105<91,H105,0),0) -> 0 | U105: =IF(Q105>90,H105,0) -> 0 | V105: =IF(J105="Por vencer",H105,0) -> 0 | W105: =IF(J105="Vigente",H105,0) -> 7741.04
A106: 46190 | B106: HMO/2026/00417 | C106: JUAN HERMENEGILDO OLIVAS MENDOZA | D106: 16200 | E106: 2592 | F106: 18792 | G106: 18792 | H106: =D106 -> 16200 | I106: 46190 | J106: Vencido | K106: Sin pagar | L106: ILSE GARCÍA | M106: Contado | N106: 46192 | O106: =MONTH(N106) -> 6 | P106: =WEEKNUM(N106) -> 25 | Q106: =IF(J106="Vencido",N106-I106+1,0) -> 3 | R106: =IF(Q106>0,IF(Q106<31,H106,0),0) -> 16200 | S106: =IF(Q106>30,IF(Q106<61,H106,0),0) -> 0 | T106: =IF(Q106>60,IF(Q106<91,H106,0),0) -> 0 | U106: =IF(Q106>90,H106,0) -> 0 | V106: =IF(J106="Por vencer",H106,0) -> 0 | W106: =IF(J106="Vigente",H106,0) -> 0
A107: 46190 | B107: CLN/2026/00156 | C107: MARIA DEL CARMEN RIVERA QUINTERO | D107: 13500 | E107: 2160 | F107: 15660 | G107: 15660 | H107: =D107 -> 13500 | I107: 46220 | J107: Vigente | K107: Sin pagar | L107: FREDY SALAS | M107: Crédito | N107: 46192 | O107: =MONTH(N107) -> 6 | P107: =WEEKNUM(N107) -> 25 | Q107: =IF(J107="Vencido",N107-I107+1,0) -> 0 | R107: =IF(Q107>0,IF(Q107<31,H107,0),0) -> 0 | S107: =IF(Q107>30,IF(Q107<61,H107,0),0) -> 0 | T107: =IF(Q107>60,IF(Q107<91,H107,0),0) -> 0 | U107: =IF(Q107>90,H107,0) -> 0 | V107: =IF(J107="Por vencer",H107,0) -> 0 | W107: =IF(J107="Vigente",H107,0) -> 13500
A108: 46189 | B108: HMO/2026/00413 | C108: ANTONIO ROMAN PEÑA | D108: 74942.17 | E108: 11990.75 | F108: 86932.92 | G108: 86932.92 | H108: =D108 -> 74942.17 | I108: 46219 | J108: Vigente | K108: Sin pagar | L108: ILSE GARCÍA | M108: Crédito | N108: 46192 | O108: =MONTH(N108) -> 6 | P108: =WEEKNUM(N108) -> 25 | Q108: =IF(J108="Vencido",N108-I108+1,0) -> 0 | R108: =IF(Q108>0,IF(Q108<31,H108,0),0) -> 0 | S108: =IF(Q108>30,IF(Q108<61,H108,0),0) -> 0 | T108: =IF(Q108>60,IF(Q108<91,H108,0),0) -> 0 | U108: =IF(Q108>90,H108,0) -> 0 | V108: =IF(J108="Por vencer",H108,0) -> 0 | W108: =IF(J108="Vigente",H108,0) -> 74942.17
... A130: 46181 | B130: CLN/2026/00147 | C130: JIMMY JAVIER VITE QUIMIZ | D130: 2200 | E130: 352 | F130: 2552 | G130: 2552 | H130: =D130 -> 2200 | I130: 46181 | J130: Vencido | K130: Sin pagar | L130: MATEO LÓPEZ | M130: Contado | N130: 46192 | O130: =MONTH(N130) -> 6 | P130: =WEEKNUM(N130) -> 25 | Q130: =IF(J130="Vencido",N130-I130+1,0) -> 12 | R130: =IF(Q130>0,IF(Q130<31,H130,0),0) -> 2200 | S130: =IF(Q130>30,IF(Q130<61,H130,0),0) -> 0 | T130: =IF(Q130>60,IF(Q130<91,H130,0),0) -> 0 | U130: =IF(Q130>90,H130,0) -> 0 | V130: =IF(J130="Por vencer",H130,0) -> 0 | W130: =IF(J130="Vigente",H130,0) -> 0
A131: 46178 | B131: HMO/2026/00383 | C131: ACUAGRO | D131: 142000 | F131: 142000 | G131: 142000 | H131: =D131 -> 142000 | I131: 46178 | J131: Vencido | K131: Sin pagar | L131: ILSE GARCÍA | M131: Contado | N131: 46192 | O131: =MONTH(N131) -> 6 | P131: =WEEKNUM(N131) -> 25 | Q131: =IF(J131="Vencido",N131-I131+1,0) -> 15 | R131: =IF(Q131>0,IF(Q131<31,H131,0),0) -> 142000 | S131: =IF(Q131>30,IF(Q131<61,H131,0),0) -> 0 | T131: =IF(Q131>60,IF(Q131<91,H131,0),0) -> 0 | U131: =IF(Q131>90,H131,0) -> 0 | V131: =IF(J131="Por vencer",H131,0) -> 0 | W131: =IF(J131="Vigente",H131,0) -> 0
A132: 46178 | B132: CLN/2026/00146 | C132: PLANTA PROCESADORA CAMARONEX | D132: 27000 | E132: 4320 | F132: 31320 | G132: 31320 | H132: =D132 -> 27000 | I132: 46208 | J132: Vigente | K132: Sin pagar | L132: MATEO LÓPEZ | M132: Crédito | N132: 46192 | O132: =MONTH(N132) -> 6 | P132: =WEEKNUM(N132) -> 25 | Q132: =IF(J132="Vencido",N132-I132+1,0) -> 0 | R132: =IF(Q132>0,IF(Q132<31,H132,0),0) -> 0 | S132: =IF(Q132>30,IF(Q132<61,H132,0),0) -> 0 | T132: =IF(Q132>60,IF(Q132<91,H132,0),0) -> 0 | U132: =IF(Q132>90,H132,0) -> 0 | V132: =IF(J132="Por vencer",H132,0) -> 0 | W132: =IF(J132="Vigente",H132,0) -> 27000
A133: 46177 | B133: HMO/2026/00376 | C133: LUCINA YARLIN OCHOA QUIÑONEZ | D133: 16660 | E133: 2665.6 | F133: 19325.6 | G133: 19325.6 | H133: =D133 -> 16660 | I133: 46207 | J133: Vigente | K133: Sin pagar | L133: FREDY SALAS | M133: Crédito | N133: 46192 | O133: =MONTH(N133) -> 6 | P133: =WEEKNUM(N133) -> 25 | Q133: =IF(J133="Vencido",N133-I133+1,0) -> 0 | R133: =IF(Q133>0,IF(Q133<31,H133,0),0) -> 0 | S133: =IF(Q133>30,IF(Q133<61,H133,0),0) -> 0 | T133: =IF(Q133>60,IF(Q133<91,H133,0),0) -> 0 | U133: =IF(Q133>90,H133,0) -> 0 | V133: =IF(J133="Por vencer",H133,0) -> 0 | W133: =IF(J133="Vigente",H133,0) -> 16660
A134: 46177 | B134: HMO/2026/00375 | C134: ACUICOLA BOCA | D134: 9900 | E134: 1584 | F134: 11484 | G134: 11484 | H134: =D134 -> 9900 | I134: 46207 | J134: Vigente | K134: Sin pagar | L134: FREDY SALAS | M134: Crédito | N134: 46192 | O134: =MONTH(N134) -> 6 | P134: =WEEKNUM(N134) -> 25 | Q134: =IF(J134="Vencido",N134-I134+1,0) -> 0 | R134: =IF(Q134>0,IF(Q134<31,H134,0),0) -> 0 | S134: =IF(Q134>30,IF(Q134<61,H134,0),0) -> 0 | T134: =IF(Q134>60,IF(Q134<91,H134,0),0) -> 0 | U134: =IF(Q134>90,H134,0) -> 0 | V134: =IF(J134="Por vencer",H134,0) -> 0 | W134: =IF(J134="Vigente",H134,0) -> 9900
A135: 46174 | B135: HMO/2026/00370 | C135: "PUBLICO EN GENERAL" | D135: 8000 | E135: 1280 | F135: 9280 | G135: 9280 | H135: =D135 -> 8000 | I135: 46174 | J135: Vencido | K135: Sin pagar | L135: ILSE GARCÍA | M135: Contado | N135: 46192 | O135: =MONTH(N135) -> 6 | P135: =WEEKNUM(N135) -> 25 | Q135: =IF(J135="Vencido",N135-I135+1,0) -> 19 | R135: =IF(Q135>0,IF(Q135<31,H135,0),0) -> 8000 | S135: =IF(Q135>30,IF(Q135<61,H135,0),0) -> 0 | T135: =IF(Q135>60,IF(Q135<91,H135,0),0) -> 0 | U135: =IF(Q135>90,H135,0) -> 0 | V135: =IF(J135="Por vencer",H135,0) -> 0 | W135: =IF(J135="Vigente",H135,0) -> 0
A136: 46174 | B136: HMO/2026/00369 | C136: "PUBLICO EN GENERAL" | D136: 8000 | E136: 1280 | F136: 9280 | G136: 9280 | H136: =D136 -> 8000 | I136: 46174 | J136: Vencido | K136: Sin pagar | L136: ILSE GARCÍA | M136: Contado | N136: 46192 | O136: =MONTH(N136) -> 6 | P136: =WEEKNUM(N136) -> 25 | Q136: =IF(J136="Vencido",N136-I136+1,0) -> 19 | R136: =IF(Q136>0,IF(Q136<31,H136,0),0) -> 8000 | S136: =IF(Q136>30,IF(Q136<61,H136,0),0) -> 0 | T136: =IF(Q136>60,IF(Q136<91,H136,0),0) -> 0 | U136: =IF(Q136>90,H136,0) -> 0 | V136: =IF(J136="Por vencer",H136,0) -> 0 | W136: =IF(J136="Vigente",H136,0) -> 0
A137: 46171 | B137: CLN/2026/00143 | C137: WALBRO LOS MOCHIS | D137: 381068.6 | E137: 60970.98 | F137: 442039.58 | G137: 2511.59 | H137: =G137/1.16 -> 2165.1638 | I137: 46201 | J137: Vigente | K137: Pagado parcialmente | L137: ILSE GARCÍA | M137: Crédito | N137: 46192 | O137: =MONTH(N137) -> 6 | P137: =WEEKNUM(N137) -> 25 | Q137: =IF(J137="Vencido",N137-I137+1,0) -> 0 | R137: =IF(Q137>0,IF(Q137<31,H137,0),0) -> 0 | S137: =IF(Q137>30,IF(Q137<61,H137,0),0) -> 0 | T137: =IF(Q137>60,IF(Q137<91,H137,0),0) -> 0 | U137: =IF(Q137>90,H137,0) -> 0 | V137: =IF(J137="Por vencer",H137,0) -> 0 | W137: =IF(J137="Vigente",H137,0) -> 2165.1638
A138: 46170 | B138: HMO/2026/00362 | C138: EULALIO MOLINA TERAN | D138: 42750 | E138: 6840 | F138: 49590 | G138: 49590 | H138: =D138 -> 42750 | I138: 46200 | J138: Vigente | K138: Sin pagar | L138: ILSE GARCÍA | M138: Crédito | N138: 46192 | O138: =MONTH(N138) -> 6 | P138: =WEEKNUM(N138) -> 25 | Q138: =IF(J138="Vencido",N138-I138+1,0) -> 0 | R138: =IF(Q138>0,IF(Q138<31,H138,0),0) -> 0 | S138: =IF(Q138>30,IF(Q138<61,H138,0),0) -> 0 | T138: =IF(Q138>60,IF(Q138<91,H138,0),0) -> 0 | U138: =IF(Q138>90,H138,0) -> 0 | V138: =IF(J138="Por vencer",H138,0) -> 0 | W138: =IF(J138="Vigente",H138,0) -> 42750
A139: 46170 | B139: CLN/2026/00141 | C139: JESUS ESTEBAN CHAVEZ PRECIADO | D139: 46680 | E139: 7468.8 | F139: 54148.8 | G139: 54148.8 | H139: =D139 -> 46680 | I139: 46200 | J139: Vigente | K139: Sin pagar | L139: MATEO LÓPEZ | M139: Crédito | N139: 46192 | O139: =MONTH(N139) -> 6 | P139: =WEEKNUM(N139) -> 25 | Q139: =IF(J139="Vencido",N139-I139+1,0) -> 0 | R139: =IF(Q139>0,IF(Q139<31,H139,0),0) -> 0 | S139: =IF(Q139>30,IF(Q139<61,H139,0),0) -> 0 | T139: =IF(Q139>60,IF(Q139<91,H139,0),0) -> 0 | U139: =IF(Q139>90,H139,0) -> 0 | V139: =IF(J139="Por vencer",H139,0) -> 0 | W139: =IF(J139="Vigente",H139,0) -> 46680
A140: 46169 | B140: HMO/2026/00360 | C140: AGROPECUARIA MONTE SINAI | D140: 7015.9 | F140: 7015.9 | G140: 7015.9 | H140: =D140 -> 7015.9 | I140: 46199 | J140: Por vencer | K140: Sin pagar | L140: ILSE GARCÍA | M140: Crédito | N140: 46192 | O140: =MONTH(N140) -> 6 | P140: =WEEKNUM(N140) -> 25 | Q140: =IF(J140="Vencido",N140-I140+1,0) -> 0 | R140: =IF(Q140>0,IF(Q140<31,H140,0),0) -> 0 | S140: =IF(Q140>30,IF(Q140<61,H140,0),0) -> 0 | T140: =IF(Q140>60,IF(Q140<91,H140,0),0) -> 0 | U140: =IF(Q140>90,H140,0) -> 0 | V140: =IF(J140="Por vencer",H140,0) -> 7015.9 | W140: =IF(J140="Vigente",H140,0) -> 0
A141: 46169 | B141: HMO/2026/00359 | C141: AGROPECUARIA MONTE SINAI | D141: 20000 | F141: 20000 | G141: 20000 | H141: =D141 -> 20000 | I141: 46199 | J141: Por vencer | K141: Sin pagar | L141: ILSE GARCÍA | M141: Crédito | N141: 46192 | O141: =MONTH(N141) -> 6 | P141: =WEEKNUM(N141) -> 25 | Q141: =IF(J141="Vencido",N141-I141+1,0) -> 0 | R141: =IF(Q141>0,IF(Q141<31,H141,0),0) -> 0 | S141: =IF(Q141>30,IF(Q141<61,H141,0),0) -> 0 | T141: =IF(Q141>60,IF(Q141<91,H141,0),0) -> 0 | U141: =IF(Q141>90,H141,0) -> 0 | V141: =IF(J141="Por vencer",H141,0) -> 20000 | W141: =IF(J141="Vigente",H141,0) -> 0
A142: 46169 | B142: CLN/2026/00140 | C142: AGRO PRODUCTOS BALEY | D142: 27200 | E142: 4352 | F142: 31552 | G142: 31552 | H142: =D142 -> 27200 | I142: 46199 | J142: Por vencer | K142: Sin pagar | L142: MATEO LÓPEZ | M142: Crédito | N142: 46192 | O142: =MONTH(N142) -> 6 | P142: =WEEKNUM(N142) -> 25 | Q142: =IF(J142="Vencido",N142-I142+1,0) -> 0 | R142: =IF(Q142>0,IF(Q142<31,H142,0),0) -> 0 | S142: =IF(Q142>30,IF(Q142<61,H142,0),0) -> 0 | T142: =IF(Q142>60,IF(Q142<91,H142,0),0) -> 0 | U142: =IF(Q142>90,H142,0) -> 0 | V142: =IF(J142="Por vencer",H142,0) -> 27200 | W142: =IF(J142="Vigente",H142,0) -> 0
A143: 46168 | B143: HMO/2026/00357 | C143: ABASTECEDORA HIGIENICA DE SONORA | D143: 17099.28 | E143: 2735.88 | F143: 19835.16 | G143: 19835.16 | H143: =D143 -> 17099.28 | I143: 46198 | J143: Por vencer | K143: Sin pagar | L143: ILSE GARCÍA | M143: Crédito | N143: 46192 | O143: =MONTH(N143) -> 6 | P143: =WEEKNUM(N143) -> 25 | Q143: =IF(J143="Vencido",N143-I143+1,0) -> 0 | R143: =IF(Q143>0,IF(Q143<31,H143,0),0) -> 0 | S143: =IF(Q143>30,IF(Q143<61,H143,0),0) -> 0 | T143: =IF(Q143>60,IF(Q143<91,H143,0),0) -> 0 | U143: =IF(Q143>90,H143,0) -> 0 | V143: =IF(J143="Por vencer",H143,0) -> 17099.28 | W143: =IF(J143="Vigente",H143,0) -> 0
A144: 46168 | B144: HMO/2026/00350 | C144: INSECTICIDAS DEL PACIFICO | D144: 9689.59 | E144: 1550.33 | F144: 11239.92 | G144: 11239.92 | H144: =D144 -> 9689.59 | I144: 46198 | J144: Por vencer | K144: Sin pagar | L144: ILSE GARCÍA | M144: Crédito | N144: 46192 | O144: =MONTH(N144) -> 6 | P144: =WEEKNUM(N144) -> 25 | Q144: =IF(J144="Vencido",N144-I144+1,0) -> 0 | R144: =IF(Q144>0,IF(Q144<31,H144,0),0) -> 0 | S144: =IF(Q144>30,IF(Q144<61,H144,0),0) -> 0 | T144: =IF(Q144>60,IF(Q144<91,H144,0),0) -> 0 | U144: =IF(Q144>90,H144,0) -> 0 | V144: =IF(J144="Por vencer",H144,0) -> 9689.59 | W144: =IF(J144="Vigente",H144,0) -> 0
A145: 46167 | B145: HMO/2026/00348 | C145: EDITH CABRERA GARCIA | D145: 9000 | E145: 1440 | F145: 10440 | G145: 10440 | H145: =D145 -> 9000 | I145: 46197 | J145: Por vencer | K145: Sin pagar | L145: ILSE GARCÍA | M145: Crédito | N145: 46192 | O145: =MONTH(N145) -> 6 | P145: =WEEKNUM(N145) -> 25 | Q145: =IF(J145="Vencido",N145-I145+1,0) -> 0 | R145: =IF(Q145>0,IF(Q145<31,H145,0),0) -> 0 | S145: =IF(Q145>30,IF(Q145<61,H145,0),0) -> 0 | T145: =IF(Q145>60,IF(Q145<91,H145,0),0) -> 0 | U145: =IF(Q145>90,H145,0) -> 0 | V145: =IF(J145="Por vencer",H145,0) -> 9000 | W145: =IF(J145="Vigente",H145,0) -> 0
A146: 46164 | B146: HMO/2026/00347 | C146: NRW CHEMIE MEXICANA | D146: 66167.85 | E146: 10586.86 | F146: 76754.71 | G146: 76754.71 | H146: =D146 -> 66167.85 | I146: 46194 | J146: Por vencer | K146: Sin pagar | L146: ILSE GARCÍA | M146: Crédito | N146: 46192 | O146: =MONTH(N146) -> 6 | P146: =WEEKNUM(N146) -> 25 | Q146: =IF(J146="Vencido",N146-I146+1,0) -> 0 | R146: =IF(Q146>0,IF(Q146<31,H146,0),0) -> 0 | S146: =IF(Q146>30,IF(Q146<61,H146,0),0) -> 0 | T146: =IF(Q146>60,IF(Q146<91,H146,0),0) -> 0 | U146: =IF(Q146>90,H146,0) -> 0 | V146: =IF(J146="Por vencer",H146,0) -> 66167.85 | W146: =IF(J146="Vigente",H146,0) -> 0
A147: 46164 | B147: CLN/2026/00135 | C147: PLANTA PROCESADORA CAMARONEX | D147: 27000 | E147: 4320 | F147: 31320 | G147: 31320 | H147: =D147 -> 27000 | I147: 46194 | J147: Por vencer | K147: Sin pagar | L147: MATEO LÓPEZ | M147: Crédito | N147: 46192 | O147: =MONTH(N147) -> 6 | P147: =WEEKNUM(N147) -> 25 | Q147: =IF(J147="Vencido",N147-I147+1,0) -> 0 | R147: =IF(Q147>0,IF(Q147<31,H147,0),0) -> 0 | S147: =IF(Q147>30,IF(Q147<61,H147,0),0) -> 0 | T147: =IF(Q147>60,IF(Q147<91,H147,0),0) -> 0 | U147: =IF(Q147>90,H147,0) -> 0 | V147: =IF(J147="Por vencer",H147,0) -> 27000 | W147: =IF(J147="Vigente",H147,0) -> 0
A148: 46164 | B148: CLN/2026/00134 | C148: QMX4 | D148: 46200 | E148: 7392 | F148: 53592 | G148: 53592 | H148: =D148 -> 46200 | I148: 46194 | J148: Por vencer | K148: Sin pagar | L148: FREDY SALAS | M148: Crédito | N148: 46192 | O148: =MONTH(N148) -> 6 | P148: =WEEKNUM(N148) -> 25 | Q148: =IF(J148="Vencido",N148-I148+1,0) -> 0 | R148: =IF(Q148>0,IF(Q148<31,H148,0),0) -> 0 | S148: =IF(Q148>30,IF(Q148<61,H148,0),0) -> 0 | T148: =IF(Q148>60,IF(Q148<91,H148,0),0) -> 0 | U148: =IF(Q148>90,H148,0) -> 0 | V148: =IF(J148="Por vencer",H148,0) -> 46200 | W148: =IF(J148="Vigente",H148,0) -> 0
A149: 46163 | B149: HMO/2026/00345 | C149: BIOMA FORMULACIONES | D149: 110611.14 | E149: 17697.78 | F149: 128308.92 | G149: 128308.92 | H149: =D149 -> 110611.14 | I149: 46193 | J149: Por vencer | K149: Sin pagar | L149: ILSE GARCÍA | M149: Crédito | N149: 46192 | O149: =MONTH(N149) -> 6 | P149: =WEEKNUM(N149) -> 25 | Q149: =IF(J149="Vencido",N149-I149+1,0) -> 0 | R149: =IF(Q149>0,IF(Q149<31,H149,0),0) -> 0 | S149: =IF(Q149>30,IF(Q149<61,H149,0),0) -> 0 | T149: =IF(Q149>60,IF(Q149<91,H149,0),0) -> 0 | U149: =IF(Q149>90,H149,0) -> 0 | V149: =IF(J149="Por vencer",H149,0) -> 110611.14 | W149: =IF(J149="Vigente",H149,0) -> 0
A150: 46162 | B150: CLN/2026/00131 | C150: AQUA DUX DE MEXICO | D150: 12000 | E150: 1920 | F150: 13920 | G150: 13920 | H150: =D150 -> 12000 | I150: 46192 | J150: Vencido | K150: Sin pagar | L150: FREDY SALAS | M150: Crédito | N150: 46192 | O150: =MONTH(N150) -> 6 | P150: =WEEKNUM(N150) -> 25 | Q150: =IF(J150="Vencido",N150-I150+1,0) -> 1 | R150: =IF(Q150>0,IF(Q150<31,H150,0),0) -> 12000 | S150: =IF(Q150>30,IF(Q150<61,H150,0),0) -> 0 | T150: =IF(Q150>60,IF(Q150<91,H150,0),0) -> 0 | U150: =IF(Q150>90,H150,0) -> 0 | V150: =IF(J150="Por vencer",H150,0) -> 0 | W150: =IF(J150="Vigente",H150,0) -> 0
A151: 46161 | B151: HMO/2026/00342 | C151: GRUBOSA COMERCIAL | D151: 7905 | E151: 1264.8 | F151: 9169.8 | G151: 9169.8 | H151: =D151 -> 7905 | I151: 46191 | J151: Vencido | K151: Sin pagar | L151: MATEO LÓPEZ | M151: Crédito | N151: 46192 | O151: =MONTH(N151) -> 6 | P151: =WEEKNUM(N151) -> 25 | Q151: =IF(J151="Vencido",N151-I151+1,0) -> 2 | R151: =IF(Q151>0,IF(Q151<31,H151,0),0) -> 7905 | S151: =IF(Q151>30,IF(Q151<61,H151,0),0) -> 0 | T151: =IF(Q151>60,IF(Q151<91,H151,0),0) -> 0 | U151: =IF(Q151>90,H151,0) -> 0 | V151: =IF(J151="Por vencer",H151,0) -> 0 | W151: =IF(J151="Vigente",H151,0) -> 0
A152: 46160 | B152: HMO/2026/00338 | C152: ALTERA PUBLICIDAD | D152: 82000 | E152: 13120 | F152: 95120 | G152: 95120 | H152: =D152 -> 82000 | I152: 46205 | J152: Vigente | K152: Sin pagar | L152: ILSE GARCÍA | M152: Crédito | N152: 46192 | O152: =MONTH(N152) -> 6 | P152: =WEEKNUM(N152) -> 25 | Q152: =IF(J152="Vencido",N152-I152+1,0) -> 0 | R152: =IF(Q152>0,IF(Q152<31,H152,0),0) -> 0 | S152: =IF(Q152>30,IF(Q152<61,H152,0),0) -> 0 | T152: =IF(Q152>60,IF(Q152<91,H152,0),0) -> 0 | U152: =IF(Q152>90,H152,0) -> 0 | V152: =IF(J152="Por vencer",H152,0) -> 0 | W152: =IF(J152="Vigente",H152,0) -> 82000
...

Sheet BD CxP
A1: Número | B1: Origen | C1: Proveedor | D1: Referencia | E1: Fecha de factura | F1: Fecha vencimiento | G1: Divisa | H1: Importe | I1: Impuesto | J1: Total | K1: Total en divisa | L1: Importe adeudado | M1: Estado de pago | N1: Vendedor | O1: Fecha pago | P1: Dias de crédito | Q1: Condición | R1: Día vencimiento | S1: Mes vencimiento | T1: Año vencimiento | U1: Día factura | V1: Mes factura | W1: Año factura | X1: Importe | Y1: Total | Z1: Estatus | AA1: Fecha | AB1: Mes | AC1: Semana | AD1: Dias vencido | AE1: Vencido 0-30 días | AF1: Vencido 31-60 días | AG1: Vencido >60 días | AH1: Vigente | AJ1: ESTADO DE PAGO: SOLO SIN PAGAR, las abonadas se eliminan de las cuentas por pagar? | AO1: SOLENIS SOLO LAS DE LIDERZA
A2: BILL/2026/06/0061 | B2: OC02585 | C2: ORBEX CHEMICAL | D2: HMO-25156 | E2: 46192 | F2: 46222 | G2: MXN | H2: -1200 | I2: -192 | J2: -1392 | K2: -1392 | L2: 1392 | M2: Sin pagar | N2: IRLANDA ROJO | P2: =+F2-E2 -> 30 | Q2: =IF(P2>1,"Crédito","Contado") -> Crédito | R2: =DAY(F2) -> 19 | S2: =MONTH(F2) -> 7 | T2: =YEAR(F2) -> 2026 | U2: =DAY(E2) -> 19 | V2: =MONTH(E2) -> 6 | W2: =YEAR(E2) -> 2026 | X2: =+H2*-1 -> 1200 | Y2: =+J2*-1 -> 1392 | Z2: =IF(F2>AA2,"Vigente","Vencido") -> Vigente | AA2: 46199 | AB2: =MONTH(AA2) -> 6 | AC2: =WEEKNUM(AA2) -> 26 | AD2: =IF(Z2="Vencido",AA2-F2+1,0) -> 0 | AE2: =IF(AD2>0,IF(AD2<31,X2,0),0) -> 0 | AF2: =IF(AD2>30,IF(AD2<61,X2,0),0) -> 0 | AG2: =IF(AD2>60,X2,0) -> 0 | AH2: =IF(Z2="Vigente",X2,0) -> 1200
A3: BILL/2026/06/0060 | B3: OC02591 | C3: ORBEX CHEMICAL | D3: HMO-25157 | E3: 46192 | F3: 46222 | G3: USD | H3: -27720.6 | I3: -4435.3 | J3: -32155.9 | K3: -1851.36 | L3: 1851.36 | M3: Sin pagar | N3: IRLANDA ROJO | P3: =+F3-E3 -> 30 | Q3: =IF(P3>1,"Crédito","Contado") -> Crédito | R3: =DAY(F3) -> 19 | S3: =MONTH(F3) -> 7 | T3: =YEAR(F3) -> 2026 | U3: =DAY(E3) -> 19 | V3: =MONTH(E3) -> 6 | W3: =YEAR(E3) -> 2026 | X3: =+H3*-1 -> 27720.6 | Y3: =+J3*-1 -> 32155.9 | Z3: =IF(F3>AA3,"Vigente","Vencido") -> Vigente | AA3: 46199 | AB3: =MONTH(AA3) -> 6 | AC3: =WEEKNUM(AA3) -> 26 | AD3: =IF(Z3="Vencido",AA3-F3+1,0) -> 0 | AE3: =IF(AD3>0,IF(AD3<31,X3,0),0) -> 0 | AF3: =IF(AD3>30,IF(AD3<61,X3,0),0) -> 0 | AG3: =IF(AD3>60,X3,0) -> 0 | AH3: =IF(Z3="Vigente",X3,0) -> 27720.6
A4: BILL/2026/06/0059 | B4: OC02590 | C4: AUROQUIM | D4: AA 16301 | E4: 46195 | F4: 46215 | G4: MXN | H4: -64297.8 | I4: -10287.65 | J4: -74585.45 | K4: -74585.45 | L4: 74585.45 | M4: Sin pagar | N4: IRLANDA ROJO | P4: =+F4-E4 -> 20 | Q4: =IF(P4>1,"Crédito","Contado") -> Crédito | R4: =DAY(F4) -> 12 | S4: =MONTH(F4) -> 7 | T4: =YEAR(F4) -> 2026 | U4: =DAY(E4) -> 22 | V4: =MONTH(E4) -> 6 | W4: =YEAR(E4) -> 2026 | X4: =+H4*-1 -> 64297.8 | Y4: =+J4*-1 -> 74585.45 | Z4: =IF(F4>AA4,"Vigente","Vencido") -> Vigente | AA4: 46199 | AB4: =MONTH(AA4) -> 6 | AC4: =WEEKNUM(AA4) -> 26 | AD4: =IF(Z4="Vencido",AA4-F4+1,0) -> 0 | AE4: =IF(AD4>0,IF(AD4<31,X4,0),0) -> 0 | AF4: =IF(AD4>30,IF(AD4<61,X4,0),0) -> 0 | AG4: =IF(AD4>60,X4,0) -> 0 | AH4: =IF(Z4="Vigente",X4,0) -> 64297.8
A5: BILL/2026/06/0054 | B5: OC02572 | C5: WEGOCHEM MEXICANA | D5: 12003081- | E5: 46185 | F5: 46215 | G5: USD | H5: -44327.42 | I5: -7092.39 | J5: -51419.81 | K5: -2958 | L5: 2958 | M5: Sin pagar | N5: IRLANDA ROJO | P5: =+F5-E5 -> 30 | Q5: =IF(P5>1,"Crédito","Contado") -> Crédito | R5: =DAY(F5) -> 12 | S5: =MONTH(F5) -> 7 | T5: =YEAR(F5) -> 2026 | U5: =DAY(E5) -> 12 | V5: =MONTH(E5) -> 6 | W5: =YEAR(E5) -> 2026 | X5: =+H5*-1 -> 44327.42 | Y5: =+J5*-1 -> 51419.81 | Z5: =IF(F5>AA5,"Vigente","Vencido") -> Vigente | AA5: 46199 | AB5: =MONTH(AA5) -> 6 | AC5: =WEEKNUM(AA5) -> 26 | AD5: =IF(Z5="Vencido",AA5-F5+1,0) -> 0 | AE5: =IF(AD5>0,IF(AD5<31,X5,0),0) -> 0 | AF5: =IF(AD5>30,IF(AD5<61,X5,0),0) -> 0 | AG5: =IF(AD5>60,X5,0) -> 0 | AH5: =IF(Z5="Vigente",X5,0) -> 44327.42
A6: BILL/2026/06/0053 | B6: OC02563 | C6: WEGOCHEM MEXICANA | D6: 12003081 | E6: 46185 | F6: 46215 | G6: USD | H6: -132982.25 | I6: -21277.16 | J6: -154259.41 | K6: -8874 | L6: 8874 | M6: Sin pagar | N6: IRLANDA ROJO | P6: =+F6-E6 -> 30 | Q6: =IF(P6>1,"Crédito","Contado") -> Crédito | R6: =DAY(F6) -> 12 | S6: =MONTH(F6) -> 7 | T6: =YEAR(F6) -> 2026 | U6: =DAY(E6) -> 12 | V6: =MONTH(E6) -> 6 | W6: =YEAR(E6) -> 2026 | X6: =+H6*-1 -> 132982.25 | Y6: =+J6*-1 -> 154259.41 | Z6: =IF(F6>AA6,"Vigente","Vencido") -> Vigente | AA6: 46199 | AB6: =MONTH(AA6) -> 6 | AC6: =WEEKNUM(AA6) -> 26 | AD6: =IF(Z6="Vencido",AA6-F6+1,0) -> 0 | AE6: =IF(AD6>0,IF(AD6<31,X6,0),0) -> 0 | AF6: =IF(AD6>30,IF(AD6<61,X6,0),0) -> 0 | AG6: =IF(AD6>60,X6,0) -> 0 | AH6: =IF(Z6="Vigente",X6,0) -> 132982.25
A7: BILL/2026/06/0052 | B7: OC02559 | C7: REACCIONES QUIMICAS | D7: 62616 | E7: 46188 | F7: 46218 | G7: MXN | H7: -22104 | I7: -3536.64 | J7: -25640.64 | K7: -25640.64 | L7: 25640.64 | M7: Sin pagar | N7: IRLANDA ROJO | P7: =+F7-E7 -> 30 | Q7: =IF(P7>1,"Crédito","Contado") -> Crédito | R7: =DAY(F7) -> 15 | S7: =MONTH(F7) -> 7 | T7: =YEAR(F7) -> 2026 | U7: =DAY(E7) -> 15 | V7: =MONTH(E7) -> 6 | W7: =YEAR(E7) -> 2026 | X7: =+H7*-1 -> 22104 | Y7: =+J7*-1 -> 25640.64 | Z7: =IF(F7>AA7,"Vigente","Vencido") -> Vigente | AA7: 46199 | AB7: =MONTH(AA7) -> 6 | AC7: =WEEKNUM(AA7) -> 26 | AD7: =IF(Z7="Vencido",AA7-F7+1,0) -> 0 | AE7: =IF(AD7>0,IF(AD7<31,X7,0),0) -> 0 | AF7: =IF(AD7>30,IF(AD7<61,X7,0),0) -> 0 | AG7: =IF(AD7>60,X7,0) -> 0 | AH7: =IF(Z7="Vigente",X7,0) -> 22104
A8: BILL/2026/06/0051 | B8: OC02567 | C8: REACCIONES QUIMICAS | D8: 62617 | E8: 46188 | F8: 46218 | G8: MXN | H8: -22104 | I8: -3536.64 | J8: -25640.64 | K8: -25640.64 | L8: 25640.64 | M8: Sin pagar | N8: IRLANDA ROJO | P8: =+F8-E8 -> 30 | Q8: =IF(P8>1,"Crédito","Contado") -> Crédito | R8: =DAY(F8) -> 15 | S8: =MONTH(F8) -> 7 | T8: =YEAR(F8) -> 2026 | U8: =DAY(E8) -> 15 | V8: =MONTH(E8) -> 6 | W8: =YEAR(E8) -> 2026 | X8: =+H8*-1 -> 22104 | Y8: =+J8*-1 -> 25640.64 | Z8: =IF(F8>AA8,"Vigente","Vencido") -> Vigente | AA8: 46199 | AB8: =MONTH(AA8) -> 6 | AC8: =WEEKNUM(AA8) -> 26 | AD8: =IF(Z8="Vencido",AA8-F8+1,0) -> 0 | AE8: =IF(AD8>0,IF(AD8<31,X8,0),0) -> 0 | AF8: =IF(AD8>30,IF(AD8<61,X8,0),0) -> 0 | AG8: =IF(AD8>60,X8,0) -> 0 | AH8: =IF(Z8="Vigente",X8,0) -> 22104
A9: BILL/2026/06/0050 | B9: OC02575 | C9: REACCIONES QUIMICAS | D9: 62628 | E9: 46189 | F9: 46219 | G9: MXN | H9: -44208 | I9: -7073.28 | J9: -51281.28 | K9: -51281.28 | L9: 51281.28 | M9: Sin pagar | N9: IRLANDA ROJO | P9: =+F9-E9 -> 30 | Q9: =IF(P9>1,"Crédito","Contado") -> Crédito | R9: =DAY(F9) -> 16 | S9: =MONTH(F9) -> 7 | T9: =YEAR(F9) -> 2026 | U9: =DAY(E9) -> 16 | V9: =MONTH(E9) -> 6 | W9: =YEAR(E9) -> 2026 | X9: =+H9*-1 -> 44208 | Y9: =+J9*-1 -> 51281.28 | Z9: =IF(F9>AA9,"Vigente","Vencido") -> Vigente | AA9: 46199 | AB9: =MONTH(AA9) -> 6 | AC9: =WEEKNUM(AA9) -> 26 | AD9: =IF(Z9="Vencido",AA9-F9+1,0) -> 0 | AE9: =IF(AD9>0,IF(AD9<31,X9,0),0) -> 0 | AF9: =IF(AD9>30,IF(AD9<61,X9,0),0) -> 0 | AG9: =IF(AD9>60,X9,0) -> 0 | AH9: =IF(Z9="Vigente",X9,0) -> 44208
A10: BILL/2026/06/0049 | B10: OC02587 | C10: NRW CHEMIE MEXICANA | D10: OBR38398 | E10: 46190 | F10: 46220 | G10: USD | H10: -2085.78 | I10: -333.72 | J10: -2419.5 | K10: -140.65 | L10: 140.65 | M10: Sin pagar | N10: IRLANDA ROJO | P10: =+F10-E10 -> 30 | Q10: =IF(P10>1,"Crédito","Contado") -> Crédito | R10: =DAY(F10) -> 17 | S10: =MONTH(F10) -> 7 | T10: =YEAR(F10) -> 2026 | U10: =DAY(E10) -> 17 | V10: =MONTH(E10) -> 6 | W10: =YEAR(E10) -> 2026 | X10: =+H10*-1 -> 2085.78 | Y10: =+J10*-1 -> 2419.5 | Z10: =IF(F10>AA10,"Vigente","Vencido") -> Vigente | AA10: 46199 | AB10: =MONTH(AA10) -> 6 | AC10: =WEEKNUM(AA10) -> 26 | AD10: =IF(Z10="Vencido",AA10-F10+1,0) -> 0 | AE10: =IF(AD10>0,IF(AD10<31,X10,0),0) -> 0 | AF10: =IF(AD10>30,IF(AD10<61,X10,0),0) -> 0 | AG10: =IF(AD10>60,X10,0) -> 0 | AH10: =IF(Z10="Vigente",X10,0) -> 2085.78
A11: BILL/2026/06/0043 | B11: OC02532 | C11: REACCIONES QUIMICAS | D11: 62530 | E11: 46176 | F11: 46206 | G11: MXN | H11: -121572 | I11: -19451.52 | J11: -141023.52 | K11: -141023.52 | L11: 141023.52 | M11: Sin pagar | N11: IRLANDA ROJO | P11: =+F11-E11 -> 30 | Q11: =IF(P11>1,"Crédito","Contado") -> Crédito | R11: =DAY(F11) -> 3 | S11: =MONTH(F11) -> 7 | T11: =YEAR(F11) -> 2026 | U11: =DAY(E11) -> 3 | V11: =MONTH(E11) -> 6 | W11: =YEAR(E11) -> 2026 | X11: =+H11*-1 -> 121572 | Y11: =+J11*-1 -> 141023.52 | Z11: =IF(F11>AA11,"Vigente","Vencido") -> Vigente | AA11: 46199 | AB11: =MONTH(AA11) -> 6 | AC11: =WEEKNUM(AA11) -> 26 | AD11: =IF(Z11="Vencido",AA11-F11+1,0) -> 0 | AE11: =IF(AD11>0,IF(AD11<31,X11,0),0) -> 0 | AF11: =IF(AD11>30,IF(AD11<61,X11,0),0) -> 0 | AG11: =IF(AD11>60,X11,0) -> 0 | AH11: =IF(Z11="Vigente",X11,0) -> 121572
A12: BILL/2026/06/0042 | B12: OC02554 | C12: ALKEM INDUSTRIAS | D12: M 69787- | E12: 46185 | F12: 46215 | G12: USD | H12: -18513.21 | I12: -2962.11 | J12: -21475.32 | K12: -1235.4 | L12: 1235.4 | M12: Sin pagar | N12: IRLANDA ROJO | P12: =+F12-E12 -> 30 | Q12: =IF(P12>1,"Crédito","Contado") -> Crédito | R12: =DAY(F12) -> 12 | S12: =MONTH(F12) -> 7 | T12: =YEAR(F12) -> 2026 | U12: =DAY(E12) -> 12 | V12: =MONTH(E12) -> 6 | W12: =YEAR(E12) -> 2026 | X12: =+H12*-1 -> 18513.21 | Y12: =+J12*-1 -> 21475.32 | Z12: =IF(F12>AA12,"Vigente","Vencido") -> Vigente | AA12: 46199 | AB12: =MONTH(AA12) -> 6 | AC12: =WEEKNUM(AA12) -> 26 | AD12: =IF(Z12="Vencido",AA12-F12+1,0) -> 0 | AE12: =IF(AD12>0,IF(AD12<31,X12,0),0) -> 0 | AF12: =IF(AD12>30,IF(AD12<61,X12,0),0) -> 0 | AG12: =IF(AD12>60,X12,0) -> 0 | AH12: =IF(Z12="Vigente",X12,0) -> 18513.21
A13: BILL/2026/06/0041 | B13: OC02544 | C13: ALKEM INDUSTRIAS | D13: M 69787 | E13: 46185 | F13: 46215 | G13: USD | H13: -74052.86 | I13: -11848.46 | J13: -85901.32 | K13: -4941.6 | L13: 4941.6 | M13: Sin pagar | N13: IRLANDA ROJO | P13: =+F13-E13 -> 30 | Q13: =IF(P13>1,"Crédito","Contado") -> Crédito | R13: =DAY(F13) -> 12 | S13: =MONTH(F13) -> 7 | T13: =YEAR(F13) -> 2026 | U13: =DAY(E13) -> 12 | V13: =MONTH(E13) -> 6 | W13: =YEAR(E13) -> 2026 | X13: =+H13*-1 -> 74052.86 | Y13: =+J13*-1 -> 85901.32 | Z13: =IF(F13>AA13,"Vigente","Vencido") -> Vigente | AA13: 46199 | AB13: =MONTH(AA13) -> 6 | AC13: =WEEKNUM(AA13) -> 26 | AD13: =IF(Z13="Vencido",AA13-F13+1,0) -> 0 | AE13: =IF(AD13>0,IF(AD13<31,X13,0),0) -> 0 | AF13: =IF(AD13>30,IF(AD13<61,X13,0),0) -> 0 | AG13: =IF(AD13>60,X13,0) -> 0 | AH13: =IF(Z13="Vigente",X13,0) -> 74052.86
... A20: BILL/2026/06/0034 | B20: OC02560 | C20: COMERCIALIZADORA LAFEL DE CULIACAN | D20: F9667 | E20: 46184 | F20: 46214 | G20: MXN | H20: -11110 | I20: -1777.6 | J20: -12887.6 | K20: -12887.6 | L20: 12887.6 | M20: Sin pagar | N20: IRLANDA ROJO | P20: =+F20-E20 -> 30 | Q20: =IF(P20>1,"Crédito","Contado") -> Crédito | R20: =DAY(F20) -> 11 | S20: =MONTH(F20) -> 7 | T20: =YEAR(F20) -> 2026 | U20: =DAY(E20) -> 11 | V20: =MONTH(E20) -> 6 | W20: =YEAR(E20) -> 2026 | X20: =+H20*-1 -> 11110 | Y20: =+J20*-1 -> 12887.6 | Z20: =IF(F20>AA20,"Vigente","Vencido") -> Vigente | AA20: 46199 | AB20: =MONTH(AA20) -> 6 | AC20: =WEEKNUM(AA20) -> 26 | AD20: =IF(Z20="Vencido",AA20-F20+1,0) -> 0 | AE20: =IF(AD20>0,IF(AD20<31,X20,0),0) -> 0 | AF20: =IF(AD20>30,IF(AD20<61,X20,0),0) -> 0 | AG20: =IF(AD20>60,X20,0) -> 0 | AH20: =IF(Z20="Vigente",X20,0) -> 11110
A21: BILL/2026/06/0033 | B21: OC02545 | C21: NATRIUM DE MEXICO | D21: 398 | E21: 46184 | F21: 46214 | G21: USD | H21: -105903.88 | J21: -105903.88 | K21: -6090 | L21: 6090 | M21: Sin pagar | N21: IRLANDA ROJO | P21: =+F21-E21 -> 30 | Q21: =IF(P21>1,"Crédito","Contado") -> Crédito | R21: =DAY(F21) -> 11 | S21: =MONTH(F21) -> 7 | T21: =YEAR(F21) -> 2026 | U21: =DAY(E21) -> 11 | V21: =MONTH(E21) -> 6 | W21: =YEAR(E21) -> 2026 | X21: =+H21*-1 -> 105903.88 | Y21: =+J21*-1 -> 105903.88 | Z21: =IF(F21>AA21,"Vigente","Vencido") -> Vigente | AA21: 46199 | AB21: =MONTH(AA21) -> 6 | AC21: =WEEKNUM(AA21) -> 26 | AD21: =IF(Z21="Vencido",AA21-F21+1,0) -> 0 | AE21: =IF(AD21>0,IF(AD21<31,X21,0),0) -> 0 | AF21: =IF(AD21>30,IF(AD21<61,X21,0),0) -> 0 | AG21: =IF(AD21>60,X21,0) -> 0 | AH21: =IF(Z21="Vigente",X21,0) -> 105903.88
A22: BILL/2026/06/0019 | B22: OC02411 | C22: SOLENIS TECHNOLOGIES MEXICO | D22: 0135775783 | E22: 46181 | F22: 46241 | G22: USD | H22: -1115915.7 | I22: -178546.51 | J22: -1294462.2 | K22: -74072.97 | L22: 74072.97 | M22: Sin pagar | N22: IRLANDA ROJO | P22: =+F22-E22 -> 60 | Q22: =IF(P22>1,"Crédito","Contado") -> Crédito | R22: =DAY(F22) -> 7 | S22: =MONTH(F22) -> 8 | T22: =YEAR(F22) -> 2026 | U22: =DAY(E22) -> 8 | V22: =MONTH(E22) -> 6 | W22: =YEAR(E22) -> 2026 | X22: =+H22*-1 -> 1115915.7 | Y22: =+J22*-1 -> 1294462.2 | Z22: =IF(F22>AA22,"Vigente","Vencido") -> Vigente | AA22: 46199 | AB22: =MONTH(AA22) -> 6 | AC22: =WEEKNUM(AA22) -> 26 | AD22: =IF(Z22="Vencido",AA22-F22+1,0) -> 0 | AE22: =IF(AD22>0,IF(AD22<31,X22,0),0) -> 0 | AF22: =IF(AD22>30,IF(AD22<61,X22,0),0) -> 0 | AG22: =IF(AD22>60,X22,0) -> 0 | AH22: =IF(Z22="Vigente",X22,0) -> 1115915.7
A23: BILL/2026/06/0018 | B23: OC02470 | C23: ORBEX CHEMICAL | D23: HMO-25050 | E23: 46181 | F23: 46211 | G23: USD | H23: -171431.16 | I23: -27428.99 | J23: -198860.15 | K23: -11379.37 | L23: 11379.37 | M23: Sin pagar | N23: IRLANDA ROJO | P23: =+F23-E23 -> 30 | Q23: =IF(P23>1,"Crédito","Contado") -> Crédito | R23: =DAY(F23) -> 8 | S23: =MONTH(F23) -> 7 | T23: =YEAR(F23) -> 2026 | U23: =DAY(E23) -> 8 | V23: =MONTH(E23) -> 6 | W23: =YEAR(E23) -> 2026 | X23: =+H23*-1 -> 171431.16 | Y23: =+J23*-1 -> 198860.15 | Z23: =IF(F23>AA23,"Vigente","Vencido") -> Vigente | AA23: 46199 | AB23: =MONTH(AA23) -> 6 | AC23: =WEEKNUM(AA23) -> 26 | AD23: =IF(Z23="Vencido",AA23-F23+1,0) -> 0 | AE23: =IF(AD23>0,IF(AD23<31,X23,0),0) -> 0 | AF23: =IF(AD23>30,IF(AD23<61,X23,0),0) -> 0 | AG23: =IF(AD23>60,X23,0) -> 0 | AH23: =IF(Z23="Vigente",X23,0) -> 171431.16
A24: BILL/2026/06/0017 | B24: OC02523 | C24: POLAQUIMIA | D24: 225801 | E24: 46176 | F24: 46206 | G24: USD | H24: -22413.67 | I24: -3586.19 | J24: -25999.86 | K24: -1503.36 | L24: 1503.36 | M24: Sin pagar | N24: IRLANDA ROJO | P24: =+F24-E24 -> 30 | Q24: =IF(P24>1,"Crédito","Contado") -> Crédito | R24: =DAY(F24) -> 3 | S24: =MONTH(F24) -> 7 | T24: =YEAR(F24) -> 2026 | U24: =DAY(E24) -> 3 | V24: =MONTH(E24) -> 6 | W24: =YEAR(E24) -> 2026 | X24: =+H24*-1 -> 22413.67 | Y24: =+J24*-1 -> 25999.86 | Z24: =IF(F24>AA24,"Vigente","Vencido") -> Vigente | AA24: 46199 | AB24: =MONTH(AA24) -> 6 | AC24: =WEEKNUM(AA24) -> 26 | AD24: =IF(Z24="Vencido",AA24-F24+1,0) -> 0 | AE24: =IF(AD24>0,IF(AD24<31,X24,0),0) -> 0 | AF24: =IF(AD24>30,IF(AD24<61,X24,0),0) -> 0 | AG24: =IF(AD24>60,X24,0) -> 0 | AH24: =IF(Z24="Vigente",X24,0) -> 22413.67
A25: BILL/2026/06/0013 | B25: OC02531 | C25: MAXICHEMICAL | D25: A - 38031 | E25: 46175 | F25: 46205 | G25: MXN | H25: -475 | I25: -76 | J25: -551 | K25: -551 | L25: 551 | M25: Sin pagar | N25: IRLANDA ROJO | P25: =+F25-E25 -> 30 | Q25: =IF(P25>1,"Crédito","Contado") -> Crédito | R25: =DAY(F25) -> 2 | S25: =MONTH(F25) -> 7 | T25: =YEAR(F25) -> 2026 | U25: =DAY(E25) -> 2 | V25: =MONTH(E25) -> 6 | W25: =YEAR(E25) -> 2026 | X25: =+H25*-1 -> 475 | Y25: =+J25*-1 -> 551 | Z25: =IF(F25>AA25,"Vigente","Vencido") -> Vigente | AA25: 46199 | AB25: =MONTH(AA25) -> 6 | AC25: =WEEKNUM(AA25) -> 26 | AD25: =IF(Z25="Vencido",AA25-F25+1,0) -> 0 | AE25: =IF(AD25>0,IF(AD25<31,X25,0),0) -> 0 | AF25: =IF(AD25>30,IF(AD25<61,X25,0),0) -> 0 | AG25: =IF(AD25>60,X25,0) -> 0 | AH25: =IF(Z25="Vigente",X25,0) -> 475
A26: BILL/2026/06/0012 | B26: OC02527 | C26: MAXICHEMICAL | D26: A - 38018 | E26: 46174 | F26: 46204 | G26: USD | H26: -19375.65 | I26: -3100.1 | J26: -22475.75 | K26: -1295.4 | L26: 1295.4 | M26: Sin pagar | N26: IRLANDA ROJO | P26: =+F26-E26 -> 30 | Q26: =IF(P26>1,"Crédito","Contado") -> Crédito | R26: =DAY(F26) -> 1 | S26: =MONTH(F26) -> 7 | T26: =YEAR(F26) -> 2026 | U26: =DAY(E26) -> 1 | V26: =MONTH(E26) -> 6 | W26: =YEAR(E26) -> 2026 | X26: =+H26*-1 -> 19375.65 | Y26: =+J26*-1 -> 22475.75 | Z26: =IF(F26>AA26,"Vigente","Vencido") -> Vigente | AA26: 46199 | AB26: =MONTH(AA26) -> 6 | AC26: =WEEKNUM(AA26) -> 26 | AD26: =IF(Z26="Vencido",AA26-F26+1,0) -> 0 | AE26: =IF(AD26>0,IF(AD26<31,X26,0),0) -> 0 | AF26: =IF(AD26>30,IF(AD26<61,X26,0),0) -> 0 | AG26: =IF(AD26>60,X26,0) -> 0 | AH26: =IF(Z26="Vigente",X26,0) -> 19375.65
A27: BILL/2026/06/0010 | B27: OC02525 | C27: COMERCIALIZADORA LAFEL DE CULIACAN | D27: F9608 | E27: 46174 | F27: 46204 | G27: MXN | H27: -13200 | I27: -2112 | J27: -15312 | K27: -15312 | L27: 15312 | M27: Sin pagar | N27: IRLANDA ROJO | P27: =+F27-E27 -> 30 | Q27: =IF(P27>1,"Crédito","Contado") -> Crédito | R27: =DAY(F27) -> 1 | S27: =MONTH(F27) -> 7 | T27: =YEAR(F27) -> 2026 | U27: =DAY(E27) -> 1 | V27: =MONTH(E27) -> 6 | W27: =YEAR(E27) -> 2026 | X27: =+H27*-1 -> 13200 | Y27: =+J27*-1 -> 15312 | Z27: =IF(F27>AA27,"Vigente","Vencido") -> Vigente | AA27: 46199 | AB27: =MONTH(AA27) -> 6 | AC27: =WEEKNUM(AA27) -> 26 | AD27: =IF(Z27="Vencido",AA27-F27+1,0) -> 0 | AE27: =IF(AD27>0,IF(AD27<31,X27,0),0) -> 0 | AF27: =IF(AD27>30,IF(AD27<61,X27,0),0) -> 0 | AG27: =IF(AD27>60,X27,0) -> 0 | AH27: =IF(Z27="Vigente",X27,0) -> 13200
A28: BILL/2026/06/0009 | B28: OC02517 | C28: POLAQUIMIA | D28: 225770 | E28: 46174 | F28: 46204 | G28: USD | H28: -112431.24 | I28: -17989 | J28: -130420.24 | K28: -7516.8 | L28: 7516.8 | M28: Sin pagar | N28: IRLANDA ROJO | P28: =+F28-E28 -> 30 | Q28: =IF(P28>1,"Crédito","Contado") -> Crédito | R28: =DAY(F28) -> 1 | S28: =MONTH(F28) -> 7 | T28: =YEAR(F28) -> 2026 | U28: =DAY(E28) -> 1 | V28: =MONTH(E28) -> 6 | W28: =YEAR(E28) -> 2026 | X28: =+H28*-1 -> 112431.24 | Y28: =+J28*-1 -> 130420.24 | Z28: =IF(F28>AA28,"Vigente","Vencido") -> Vigente | AA28: 46199 | AB28: =MONTH(AA28) -> 6 | AC28: =WEEKNUM(AA28) -> 26 | AD28: =IF(Z28="Vencido",AA28-F28+1,0) -> 0 | AE28: =IF(AD28>0,IF(AD28<31,X28,0),0) -> 0 | AF28: =IF(AD28>30,IF(AD28<61,X28,0),0) -> 0 | AG28: =IF(AD28>60,X28,0) -> 0 | AH28: =IF(Z28="Vigente",X28,0) -> 112431.24
A29: BILL/2026/06/0008 | B29: OC02526 | C29: QMX4 | D29: FC86924 | E29: 46175 | F29: 46205 | G29: MXN | H29: -8950 | I29: -1432 | J29: -10382 | K29: -10382 | L29: 10382 | M29: Sin pagar | N29: IRLANDA ROJO | P29: =+F29-E29 -> 30 | Q29: =IF(P29>1,"Crédito","Contado") -> Crédito | R29: =DAY(F29) -> 2 | S29: =MONTH(F29) -> 7 | T29: =YEAR(F29) -> 2026 | U29: =DAY(E29) -> 2 | V29: =MONTH(E29) -> 6 | W29: =YEAR(E29) -> 2026 | X29: =+H29*-1 -> 8950 | Y29: =+J29*-1 -> 10382 | Z29: =IF(F29>AA29,"Vigente","Vencido") -> Vigente | AA29: 46199 | AB29: =MONTH(AA29) -> 6 | AC29: =WEEKNUM(AA29) -> 26 | AD29: =IF(Z29="Vencido",AA29-F29+1,0) -> 0 | AE29: =IF(AD29>0,IF(AD29<31,X29,0),0) -> 0 | AF29: =IF(AD29>30,IF(AD29<61,X29,0),0) -> 0 | AG29: =IF(AD29>60,X29,0) -> 0 | AH29: =IF(Z29="Vigente",X29,0) -> 8950
A30: BILL/2026/05/0095 | B30: OC02547 | C30: WEGOCHEM MEXICANA | D30: 12002931-- | E30: 46167 | F30: 46197 | G30: USD | H30: -42437.19 | I30: -6789.95 | J30: -49227.14 | K30: -2842 | L30: 2842 | M30: Sin pagar | N30: IRLANDA ROJO | P30: =+F30-E30 -> 30 | Q30: =IF(P30>1,"Crédito","Contado") -> Crédito | R30: =DAY(F30) -> 24 | S30: =MONTH(F30) -> 6 | T30: =YEAR(F30) -> 2026 | U30: =DAY(E30) -> 25 | V30: =MONTH(E30) -> 5 | W30: =YEAR(E30) -> 2026 | X30: =+H30*-1 -> 42437.19 | Y30: =+J30*-1 -> 49227.14 | Z30: =IF(F30>AA30,"Vigente","Vencido") -> Vencido | AA30: 46199 | AB30: =MONTH(AA30) -> 6 | AC30: =WEEKNUM(AA30) -> 26 | AD30: =IF(Z30="Vencido",AA30-F30+1,0) -> 3 | AE30: =IF(AD30>0,IF(AD30<31,X30,0),0) -> 42437.19 | AF30: =IF(AD30>30,IF(AD30<61,X30,0),0) -> 0 | AG30: =IF(AD30>60,X30,0) -> 0 | AH30: =IF(Z30="Vigente",X30,0) -> 0
A31: BILL/2026/05/0094 | B31: OC02546 | C31: WEGOCHEM MEXICANA | D31: 12002931- | E31: 46167 | F31: 46197 | G31: USD | H31: -127311.56 | I31: -20369.85 | J31: -147681.41 | K31: -8526 | L31: 8526 | M31: Sin pagar | N31: IRLANDA ROJO | P31: =+F31-E31 -> 30 | Q31: =IF(P31>1,"Crédito","Contado") -> Crédito | R31: =DAY(F31) -> 24 | S31: =MONTH(F31) -> 6 | T31: =YEAR(F31) -> 2026 | U31: =DAY(E31) -> 25 | V31: =MONTH(E31) -> 5 | W31: =YEAR(E31) -> 2026 | X31: =+H31*-1 -> 127311.56 | Y31: =+J31*-1 -> 147681.41 | Z31: =IF(F31>AA31,"Vigente","Vencido") -> Vencido | AA31: 46199 | AB31: =MONTH(AA31) -> 6 | AC31: =WEEKNUM(AA31) -> 26 | AD31: =IF(Z31="Vencido",AA31-F31+1,0) -> 3 | AE31: =IF(AD31>0,IF(AD31<31,X31,0),0) -> 127311.56 | AF31: =IF(AD31>30,IF(AD31<61,X31,0),0) -> 0 | AG31: =IF(AD31>60,X31,0) -> 0 | AH31: =IF(Z31="Vigente",X31,0) -> 0
A32: BILL/2026/05/0093 | B32: OC02496 | C32: WEGOCHEM MEXICANA | D32: 12002931 | E32: 46167 | F32: 46197 | G32: USD | H32: -42437.19 | I32: -6789.95 | J32: -49227.14 | K32: -2842 | L32: 2842 | M32: Sin pagar | N32: IRLANDA ROJO | P32: =+F32-E32 -> 30 | Q32: =IF(P32>1,"Crédito","Contado") -> Crédito | R32: =DAY(F32) -> 24 | S32: =MONTH(F32) -> 6 | T32: =YEAR(F32) -> 2026 | U32: =DAY(E32) -> 25 | V32: =MONTH(E32) -> 5 | W32: =YEAR(E32) -> 2026 | X32: =+H32*-1 -> 42437.19 | Y32: =+J32*-1 -> 49227.14 | Z32: =IF(F32>AA32,"Vigente","Vencido") -> Vencido | AA32: 46199 | AB32: =MONTH(AA32) -> 6 | AC32: =WEEKNUM(AA32) -> 26 | AD32: =IF(Z32="Vencido",AA32-F32+1,0) -> 3 | AE32: =IF(AD32>0,IF(AD32<31,X32,0),0) -> 42437.19 | AF32: =IF(AD32>30,IF(AD32<61,X32,0),0) -> 0 | AG32: =IF(AD32>60,X32,0) -> 0 | AH32: =IF(Z32="Vigente",X32,0) -> 0
A33: BILL/2026/05/0092 | B33: OC02506 | C33: ORBEX CHEMICAL | D33: HMO-24944 | E33: 46168 | F33: 46198 | G33: USD | H33: -19862.8 | I33: -3178.05 | J33: -23040.85 | K33: -1334 | L33: 1334 | M33: Sin pagar | N33: IRLANDA ROJO | P33: =+F33-E33 -> 30 | Q33: =IF(P33>1,"Crédito","Contado") -> Crédito | R33: =DAY(F33) -> 25 | S33: =MONTH(F33) -> 6 | T33: =YEAR(F33) -> 2026 | U33: =DAY(E33) -> 26 | V33: =MONTH(E33) -> 5 | W33: =YEAR(E33) -> 2026 | X33: =+H33*-1 -> 19862.8 | Y33: =+J33*-1 -> 23040.85 | Z33: =IF(F33>AA33,"Vigente","Vencido") -> Vencido | AA33: 46199 | AB33: =MONTH(AA33) -> 6 | AC33: =WEEKNUM(AA33) -> 26 | AD33: =IF(Z33="Vencido",AA33-F33+1,0) -> 2 | AE33: =IF(AD33>0,IF(AD33<31,X33,0),0) -> 19862.8 | AF33: =IF(AD33>30,IF(AD33<61,X33,0),0) -> 0 | AG33: =IF(AD33>60,X33,0) -> 0 | AH33: =IF(Z33="Vigente",X33,0) -> 0
... A35: BILL/2026/05/0089 | B35: OC02471 | C35: KOPRIMO | D35: FV103932 | E35: 46168 | F35: 46198 | G35: USD | H35: -238353.6 | I35: -38136.58 | J35: -276490.18 | K35: -16008 | L35: 16008 | M35: Sin pagar | N35: IRLANDA ROJO | P35: =+F35-E35 -> 30 | Q35: =IF(P35>1,"Crédito","Contado") -> Crédito | R35: =DAY(F35) -> 25 | S35: =MONTH(F35) -> 6 | T35: =YEAR(F35) -> 2026 | U35: =DAY(E35) -> 26 | V35: =MONTH(E35) -> 5 | W35: =YEAR(E35) -> 2026 | X35: =+H35*-1 -> 238353.6 | Y35: =+J35*-1 -> 276490.18 | Z35: =IF(F35>AA35,"Vigente","Vencido") -> Vencido | AA35: 46199 | AB35: =MONTH(AA35) -> 6 | AC35: =WEEKNUM(AA35) -> 26 | AD35: =IF(Z35="Vencido",AA35-F35+1,0) -> 2 | AE35: =IF(AD35>0,IF(AD35<31,X35,0),0) -> 238353.6 | AF35: =IF(AD35>30,IF(AD35<61,X35,0),0) -> 0 | AG35: =IF(AD35>60,X35,0) -> 0 | AH35: =IF(Z35="Vigente",X35,0) -> 0
A36: BILL/2026/05/0080 | B36: OC02512 | C36: MAXICHEMICAL | D36: A - 37973 | E36: 46170 | F36: 46200 | G36: MXN | H36: -83500 | J36: -83500 | K36: -83500 | L36: 83500 | M36: Sin pagar | N36: IRLANDA ROJO | P36: =+F36-E36 -> 30 | Q36: =IF(P36>1,"Crédito","Contado") -> Crédito | R36: =DAY(F36) -> 27 | S36: =MONTH(F36) -> 6 | T36: =YEAR(F36) -> 2026 | U36: =DAY(E36) -> 28 | V36: =MONTH(E36) -> 5 | W36: =YEAR(E36) -> 2026 | X36: =+H36*-1 -> 83500 | Y36: =+J36*-1 -> 83500 | Z36: =IF(F36>AA36,"Vigente","Vencido") -> Vigente | AA36: 46199 | AB36: =MONTH(AA36) -> 6 | AC36: =WEEKNUM(AA36) -> 26 | AD36: =IF(Z36="Vencido",AA36-F36+1,0) -> 0 | AE36: =IF(AD36>0,IF(AD36<31,X36,0),0) -> 0 | AF36: =IF(AD36>30,IF(AD36<61,X36,0),0) -> 0 | AG36: =IF(AD36>60,X36,0) -> 0 | AH36: =IF(Z36="Vigente",X36,0) -> 83500
A37: BILL/2026/05/0078 | B37: OC02501 | C37: COMERCIALIZADORA LAFEL DE CULIACAN | D37: F9575 | E37: 46168 | F37: 46198 | G37: MXN | H37: -13200 | I37: -2112 | J37: -15312 | K37: -15312 | L37: 15312 | M37: Sin pagar | N37: IRLANDA ROJO | P37: =+F37-E37 -> 30 | Q37: =IF(P37>1,"Crédito","Contado") -> Crédito | R37: =DAY(F37) -> 25 | S37: =MONTH(F37) -> 6 | T37: =YEAR(F37) -> 2026 | U37: =DAY(E37) -> 26 | V37: =MONTH(E37) -> 5 | W37: =YEAR(E37) -> 2026 | X37: =+H37*-1 -> 13200 | Y37: =+J37*-1 -> 15312 | Z37: =IF(F37>AA37,"Vigente","Vencido") -> Vencido | AA37: 46199 | AB37: =MONTH(AA37) -> 6 | AC37: =WEEKNUM(AA37) -> 26 | AD37: =IF(Z37="Vencido",AA37-F37+1,0) -> 2 | AE37: =IF(AD37>0,IF(AD37<31,X37,0),0) -> 13200 | AF37: =IF(AD37>30,IF(AD37<61,X37,0),0) -> 0 | AG37: =IF(AD37>60,X37,0) -> 0 | AH37: =IF(Z37="Vigente",X37,0) -> 0
A38: BILL/2026/05/0077 | B38: OC02500 | C38: MAXICHEMICAL | D38: A - 37942 | E38: 46168 | F38: 46198 | G38: MXN | H38: -2200 | I38: -352 | J38: -2552 | K38: -2552 | L38: 2552 | M38: Sin pagar | N38: IRLANDA ROJO | P38: =+F38-E38 -> 30 | Q38: =IF(P38>1,"Crédito","Contado") -> Crédito | R38: =DAY(F38) -> 25 | S38: =MONTH(F38) -> 6 | T38: =YEAR(F38) -> 2026 | U38: =DAY(E38) -> 26 | V38: =MONTH(E38) -> 5 | W38: =YEAR(E38) -> 2026 | X38: =+H38*-1 -> 2200 | Y38: =+J38*-1 -> 2552 | Z38: =IF(F38>AA38,"Vigente","Vencido") -> Vencido | AA38: 46199 | AB38: =MONTH(AA38) -> 6 | AC38: =WEEKNUM(AA38) -> 26 | AD38: =IF(Z38="Vencido",AA38-F38+1,0) -> 2 | AE38: =IF(AD38>0,IF(AD38<31,X38,0),0) -> 2200 | AF38: =IF(AD38>30,IF(AD38<61,X38,0),0) -> 0 | AG38: =IF(AD38>60,X38,0) -> 0 | AH38: =IF(Z38="Vigente",X38,0) -> 0
A39: BILL/2026/05/0072 | B39: OC02455 | C39: ALKEM INDUSTRIAS | D39: M 69507 | E39: 46167 | F39: 46197 | G39: USD | H39: -36894.37 | I39: -5903.1 | J39: -42797.47 | K39: -2470.8 | L39: 2470.8 | M39: Sin pagar | N39: IRLANDA ROJO | P39: =+F39-E39 -> 30 | Q39: =IF(P39>1,"Crédito","Contado") -> Crédito | R39: =DAY(F39) -> 24 | S39: =MONTH(F39) -> 6 | T39: =YEAR(F39) -> 2026 | U39: =DAY(E39) -> 25 | V39: =MONTH(E39) -> 5 | W39: =YEAR(E39) -> 2026 | X39: =+H39*-1 -> 36894.37 | Y39: =+J39*-1 -> 42797.47 | Z39: =IF(F39>AA39,"Vigente","Vencido") -> Vencido | AA39: 46199 | AB39: =MONTH(AA39) -> 6 | AC39: =WEEKNUM(AA39) -> 26 | AD39: =IF(Z39="Vencido",AA39-F39+1,0) -> 3 | AE39: =IF(AD39>0,IF(AD39<31,X39,0),0) -> 36894.37 | AF39: =IF(AD39>30,IF(AD39<61,X39,0),0) -> 0 | AG39: =IF(AD39>60,X39,0) -> 0 | AH39: =IF(Z39="Vigente",X39,0) -> 0
A40: BILL/2026/05/0065 | B40: OC02446 | C40: ALKEM INDUSTRIAS | D40: M 69506 | E40: 46167 | F40: 46197 | G40: USD | H40: -2703.56 | I40: -432.57 | J40: -3136.13 | K40: -180.96 | L40: 180.96 | M40: Sin pagar | N40: IRLANDA ROJO | P40: =+F40-E40 -> 30 | Q40: =IF(P40>1,"Crédito","Contado") -> Crédito | R40: =DAY(F40) -> 24 | S40: =MONTH(F40) -> 6 | T40: =YEAR(F40) -> 2026 | U40: =DAY(E40) -> 25 | V40: =MONTH(E40) -> 5 | W40: =YEAR(E40) -> 2026 | X40: =+H40*-1 -> 2703.56 | Y40: =+J40*-1 -> 3136.13 | Z40: =IF(F40>AA40,"Vigente","Vencido") -> Vencido | AA40: 46199 | AB40: =MONTH(AA40) -> 6 | AC40: =WEEKNUM(AA40) -> 26 | AD40: =IF(Z40="Vencido",AA40-F40+1,0) -> 3 | AE40: =IF(AD40>0,IF(AD40<31,X40,0),0) -> 2703.56 | AF40: =IF(AD40>30,IF(AD40<61,X40,0),0) -> 0 | AG40: =IF(AD40>60,X40,0) -> 0 | AH40: =IF(Z40="Vigente",X40,0) -> 0
A41: BILL/2026/05/0058 | B41: OC02480 | C41: MAXICHEMICAL | D41: A - 37871 | E41: 46161 | F41: 46191 | G41: USD | H41: -99544.27 | I41: -15927.08 | J41: -115471.35 | K41: -6677.42 | L41: 6677.42 | M41: Sin pagar | N41: IRLANDA ROJO | P41: =+F41-E41 -> 30 | Q41: =IF(P41>1,"Crédito","Contado") -> Crédito | R41: =DAY(F41) -> 18 | S41: =MONTH(F41) -> 6 | T41: =YEAR(F41) -> 2026 | U41: =DAY(E41) -> 19 | V41: =MONTH(E41) -> 5 | W41: =YEAR(E41) -> 2026 | X41: =+H41*-1 -> 99544.27 | Y41: =+J41*-1 -> 115471.35 | Z41: =IF(F41>AA41,"Vigente","Vencido") -> Vencido | AA41: 46199 | AB41: =MONTH(AA41) -> 6 | AC41: =WEEKNUM(AA41) -> 26 | AD41: =IF(Z41="Vencido",AA41-F41+1,0) -> 9 | AE41: =IF(AD41>0,IF(AD41<31,X41,0),0) -> 99544.27 | AF41: =IF(AD41>30,IF(AD41<61,X41,0),0) -> 0 | AG41: =IF(AD41>60,X41,0) -> 0 | AH41: =IF(Z41="Vigente",X41,0) -> 0
A42: BILL/2026/05/0057 | B42: OC02458 | C42: NRW CHEMIE MEXICANA | D42: HMO59936 | E42: 46155 | F42: 46185 | G42: USD | H42: -126112.12 | I42: -20177.94 | J42: -146290.06 | K42: -8479.6 | L42: 8479.6 | M42: Sin pagar | N42: IRLANDA ROJO | P42: =+F42-E42 -> 30 | Q42: =IF(P42>1,"Crédito","Contado") -> Crédito | R42: =DAY(F42) -> 12 | S42: =MONTH(F42) -> 6 | T42: =YEAR(F42) -> 2026 | U42: =DAY(E42) -> 13 | V42: =MONTH(E42) -> 5 | W42: =YEAR(E42) -> 2026 | X42: =+H42*-1 -> 126112.12 | Y42: =+J42*-1 -> 146290.06 | Z42: =IF(F42>AA42,"Vigente","Vencido") -> Vencido | AA42: 46199 | AB42: =MONTH(AA42) -> 6 | AC42: =WEEKNUM(AA42) -> 26 | AD42: =IF(Z42="Vencido",AA42-F42+1,0) -> 15 | AE42: =IF(AD42>0,IF(AD42<31,X42,0),0) -> 126112.12 | AF42: =IF(AD42>30,IF(AD42<61,X42,0),0) -> 0 | AG42: =IF(AD42>60,X42,0) -> 0 | AH42: =IF(Z42="Vigente",X42,0) -> 0
A43: BILL/2026/05/0056 | B43: OC02459 | C43: NRW CHEMIE MEXICANA | D43: HMO59937 | E43: 46155 | F43: 46185 | G43: USD | H43: -25222.42 | I43: -4035.59 | J43: -29258.01 | K43: -1695.92 | L43: 1695.92 | M43: Sin pagar | N43: IRLANDA ROJO | P43: =+F43-E43 -> 30 | Q43: =IF(P43>1,"Crédito","Contado") -> Crédito | R43: =DAY(F43) -> 12 | S43: =MONTH(F43) -> 6 | T43: =YEAR(F43) -> 2026 | U43: =DAY(E43) -> 13 | V43: =MONTH(E43) -> 5 | W43: =YEAR(E43) -> 2026 | X43: =+H43*-1 -> 25222.42 | Y43: =+J43*-1 -> 29258.01 | Z43: =IF(F43>AA43,"Vigente","Vencido") -> Vencido | AA43: 46199 | AB43: =MONTH(AA43) -> 6 | AC43: =WEEKNUM(AA43) -> 26 | AD43: =IF(Z43="Vencido",AA43-F43+1,0) -> 15 | AE43: =IF(AD43>0,IF(AD43<31,X43,0),0) -> 25222.42 | AF43: =IF(AD43>30,IF(AD43<61,X43,0),0) -> 0 | AG43: =IF(AD43>60,X43,0) -> 0 | AH43: =IF(Z43="Vigente",X43,0) -> 0
A44: BILL/2026/05/0055 | B44: OC02478 | C44: MAXICHEMICAL | D44: A - 37855 | E44: 46161 | F44: 46191 | G44: MXN | H44: -11000 | I44: -1760 | J44: -12760 | K44: -12760 | L44: 12760 | M44: Sin pagar | N44: IRLANDA ROJO | P44: =+F44-E44 -> 30 | Q44: =IF(P44>1,"Crédito","Contado") -> Crédito | R44: =DAY(F44) -> 18 | S44: =MONTH(F44) -> 6 | T44: =YEAR(F44) -> 2026 | U44: =DAY(E44) -> 19 | V44: =MONTH(E44) -> 5 | W44: =YEAR(E44) -> 2026 | X44: =+H44*-1 -> 11000 | Y44: =+J44*-1 -> 12760 | Z44: =IF(F44>AA44,"Vigente","Vencido") -> Vencido | AA44: 46199 | AB44: =MONTH(AA44) -> 6 | AC44: =WEEKNUM(AA44) -> 26 | AD44: =IF(Z44="Vencido",AA44-F44+1,0) -> 9 | AE44: =IF(AD44>0,IF(AD44<31,X44,0),0) -> 11000 | AF44: =IF(AD44>30,IF(AD44<61,X44,0),0) -> 0 | AG44: =IF(AD44>60,X44,0) -> 0 | AH44: =IF(Z44="Vigente",X44,0) -> 0
A45: BILL/2026/05/0054 | B45: OC02469 | C45: MAXICHEMICAL | D45: A - 37806 | E45: 46157 | F45: 46187 | G45: MXN | H45: -7500 | I45: -1200 | J45: -8700 | K45: -8700 | L45: 8700 | M45: Sin pagar | N45: IRLANDA ROJO | P45: =+F45-E45 -> 30 | Q45: =IF(P45>1,"Crédito","Contado") -> Crédito | R45: =DAY(F45) -> 14 | S45: =MONTH(F45) -> 6 | T45: =YEAR(F45) -> 2026 | U45: =DAY(E45) -> 15 | V45: =MONTH(E45) -> 5 | W45: =YEAR(E45) -> 2026 | X45: =+H45*-1 -> 7500 | Y45: =+J45*-1 -> 8700 | Z45: =IF(F45>AA45,"Vigente","Vencido") -> Vencido | AA45: 46199 | AB45: =MONTH(AA45) -> 6 | AC45: =WEEKNUM(AA45) -> 26 | AD45: =IF(Z45="Vencido",AA45-F45+1,0) -> 13 | AE45: =IF(AD45>0,IF(AD45<31,X45,0),0) -> 7500 | AF45: =IF(AD45>30,IF(AD45<61,X45,0),0) -> 0 | AG45: =IF(AD45>60,X45,0) -> 0 | AH45: =IF(Z45="Vigente",X45,0) -> 0
A46: BILL/2026/05/0053 | B46: OC02483 | C46: COMERCIALIZADORA LAFEL DE CULIACAN | D46: F9547 | E46: 46162 | F46: 46192 | G46: MXN | H46: -4371.72 | I46: -699.48 | J46: -5071.2 | K46: -5071.2 | L46: 5071.2 | M46: Sin pagar | N46: IRLANDA ROJO | P46: =+F46-E46 -> 30 | Q46: =IF(P46>1,"Crédito","Contado") -> Crédito | R46: =DAY(F46) -> 19 | S46: =MONTH(F46) -> 6 | T46: =YEAR(F46) -> 2026 | U46: =DAY(E46) -> 20 | V46: =MONTH(E46) -> 5 | W46: =YEAR(E46) -> 2026 | X46: =+H46*-1 -> 4371.72 | Y46: =+J46*-1 -> 5071.2 | Z46: =IF(F46>AA46,"Vigente","Vencido") -> Vencido | AA46: 46199 | AB46: =MONTH(AA46) -> 6 | AC46: =WEEKNUM(AA46) -> 26 | AD46: =IF(Z46="Vencido",AA46-F46+1,0) -> 8 | AE46: =IF(AD46>0,IF(AD46<31,X46,0),0) -> 4371.72 | AF46: =IF(AD46>30,IF(AD46<61,X46,0),0) -> 0 | AG46: =IF(AD46>60,X46,0) -> 0 | AH46: =IF(Z46="Vigente",X46,0) -> 0
A47: BILL/2026/05/0052 | B47: OC02488 | C47: COMERCIALIZADORA LAFEL DE CULIACAN | D47: F9554 | E47: 46163 | F47: 46193 | G47: MXN | H47: -39594.37 | I47: -6335.1 | J47: -45929.47 | K47: -45929.47 | L47: 45929.47 | M47: Sin pagar | N47: IRLANDA ROJO | P47: =+F47-E47 -> 30 | Q47: =IF(P47>1,"Crédito","Contado") -> Crédito | R47: =DAY(F47) -> 20 | S47: =MONTH(F47) -> 6 | T47: =YEAR(F47) -> 2026 | U47: =DAY(E47) -> 21 | V47: =MONTH(E47) -> 5 | W47: =YEAR(E47) -> 2026 | X47: =+H47*-1 -> 39594.37 | Y47: =+J47*-1 -> 45929.47 | Z47: =IF(F47>AA47,"Vigente","Vencido") -> Vencido | AA47: 46199 | AB47: =MONTH(AA47) -> 6 | AC47: =WEEKNUM(AA47) -> 26 | AD47: =IF(Z47="Vencido",AA47-F47+1,0) -> 7 | AE47: =IF(AD47>0,IF(AD47<31,X47,0),0) -> 39594.37 | AF47: =IF(AD47>30,IF(AD47<61,X47,0),0) -> 0 | AG47: =IF(AD47>60,X47,0) -> 0 | AH47: =IF(Z47="Vigente",X47,0) -> 0
A48: BILL/2026/05/0034 | B48: OC02460 | C48: MAXICHEMICAL | D48: A - 37788 | E48: 46155 | F48: 46185 | G48: MXN | H48: -5000 | I48: -800 | J48: -5800 | K48: -5800 | L48: 5800 | M48: Sin pagar | N48: IRLANDA ROJO | P48: =+F48-E48 -> 30 | Q48: =IF(P48>1,"Crédito","Contado") -> Crédito | R48: =DAY(F48) -> 12 | S48: =MONTH(F48) -> 6 | T48: =YEAR(F48) -> 2026 | U48: =DAY(E48) -> 13 | V48: =MONTH(E48) -> 5 | W48: =YEAR(E48) -> 2026 | X48: =+H48*-1 -> 5000 | Y48: =+J48*-1 -> 5800 | Z48: =IF(F48>AA48,"Vigente","Vencido") -> Vencido | AA48: 46199 | AB48: =MONTH(AA48) -> 6 | AC48: =WEEKNUM(AA48) -> 26 | AD48: =IF(Z48="Vencido",AA48-F48+1,0) -> 15 | AE48: =IF(AD48>0,IF(AD48<31,X48,0),0) -> 5000 | AF48: =IF(AD48>30,IF(AD48<61,X48,0),0) -> 0 | AG48: =IF(AD48>60,X48,0) -> 0 | AH48: =IF(Z48="Vigente",X48,0) -> 0
... A50: BILL/2026/05/0021 | B50: OC02444 | C50: MAXICHEMICAL | D50: A - 37761 | E50: 46153 | F50: 46183 | G50: MXN | H50: -9600 | I50: -1536 | J50: -11136 | K50: -11136 | L50: 11136 | M50: Sin pagar | N50: IRLANDA ROJO | P50: =+F50-E50 -> 30 | Q50: =IF(P50>1,"Crédito","Contado") -> Crédito | R50: =DAY(F50) -> 10 | S50: =MONTH(F50) -> 6 | T50: =YEAR(F50) -> 2026 | U50: =DAY(E50) -> 11 | V50: =MONTH(E50) -> 5 | W50: =YEAR(E50) -> 2026 | X50: =+H50*-1 -> 9600 | Y50: =+J50*-1 -> 11136 | Z50: =IF(F50>AA50,"Vigente","Vencido") -> Vencido | AA50: 46199 | AB50: =MONTH(AA50) -> 6 | AC50: =WEEKNUM(AA50) -> 26 | AD50: =IF(Z50="Vencido",AA50-F50+1,0) -> 17 | AE50: =IF(AD50>0,IF(AD50<31,X50,0),0) -> 9600 | AF50: =IF(AD50>30,IF(AD50<61,X50,0),0) -> 0 | AG50: =IF(AD50>60,X50,0) -> 0 | AH50: =IF(Z50="Vigente",X50,0) -> 0
A51: BILL/2026/05/0020 | B51: OC02435 | C51: MAXICHEMICAL | D51: A - 37710 | E51: 46148 | F51: 46178 | G51: MXN | H51: -3200 | J51: -3200 | K51: -3200 | L51: 3200 | M51: Sin pagar | N51: IRLANDA ROJO | P51: =+F51-E51 -> 30 | Q51: =IF(P51>1,"Crédito","Contado") -> Crédito | R51: =DAY(F51) -> 5 | S51: =MONTH(F51) -> 6 | T51: =YEAR(F51) -> 2026 | U51: =DAY(E51) -> 6 | V51: =MONTH(E51) -> 5 | W51: =YEAR(E51) -> 2026 | X51: =+H51*-1 -> 3200 | Y51: =+J51*-1 -> 3200 | Z51: =IF(F51>AA51,"Vigente","Vencido") -> Vencido | AA51: 46199 | AB51: =MONTH(AA51) -> 6 | AC51: =WEEKNUM(AA51) -> 26 | AD51: =IF(Z51="Vencido",AA51-F51+1,0) -> 22 | AE51: =IF(AD51>0,IF(AD51<31,X51,0),0) -> 3200 | AF51: =IF(AD51>30,IF(AD51<61,X51,0),0) -> 0 | AG51: =IF(AD51>60,X51,0) -> 0 | AH51: =IF(Z51="Vigente",X51,0) -> 0
A52: BILL/2026/05/0019 | B52: OC02441 | C52: MAXICHEMICAL | D52: A - 37735 | E52: 46150 | F52: 46180 | G52: MXN | H52: -16800 | I52: -2688 | J52: -19488 | K52: -19488 | L52: 19488 | M52: Sin pagar | N52: IRLANDA ROJO | P52: =+F52-E52 -> 30 | Q52: =IF(P52>1,"Crédito","Contado") -> Crédito | R52: =DAY(F52) -> 7 | S52: =MONTH(F52) -> 6 | T52: =YEAR(F52) -> 2026 | U52: =DAY(E52) -> 8 | V52: =MONTH(E52) -> 5 | W52: =YEAR(E52) -> 2026 | X52: =+H52*-1 -> 16800 | Y52: =+J52*-1 -> 19488 | Z52: =IF(F52>AA52,"Vigente","Vencido") -> Vencido | AA52: 46199 | AB52: =MONTH(AA52) -> 6 | AC52: =WEEKNUM(AA52) -> 26 | AD52: =IF(Z52="Vencido",AA52-F52+1,0) -> 20 | AE52: =IF(AD52>0,IF(AD52<31,X52,0),0) -> 16800 | AF52: =IF(AD52>30,IF(AD52<61,X52,0),0) -> 0 | AG52: =IF(AD52>60,X52,0) -> 0 | AH52: =IF(Z52="Vigente",X52,0) -> 0
A53: BILL/2026/05/0018 | B53: OC02442 | C53: MAXICHEMICAL | D53: A - 37736 | E53: 46150 | F53: 46180 | G53: MXN | H53: -11600 | I53: -1856 | J53: -13456 | K53: -13456 | L53: 13456 | M53: Sin pagar | N53: IRLANDA ROJO | P53: =+F53-E53 -> 30 | Q53: =IF(P53>1,"Crédito","Contado") -> Crédito | R53: =DAY(F53) -> 7 | S53: =MONTH(F53) -> 6 | T53: =YEAR(F53) -> 2026 | U53: =DAY(E53) -> 8 | V53: =MONTH(E53) -> 5 | W53: =YEAR(E53) -> 2026 | X53: =+H53*-1 -> 11600 | Y53: =+J53*-1 -> 13456 | Z53: =IF(F53>AA53,"Vigente","Vencido") -> Vencido | AA53: 46199 | AB53: =MONTH(AA53) -> 6 | AC53: =WEEKNUM(AA53) -> 26 | AD53: =IF(Z53="Vencido",AA53-F53+1,0) -> 20 | AE53: =IF(AD53>0,IF(AD53<31,X53,0),0) -> 11600 | AF53: =IF(AD53>30,IF(AD53<61,X53,0),0) -> 0 | AG53: =IF(AD53>60,X53,0) -> 0 | AH53: =IF(Z53="Vigente",X53,0) -> 0
A54: BILL/2026/05/0016 | B54: OC02434 | C54: COMERCIALIZADORA LAFEL DE CULIACAN | D54: F9473 | E54: 46148 | F54: 46178 | G54: MXN | H54: -84304 | I54: -13488.64 | J54: -97792.64 | K54: -97792.64 | L54: 97792.64 | M54: Sin pagar | N54: IRLANDA ROJO | P54: =+F54-E54 -> 30 | Q54: =IF(P54>1,"Crédito","Contado") -> Crédito | R54: =DAY(F54) -> 5 | S54: =MONTH(F54) -> 6 | T54: =YEAR(F54) -> 2026 | U54: =DAY(E54) -> 6 | V54: =MONTH(E54) -> 5 | W54: =YEAR(E54) -> 2026 | X54: =+H54*-1 -> 84304 | Y54: =+J54*-1 -> 97792.64 | Z54: =IF(F54>AA54,"Vigente","Vencido") -> Vencido | AA54: 46199 | AB54: =MONTH(AA54) -> 6 | AC54: =WEEKNUM(AA54) -> 26 | AD54: =IF(Z54="Vencido",AA54-F54+1,0) -> 22 | AE54: =IF(AD54>0,IF(AD54<31,X54,0),0) -> 84304 | AF54: =IF(AD54>30,IF(AD54<61,X54,0),0) -> 0 | AG54: =IF(AD54>60,X54,0) -> 0 | AH54: =IF(Z54="Vigente",X54,0) -> 0
A55: BILL/2026/04/0077 | B55: OC02307 | C55: AQUA DUX DE MEXICO | D55: HMO/2026/00002 | E55: 46136 | F55: 46196 | G55: USD | H55: -1084224.4 | I55: -173475.9 | J55: -1257700.3 | K55: -72453.6 | L55: 72453.6 | M55: Sin pagar | N55: IRLANDA ROJO | P55: =+F55-E55 -> 60 | Q55: =IF(P55>1,"Crédito","Contado") -> Crédito | R55: =DAY(F55) -> 23 | S55: =MONTH(F55) -> 6 | T55: =YEAR(F55) -> 2026 | U55: =DAY(E55) -> 24 | V55: =MONTH(E55) -> 4 | W55: =YEAR(E55) -> 2026 | X55: =+H55*-1 -> 1084224.4 | Y55: =+J55*-1 -> 1257700.3 | Z55: =IF(F55>AA55,"Vigente","Vencido") -> Vencido | AA55: 46199 | AB55: =MONTH(AA55) -> 6 | AC55: =WEEKNUM(AA55) -> 26 | AD55: =IF(Z55="Vencido",AA55-F55+1,0) -> 4 | AE55: =IF(AD55>0,IF(AD55<31,X55,0),0) -> 1084224.4 | AF55: =IF(AD55>30,IF(AD55<61,X55,0),0) -> 0 | AG55: =IF(AD55>60,X55,0) -> 0 | AH55: =IF(Z55="Vigente",X55,0) -> 0
A56: BILL/2026/03/0043 | B56: OC02253 | C56: SERVICIOS Y SOLUCIONES ACUICOLAS | D56: CLN/2026/0131 | E56: 46099 | F56: 46129 | G56: MXN | H56: -16250 | J56: -16250 | K56: -16250 | L56: 16250 | M56: Sin pagar | N56: IRLANDA ROJO | P56: =+F56-E56 -> 30 | Q56: =IF(P56>1,"Crédito","Contado") -> Crédito | R56: =DAY(F56) -> 17 | S56: =MONTH(F56) -> 4 | T56: =YEAR(F56) -> 2026 | U56: =DAY(E56) -> 18 | V56: =MONTH(E56) -> 3 | W56: =YEAR(E56) -> 2026 | X56: =+H56*-1 -> 16250 | Y56: =+J56*-1 -> 16250 | Z56: =IF(F56>AA56,"Vigente","Vencido") -> Vencido | AA56: 46199 | AB56: =MONTH(AA56) -> 6 | AC56: =WEEKNUM(AA56) -> 26 | AD56: =IF(Z56="Vencido",AA56-F56+1,0) -> 71 | AE56: =IF(AD56>0,IF(AD56<31,X56,0),0) -> 0 | AF56: =IF(AD56>30,IF(AD56<61,X56,0),0) -> 0 | AG56: =IF(AD56>60,X56,0) -> 16250 | AH56: =IF(Z56="Vigente",X56,0) -> 0
A57: BILL/2026/03/0033 | B57: OC02218 | C57: SERVICIOS Y SOLUCIONES ACUICOLAS | D57: CLN/2026/0110-- | E57: 46088 | F57: 46118 | G57: MXN | H57: -6800 | J57: -6800 | K57: -6800 | L57: 6800 | M57: Sin pagar | N57: IRLANDA ROJO | P57: =+F57-E57 -> 30 | Q57: =IF(P57>1,"Crédito","Contado") -> Crédito | R57: =DAY(F57) -> 6 | S57: =MONTH(F57) -> 4 | T57: =YEAR(F57) -> 2026 | U57: =DAY(E57) -> 7 | V57: =MONTH(E57) -> 3 | W57: =YEAR(E57) -> 2026 | X57: =+H57*-1 -> 6800 | Y57: =+J57*-1 -> 6800 | Z57: =IF(F57>AA57,"Vigente","Vencido") -> Vencido | AA57: 46199 | AB57: =MONTH(AA57) -> 6 | AC57: =WEEKNUM(AA57) -> 26 | AD57: =IF(Z57="Vencido",AA57-F57+1,0) -> 82 | AE57: =IF(AD57>0,IF(AD57<31,X57,0),0) -> 0 | AF57: =IF(AD57>30,IF(AD57<61,X57,0),0) -> 0 | AG57: =IF(AD57>60,X57,0) -> 6800 | AH57: =IF(Z57="Vigente",X57,0) -> 0
A58: BILL/2026/03/0032 | B58: OC02213 | C58: SERVICIOS Y SOLUCIONES ACUICOLAS | D58: CLN/2026/0110- | E58: 46088 | F58: 46118 | G58: MXN | H58: -7500 | J58: -7500 | K58: -7500 | L58: 7500 | M58: Sin pagar | N58: IRLANDA ROJO | P58: =+F58-E58 -> 30 | Q58: =IF(P58>1,"Crédito","Contado") -> Crédito | R58: =DAY(F58) -> 6 | S58: =MONTH(F58) -> 4 | T58: =YEAR(F58) -> 2026 | U58: =DAY(E58) -> 7 | V58: =MONTH(E58) -> 3 | W58: =YEAR(E58) -> 2026 | X58: =+H58*-1 -> 7500 | Y58: =+J58*-1 -> 7500 | Z58: =IF(F58>AA58,"Vigente","Vencido") -> Vencido | AA58: 46199 | AB58: =MONTH(AA58) -> 6 | AC58: =WEEKNUM(AA58) -> 26 | AD58: =IF(Z58="Vencido",AA58-F58+1,0) -> 82 | AE58: =IF(AD58>0,IF(AD58<31,X58,0),0) -> 0 | AF58: =IF(AD58>30,IF(AD58<61,X58,0),0) -> 0 | AG58: =IF(AD58>60,X58,0) -> 7500 | AH58: =IF(Z58="Vigente",X58,0) -> 0
A59: BILL/2026/03/0031 | B59: OC02219 | C59: SERVICIOS Y SOLUCIONES ACUICOLAS | D59: CLN/2026/0110 | E59: 46088 | F59: 46118 | G59: MXN | H59: -15000 | J59: -15000 | K59: -15000 | L59: 15000 | M59: Sin pagar | N59: IRLANDA ROJO | P59: =+F59-E59 -> 30 | Q59: =IF(P59>1,"Crédito","Contado") -> Crédito | R59: =DAY(F59) -> 6 | S59: =MONTH(F59) -> 4 | T59: =YEAR(F59) -> 2026 | U59: =DAY(E59) -> 7 | V59: =MONTH(E59) -> 3 | W59: =YEAR(E59) -> 2026 | X59: =+H59*-1 -> 15000 | Y59: =+J59*-1 -> 15000 | Z59: =IF(F59>AA59,"Vigente","Vencido") -> Vencido | AA59: 46199 | AB59: =MONTH(AA59) -> 6 | AC59: =WEEKNUM(AA59) -> 26 | AD59: =IF(Z59="Vencido",AA59-F59+1,0) -> 82 | AE59: =IF(AD59>0,IF(AD59<31,X59,0),0) -> 0 | AF59: =IF(AD59>30,IF(AD59<61,X59,0),0) -> 0 | AG59: =IF(AD59>60,X59,0) -> 15000 | AH59: =IF(Z59="Vigente",X59,0) -> 0
A60: BILL/2026/03/0010 | B60: OC02209 | C60: DISTRIBUIDORA DE SOSA Y ACIDOS | D60: DSA 242129 | E60: 46087 | F60: 46117 | G60: MXN | H60: -455037.5 | J60: -455037.5 | K60: -455037.5 | L60: 455037.5 | M60: Sin pagar | N60: IRLANDA ROJO | P60: =+F60-E60 -> 30 | Q60: =IF(P60>1,"Crédito","Contado") -> Crédito | R60: =DAY(F60) -> 5 | S60: =MONTH(F60) -> 4 | T60: =YEAR(F60) -> 2026 | U60: =DAY(E60) -> 6 | V60: =MONTH(E60) -> 3 | W60: =YEAR(E60) -> 2026 | X60: =+H60*-1 -> 455037.5 | Y60: =+J60*-1 -> 455037.5 | Z60: =IF(F60>AA60,"Vigente","Vencido") -> Vencido | AA60: 46199 | AB60: =MONTH(AA60) -> 6 | AC60: =WEEKNUM(AA60) -> 26 | AD60: =IF(Z60="Vencido",AA60-F60+1,0) -> 83 | AE60: =IF(AD60>0,IF(AD60<31,X60,0),0) -> 0 | AF60: =IF(AD60>30,IF(AD60<61,X60,0),0) -> 0 | AG60: =IF(AD60>60,X60,0) -> 455037.5 | AH60: =IF(Z60="Vigente",X60,0) -> 0
A61: BILL/2026/03/0006 | B61: OC02198 | C61: SERVICIOS Y SOLUCIONES ACUICOLAS | D61: CLN/2026/0103 | E61: 46085 | F61: 46115 | G61: MXN | H61: -6800 | J61: -6800 | K61: -6800 | L61: 6800 | M61: Sin pagar | N61: IRLANDA ROJO | P61: =+F61-E61 -> 30 | Q61: =IF(P61>1,"Crédito","Contado") -> Crédito | R61: =DAY(F61) -> 3 | S61: =MONTH(F61) -> 4 | T61: =YEAR(F61) -> 2026 | U61: =DAY(E61) -> 4 | V61: =MONTH(E61) -> 3 | W61: =YEAR(E61) -> 2026 | X61: =+H61*-1 -> 6800 | Y61: =+J61*-1 -> 6800 | Z61: =IF(F61>AA61,"Vigente","Vencido") -> Vencido | AA61: 46199 | AB61: =MONTH(AA61) -> 6 | AC61: =WEEKNUM(AA61) -> 26 | AD61: =IF(Z61="Vencido",AA61-F61+1,0) -> 85 | AE61: =IF(AD61>0,IF(AD61<31,X61,0),0) -> 0 | AF61: =IF(AD61>30,IF(AD61<61,X61,0),0) -> 0 | AG61: =IF(AD61>60,X61,0) -> 6800 | AH61: =IF(Z61="Vigente",X61,0) -> 0
A62: BILL/2025/10/0003 | B62: OC01792 | C62: HENKO DISTRIBUCION QUIMICA | D62: 4074 | E62: 45932 | F62: 45962 | G62: MXN | H62: -14985 | I62: -2397.6 | J62: -17382.6 | K62: -17382.6 | L62: 17382.6 | M62: Sin pagar | N62: IRLANDA ROJO | P62: =+F62-E62 -> 30 | Q62: =IF(P62>1,"Crédito","Contado") -> Crédito | R62: =DAY(F62) -> 1 | S62: =MONTH(F62) -> 11 | T62: =YEAR(F62) -> 2025 | U62: =DAY(E62) -> 2 | V62: =MONTH(E62) -> 10 | W62: =YEAR(E62) -> 2025 | X62: =+H62*-1 -> 14985 | Y62: =+J62*-1 -> 17382.6 | Z62: =IF(F62>AA62,"Vigente","Vencido") -> Vencido | AA62: 46199 | AB62: =MONTH(AA62) -> 6 | AC62: =WEEKNUM(AA62) -> 26 | AD62: =IF(Z62="Vencido",AA62-F62+1,0) -> 238 | AE62: =IF(AD62>0,IF(AD62<31,X62,0),0) -> 0 | AF62: =IF(AD62>30,IF(AD62<61,X62,0),0) -> 0 | AG62: =IF(AD62>60,X62,0) -> 14985 | AH62: =IF(Z62="Vigente",X62,0) -> 0
A63: BILL/2025/09/0116 | B63: OC01773 | C63: HENKO DISTRIBUCION QUIMICA | D63: 3998 | E63: 45927 | F63: 45957 | G63: MXN | H63: -7600 | I63: -1216 | J63: -8816 | K63: -8816 | L63: 8816 | M63: Sin pagar | N63: IRLANDA ROJO | P63: =+F63-E63 -> 30 | Q63: =IF(P63>1,"Crédito","Contado") -> Crédito | R63: =DAY(F63) -> 27 | S63: =MONTH(F63) -> 10 | T63: =YEAR(F63) -> 2025 | U63: =DAY(E63) -> 27 | V63: =MONTH(E63) -> 9 | W63: =YEAR(E63) -> 2025 | X63: =+H63*-1 -> 7600 | Y63: =+J63*-1 -> 8816 | Z63: =IF(F63>AA63,"Vigente","Vencido") -> Vencido | AA63: 46199 | AB63: =MONTH(AA63) -> 6 | AC63: =WEEKNUM(AA63) -> 26 | AD63: =IF(Z63="Vencido",AA63-F63+1,0) -> 243 | AE63: =IF(AD63>0,IF(AD63<31,X63,0),0) -> 0 | AF63: =IF(AD63>30,IF(AD63<61,X63,0),0) -> 0 | AG63: =IF(AD63>60,X63,0) -> 7600 | AH63: =IF(Z63="Vigente",X63,0) -> 0
A64: BILL/2025/09/0092 | B64: OC01742 | C64: SERVICIOS Y SOLUCIONES ACUICOLAS | D64: CLN/2025/0086 | E64: 45924 | F64: 45954 | G64: MXN | H64: -2499.98 | J64: -2499.98 | K64: -2499.98 | L64: 2499.98 | M64: Sin pagar | N64: IRLANDA ROJO | P64: =+F64-E64 -> 30 | Q64: =IF(P64>1,"Crédito","Contado") -> Crédito | R64: =DAY(F64) -> 24 | S64: =MONTH(F64) -> 10 | T64: =YEAR(F64) -> 2025 | U64: =DAY(E64) -> 24 | V64: =MONTH(E64) -> 9 | W64: =YEAR(E64) -> 2025 | X64: =+H64*-1 -> 2499.98 | Y64: =+J64*-1 -> 2499.98 | Z64: =IF(F64>AA64,"Vigente","Vencido") -> Vencido | AA64: 46199 | AB64: =MONTH(AA64) -> 6 | AC64: =WEEKNUM(AA64) -> 26 | AD64: =IF(Z64="Vencido",AA64-F64+1,0) -> 246 | AE64: =IF(AD64>0,IF(AD64<31,X64,0),0) -> 0 | AF64: =IF(AD64>30,IF(AD64<61,X64,0),0) -> 0 | AG64: =IF(AD64>60,X64,0) -> 2499.98 | AH64: =IF(Z64="Vigente",X64,0) -> 0
A65: BILL/2025/09/0065 | B65: OC01751 | C65: HENKO DISTRIBUCION QUIMICA | D65: 3957 | E65: 45923 | F65: 45953 | G65: USD | H65: -23857.03 | I65: -3817.12 | J65: -27674.15 | K65: -1503.36 | L65: 1503.36 | M65: Sin pagar | N65: IRLANDA ROJO | P65: =+F65-E65 -> 30 | Q65: =IF(P65>1,"Crédito","Contado") -> Crédito | R65: =DAY(F65) -> 23 | S65: =MONTH(F65) -> 10 | T65: =YEAR(F65) -> 2025 | U65: =DAY(E65) -> 23 | V65: =MONTH(E65) -> 9 | W65: =YEAR(E65) -> 2025 | X65: =+H65*-1 -> 23857.03 | Y65: =+J65*-1 -> 27674.15 | Z65: =IF(F65>AA65,"Vigente","Vencido") -> Vencido | AA65: 46199 | AB65: =MONTH(AA65) -> 6 | AC65: =WEEKNUM(AA65) -> 26 | AD65: =IF(Z65="Vencido",AA65-F65+1,0) -> 247 | AE65: =IF(AD65>0,IF(AD65<31,X65,0),0) -> 0 | AF65: =IF(AD65>30,IF(AD65<61,X65,0),0) -> 0 | AG65: =IF(AD65>60,X65,0) -> 23857.03 | AH65: =IF(Z65="Vigente",X65,0) -> 0
A66: BILL/2025/09/0031 | B66: OC01684 | C66: HENKO DISTRIBUCION QUIMICA | D66: 3858 | E66: 45905 | F66: 45935 | G66: USD | H66: -7240.47 | I66: -1158.48 | J66: -8398.95 | K66: -447.76 | L66: 447.76 | M66: Sin pagar | N66: IRLANDA ROJO | P66: =+F66-E66 -> 30 | Q66: =IF(P66>1,"Crédito","Contado") -> Crédito | R66: =DAY(F66) -> 5 | S66: =MONTH(F66) -> 10 | T66: =YEAR(F66) -> 2025 | U66: =DAY(E66) -> 5 | V66: =MONTH(E66) -> 9 | W66: =YEAR(E66) -> 2025 | X66: =+H66*-1 -> 7240.47 | Y66: =+J66*-1 -> 8398.95 | Z66: =IF(F66>AA66,"Vigente","Vencido") -> Vencido | AA66: 46199 | AB66: =MONTH(AA66) -> 6 | AC66: =WEEKNUM(AA66) -> 26 | AD66: =IF(Z66="Vencido",AA66-F66+1,0) -> 265 | AE66: =IF(AD66>0,IF(AD66<31,X66,0),0) -> 0 | AF66: =IF(AD66>30,IF(AD66<61,X66,0),0) -> 0 | AG66: =IF(AD66>60,X66,0) -> 7240.47 | AH66: =IF(Z66="Vigente",X66,0) -> 0
A67: BILL/2025/09/0030 | B67: OC01684 | C67: HENKO DISTRIBUCION QUIMICA | D67: 3851 | E67: 45904 | F67: 45934 | G67: USD | H67: -21639.89 | I67: -3462.38 | J67: -25102.27 | K67: -1343.28 | L67: 1343.28 | M67: Sin pagar | N67: IRLANDA ROJO | P67: =+F67-E67 -> 30 | Q67: =IF(P67>1,"Crédito","Contado") -> Crédito | R67: =DAY(F67) -> 4 | S67: =MONTH(F67) -> 10 | T67: =YEAR(F67) -> 2025 | U67: =DAY(E67) -> 4 | V67: =MONTH(E67) -> 9 | W67: =YEAR(E67) -> 2025 | X67: =+H67*-1 -> 21639.89 | Y67: =+J67*-1 -> 25102.27 | Z67: =IF(F67>AA67,"Vigente","Vencido") -> Vencido | AA67: 46199 | AB67: =MONTH(AA67) -> 6 | AC67: =WEEKNUM(AA67) -> 26 | AD67: =IF(Z67="Vencido",AA67-F67+1,0) -> 266 | AE67: =IF(AD67>0,IF(AD67<31,X67,0),0) -> 0 | AF67: =IF(AD67>30,IF(AD67<61,X67,0),0) -> 0 | AG67: =IF(AD67>60,X67,0) -> 21639.89 | AH67: =IF(Z67="Vigente",X67,0) -> 0
A68: BILL/2025/09/0021 | B68: OC01696 | C68: SERVICIOS Y SOLUCIONES ACUICOLAS | D68: CLN/2025/0066 | E68: 45909 | F68: 45939 | G68: MXN | H68: -5000 | J68: -5000 | K68: -5000 | L68: 5000 | M68: Sin pagar | N68: IRLANDA ROJO | P68: =+F68-E68 -> 30 | Q68: =IF(P68>1,"Crédito","Contado") -> Crédito | R68: =DAY(F68) -> 9 | S68: =MONTH(F68) -> 10 | T68: =YEAR(F68) -> 2025 | U68: =DAY(E68) -> 9 | V68: =MONTH(E68) -> 9 | W68: =YEAR(E68) -> 2025 | X68: =+H68*-1 -> 5000 | Y68: =+J68*-1 -> 5000 | Z68: =IF(F68>AA68,"Vigente","Vencido") -> Vencido | AA68: 46199 | AB68: =MONTH(AA68) -> 6 | AC68: =WEEKNUM(AA68) -> 26 | AD68: =IF(Z68="Vencido",AA68-F68+1,0) -> 261 | AE68: =IF(AD68>0,IF(AD68<31,X68,0),0) -> 0 | AF68: =IF(AD68>30,IF(AD68<61,X68,0),0) -> 0 | AG68: =IF(AD68>60,X68,0) -> 5000 | AH68: =IF(Z68="Vigente",X68,0) -> 0
A69: BILL/2025/09/0008 | B69: OC01683 | C69: HENKO DISTRIBUCION QUIMICA | D69: 3844 | E69: 45903 | F69: 45933 | G69: USD | H69: -24244.53 | I69: -3879.12 | J69: -28123.65 | K69: -1503.36 | L69: 1503.36 | M69: Sin pagar | N69: IRLANDA ROJO | P69: =+F69-E69 -> 30 | Q69: =IF(P69>1,"Crédito","Contado") -> Crédito | R69: =DAY(F69) -> 3 | S69: =MONTH(F69) -> 10 | T69: =YEAR(F69) -> 2025 | U69: =DAY(E69) -> 3 | V69: =MONTH(E69) -> 9 | W69: =YEAR(E69) -> 2025 | X69: =+H69*-1 -> 24244.53 | Y69: =+J69*-1 -> 28123.65 | Z69: =IF(F69>AA69,"Vigente","Vencido") -> Vencido | AA69: 46199 | AB69: =MONTH(AA69) -> 6 | AC69: =WEEKNUM(AA69) -> 26 | AD69: =IF(Z69="Vencido",AA69-F69+1,0) -> 267 | AE69: =IF(AD69>0,IF(AD69<31,X69,0),0) -> 0 | AF69: =IF(AD69>30,IF(AD69<61,X69,0),0) -> 0 | AG69: =IF(AD69>60,X69,0) -> 24244.53 | AH69: =IF(Z69="Vigente",X69,0) -> 0
A70: BILL/2025/08/0063 | B70: OC01631 | C70: HENKO DISTRIBUCION QUIMICA | D70: 3756 | E70: 45888 | F70: 45918 | G70: MXN | H70: -12600 | I70: -2016 | J70: -14616 | K70: -14616 | L70: 14616 | M70: Sin pagar | N70: IRLANDA ROJO | P70: =+F70-E70 -> 30 | Q70: =IF(P70>1,"Crédito","Contado") -> Crédito | R70: =DAY(F70) -> 18 | S70: =MONTH(F70) -> 9 | T70: =YEAR(F70) -> 2025 | U70: =DAY(E70) -> 19 | V70: =MONTH(E70) -> 8 | W70: =YEAR(E70) -> 2025 | X70: =+H70*-1 -> 12600 | Y70: =+J70*-1 -> 14616 | Z70: =IF(F70>AA70,"Vigente","Vencido") -> Vencido | AA70: 46199 | AB70: =MONTH(AA70) -> 6 | AC70: =WEEKNUM(AA70) -> 26 | AD70: =IF(Z70="Vencido",AA70-F70+1,0) -> 282 | AE70: =IF(AD70>0,IF(AD70<31,X70,0),0) -> 0 | AF70: =IF(AD70>30,IF(AD70<61,X70,0),0) -> 0 | AG70: =IF(AD70>60,X70,0) -> 12600 | AH70: =IF(Z70="Vigente",X70,0) -> 0
A71: BILL/2025/08/0062 | B71: OC01632 | C71: HENKO DISTRIBUCION QUIMICA | D71: 3757 | E71: 45888 | F71: 45918 | G71: MXN | H71: -21000 | I71: -3360 | J71: -24360 | K71: -24360 | L71: 24360 | M71: Sin pagar | N71: IRLANDA ROJO | P71: =+F71-E71 -> 30 | Q71: =IF(P71>1,"Crédito","Contado") -> Crédito | R71: =DAY(F71) -> 18 | S71: =MONTH(F71) -> 9 | T71: =YEAR(F71) -> 2025 | U71: =DAY(E71) -> 19 | V71: =MONTH(E71) -> 8 | W71: =YEAR(E71) -> 2025 | X71: =+H71*-1 -> 21000 | Y71: =+J71*-1 -> 24360 | Z71: =IF(F71>AA71,"Vigente","Vencido") -> Vencido | AA71: 46199 | AB71: =MONTH(AA71) -> 6 | AC71: =WEEKNUM(AA71) -> 26 | AD71: =IF(Z71="Vencido",AA71-F71+1,0) -> 282 | AE71: =IF(AD71>0,IF(AD71<31,X71,0),0) -> 0 | AF71: =IF(AD71>30,IF(AD71<61,X71,0),0) -> 0 | AG71: =IF(AD71>60,X71,0) -> 21000 | AH71: =IF(Z71="Vigente",X71,0) -> 0
A72: BILL/2025/08/0040 | B72: OC01600 | C72: HENKO DISTRIBUCION QUIMICA | D72: 3703 | E72: 45881 | F72: 45911 | G72: MXN | H72: -7600 | I72: -1216 | J72: -8816 | K72: -8816 | L72: 8816 | M72: Sin pagar | N72: IRLANDA ROJO | P72: =+F72-E72 -> 30 | Q72: =IF(P72>1,"Crédito","Contado") -> Crédito | R72: =DAY(F72) -> 11 | S72: =MONTH(F72) -> 9 | T72: =YEAR(F72) -> 2025 | U72: =DAY(E72) -> 12 | V72: =MONTH(E72) -> 8 | W72: =YEAR(E72) -> 2025 | X72: =+H72*-1 -> 7600 | Y72: =+J72*-1 -> 8816 | Z72: =IF(F72>AA72,"Vigente","Vencido") -> Vencido | AA72: 46199 | AB72: =MONTH(AA72) -> 6 | AC72: =WEEKNUM(AA72) -> 26 | AD72: =IF(Z72="Vencido",AA72-F72+1,0) -> 289 | AE72: =IF(AD72>0,IF(AD72<31,X72,0),0) -> 0 | AF72: =IF(AD72>30,IF(AD72<61,X72,0),0) -> 0 | AG72: =IF(AD72>60,X72,0) -> 7600 | AH72: =IF(Z72="Vigente",X72,0) -> 0
A73: BILL/2025/08/0036 | B73: OC01615 | C73: HENKO DISTRIBUCION QUIMICA | D73: 3725 | E73: 45883 | F73: 45913 | G73: USD | H73: -7416.85 | I73: -1186.7 | J73: -8603.55 | K73: -461.68 | L73: 461.68 | M73: Sin pagar | N73: IRLANDA ROJO | P73: =+F73-E73 -> 30 | Q73: =IF(P73>1,"Crédito","Contado") -> Crédito | R73: =DAY(F73) -> 13 | S73: =MONTH(F73) -> 9 | T73: =YEAR(F73) -> 2025 | U73: =DAY(E73) -> 14 | V73: =MONTH(E73) -> 8 | W73: =YEAR(E73) -> 2025 | X73: =+H73*-1 -> 7416.85 | Y73: =+J73*-1 -> 8603.55 | Z73: =IF(F73>AA73,"Vigente","Vencido") -> Vencido | AA73: 46199 | AB73: =MONTH(AA73) -> 6 | AC73: =WEEKNUM(AA73) -> 26 | AD73: =IF(Z73="Vencido",AA73-F73+1,0) -> 287 | AE73: =IF(AD73>0,IF(AD73<31,X73,0),0) -> 0 | AF73: =IF(AD73>30,IF(AD73<61,X73,0),0) -> 0 | AG73: =IF(AD73>60,X73,0) -> 7416.85 | AH73: =IF(Z73="Vigente",X73,0) -> 0
A74: BILL/2025/08/0026 | B74: OC01591 | C74: JESUS FRANCISCO OLMOS CASTRO | D74: A 787 | E74: 45882 | F74: 45912 | G74: MXN | H74: -12540 | I74: -1849.65 | J74: -14389.65 | K74: -14389.65 | L74: 14389.65 | M74: Sin pagar | N74: IRLANDA ROJO | P74: =+F74-E74 -> 30 | Q74: =IF(P74>1,"Crédito","Contado") -> Crédito | R74: =DAY(F74) -> 12 | S74: =MONTH(F74) -> 9 | T74: =YEAR(F74) -> 2025 | U74: =DAY(E74) -> 13 | V74: =MONTH(E74) -> 8 | W74: =YEAR(E74) -> 2025 | X74: =+H74*-1 -> 12540 | Y74: =+J74*-1 -> 14389.65 | Z74: =IF(F74>AA74,"Vigente","Vencido") -> Vencido | AA74: 46199 | AB74: =MONTH(AA74) -> 6 | AC74: =WEEKNUM(AA74) -> 26 | AD74: =IF(Z74="Vencido",AA74-F74+1,0) -> 288 | AE74: =IF(AD74>0,IF(AD74<31,X74,0),0) -> 0 | AF74: =IF(AD74>30,IF(AD74<61,X74,0),0) -> 0 | AG74: =IF(AD74>60,X74,0) -> 12540 | AH74: =IF(Z74="Vigente",X74,0) -> 0
A75: BILL/2025/07/0040 | B75: OC01491 | C75: RITA MARIA OLGUIN SERRANO | D75: CLN-362 | E75: 45853 | F75: 45883 | G75: MXN | H75: -12151.9 | I75: 151.9 | J75: -12000 | K75: -12000 | L75: 12000 | M75: Sin pagar | N75: IRLANDA ROJO | P75: =+F75-E75 -> 30 | Q75: =IF(P75>1,"Crédito","Contado") -> Crédito | R75: =DAY(F75) -> 14 | S75: =MONTH(F75) -> 8 | T75: =YEAR(F75) -> 2025 | U75: =DAY(E75) -> 15 | V75: =MONTH(E75) -> 7 | W75: =YEAR(E75) -> 2025 | X75: =+H75*-1 -> 12151.9 | Y75: =+J75*-1 -> 12000 | Z75: =IF(F75>AA75,"Vigente","Vencido") -> Vencido | AA75: 46199 | AB75: =MONTH(AA75) -> 6 | AC75: =WEEKNUM(AA75) -> 26 | AD75: =IF(Z75="Vencido",AA75-F75+1,0) -> 317 | AE75: =IF(AD75>0,IF(AD75<31,X75,0),0) -> 0 | AF75: =IF(AD75>30,IF(AD75<61,X75,0),0) -> 0 | AG75: =IF(AD75>60,X75,0) -> 12151.9 | AH75: =IF(Z75="Vigente",X75,0) -> 0
A76: BILL/2025/06/0041 | B76: OC01416 | C76: RITA MARIA OLGUIN SERRANO | D76: 9AE6E535-1E51-478E-9B2A-58D915BF45ED | E76: 45835 | F76: 45865 | G76: USD | H76: -17003.52 | I76: -2720.56 | J76: -19724.08 | K76: -1044 | L76: 1044 | M76: Sin pagar | N76: IRLANDA ROJO | P76: =+F76-E76 -> 30 | Q76: =IF(P76>1,"Crédito","Contado") -> Crédito | R76: =DAY(F76) -> 27 | S76: =MONTH(F76) -> 7 | T76: =YEAR(F76) -> 2025 | U76: =DAY(E76) -> 27 | V76: =MONTH(E76) -> 6 | W76: =YEAR(E76) -> 2025 | X76: =+H76*-1 -> 17003.52 | Y76: =+J76*-1 -> 19724.08 | Z76: =IF(F76>AA76,"Vigente","Vencido") -> Vencido | AA76: 46199 | AB76: =MONTH(AA76) -> 6 | AC76: =WEEKNUM(AA76) -> 26 | AD76: =IF(Z76="Vencido",AA76-F76+1,0) -> 335 | AE76: =IF(AD76>0,IF(AD76<31,X76,0),0) -> 0 | AF76: =IF(AD76>30,IF(AD76<61,X76,0),0) -> 0 | AG76: =IF(AD76>60,X76,0) -> 17003.52 | AH76: =IF(Z76="Vigente",X76,0) -> 0
A77: BILL/2024/12/0015 | B77: OC00791 | C77: QUIMLOGIC | D77: A - 994 | E77: 45635 | F77: 45650 | G77: USD | H77: -48546 | I77: -7767.36 | J77: -56313.36 | K77: -2784 | L77: 2784 | M77: Sin pagar | N77: IRLANDA ROJO | P77: =+F77-E77 -> 15 | Q77: =IF(P77>1,"Crédito","Contado") -> Crédito | R77: =DAY(F77) -> 24 | S77: =MONTH(F77) -> 12 | T77: =YEAR(F77) -> 2024 | U77: =DAY(E77) -> 9 | V77: =MONTH(E77) -> 12 | W77: =YEAR(E77) -> 2024 | X77: =+H77*-1 -> 48546 | Y77: =+J77*-1 -> 56313.36 | Z77: =IF(F77>AA77,"Vigente","Vencido") -> Vencido | AA77: 46199 | AB77: =MONTH(AA77) -> 6 | AC77: =WEEKNUM(AA77) -> 26 | AD77: =IF(Z77="Vencido",AA77-F77+1,0) -> 550 | AE77: =IF(AD77>0,IF(AD77<31,X77,0),0) -> 0 | AF77: =IF(AD77>30,IF(AD77<61,X77,0),0) -> 0 | AG77: =IF(AD77>60,X77,0) -> 48546 | AH77: =IF(Z77="Vigente",X77,0) -> 0
A78: BILL/2024/11/0007 | B78: OC00687 | C78: INHERQUIM | D78: A6782 | E78: 45597 | F78: 45627 | G78: USD | H78: -64633.93 | I78: -10341.51 | J78: -74975.44 | K78: -3741.7 | L78: 3741.7 | M78: Sin pagar | N78: IRLANDA ROJO | P78: =+F78-E78 -> 30 | Q78: =IF(P78>1,"Crédito","Contado") -> Crédito | R78: =DAY(F78) -> 1 | S78: =MONTH(F78) -> 12 | T78: =YEAR(F78) -> 2024 | U78: =DAY(E78) -> 1 | V78: =MONTH(E78) -> 11 | W78: =YEAR(E78) -> 2024 | X78: =+H78*-1 -> 64633.93 | Y78: =+J78*-1 -> 74975.44 | Z78: =IF(F78>AA78,"Vigente","Vencido") -> Vencido | AA78: 46199 | AB78: =MONTH(AA78) -> 6 | AC78: =WEEKNUM(AA78) -> 26 | AD78: =IF(Z78="Vencido",AA78-F78+1,0) -> 573 | AE78: =IF(AD78>0,IF(AD78<31,X78,0),0) -> 0 | AF78: =IF(AD78>30,IF(AD78<61,X78,0),0) -> 0 | AG78: =IF(AD78>60,X78,0) -> 64633.93 | AH78: =IF(Z78="Vigente",X78,0) -> 0
A79: BILL/2026/06/0054 | B79: OC02572 | C79: WEGOCHEM MEXICANA | D79: 12003081- | E79: 46185 | F79: 46215 | G79: USD | H79: -44327.42 | I79: -7092.39 | J79: -51419.81 | K79: -2958 | L79: 2958 | M79: Sin pagar | N79: IRLANDA ROJO | P79: =+F79-E79 -> 30 | Q79: =IF(P79>1,"Crédito","Contado") -> Crédito | R79: =DAY(F79) -> 12 | S79: =MONTH(F79) -> 7 | T79: =YEAR(F79) -> 2026 | U79: =DAY(E79) -> 12 | V79: =MONTH(E79) -> 6 | W79: =YEAR(E79) -> 2026 | X79: =+H79*-1 -> 44327.42 | Y79: =+J79*-1 -> 51419.81 | Z79: =IF(F79>AA79,"Vigente","Vencido") -> Vigente | AA79: 46192 | AB79: =MONTH(AA79) -> 6 | AC79: =WEEKNUM(AA79) -> 25 | AD79: =IF(Z79="Vencido",AA79-F79+1,0) -> 0 | AE79: =IF(AD79>0,IF(AD79<31,X79,0),0) -> 0 | AF79: =IF(AD79>30,IF(AD79<61,X79,0),0) -> 0 | AG79: =IF(AD79>60,X79,0) -> 0 | AH79: =IF(Z79="Vigente",X79,0) -> 44327.42
A80: BILL/2026/06/0053 | B80: OC02563 | C80: WEGOCHEM MEXICANA | D80: 12003081 | E80: 46185 | F80: 46215 | G80: USD | H80: -132982.25 | I80: -21277.16 | J80: -154259.41 | K80: -8874 | L80: 8874 | M80: Sin pagar | N80: IRLANDA ROJO | P80: =+F80-E80 -> 30 | Q80: =IF(P80>1,"Crédito","Contado") -> Crédito | R80: =DAY(F80) -> 12 | S80: =MONTH(F80) -> 7 | T80: =YEAR(F80) -> 2026 | U80: =DAY(E80) -> 12 | V80: =MONTH(E80) -> 6 | W80: =YEAR(E80) -> 2026 | X80: =+H80*-1 -> 132982.25 | Y80: =+J80*-1 -> 154259.41 | Z80: =IF(F80>AA80,"Vigente","Vencido") -> Vigente | AA80: 46192 | AB80: =MONTH(AA80) -> 6 | AC80: =WEEKNUM(AA80) -> 25 | AD80: =IF(Z80="Vencido",AA80-F80+1,0) -> 0 | AE80: =IF(AD80>0,IF(AD80<31,X80,0),0) -> 0 | AF80: =IF(AD80>30,IF(AD80<61,X80,0),0) -> 0 | AG80: =IF(AD80>60,X80,0) -> 0 | AH80: =IF(Z80="Vigente",X80,0) -> 132982.25
... A95: BILL/2026/06/0034 | B95: OC02560 | C95: COMERCIALIZADORA LAFEL DE CULIACAN | D95: F9667 | E95: 46184 | F95: 46214 | G95: MXN | H95: -11110 | I95: -1777.6 | J95: -12887.6 | K95: -12887.6 | L95: 12887.6 | M95: Sin pagar | N95: IRLANDA ROJO | P95: =+F95-E95 -> 30 | Q95: =IF(P95>1,"Crédito","Contado") -> Crédito | R95: =DAY(F95) -> 11 | S95: =MONTH(F95) -> 7 | T95: =YEAR(F95) -> 2026 | U95: =DAY(E95) -> 11 | V95: =MONTH(E95) -> 6 | W95: =YEAR(E95) -> 2026 | X95: =+H95*-1 -> 11110 | Y95: =+J95*-1 -> 12887.6 | Z95: =IF(F95>AA95,"Vigente","Vencido") -> Vigente | AA95: 46192 | AB95: =MONTH(AA95) -> 6 | AC95: =WEEKNUM(AA95) -> 25 | AD95: =IF(Z95="Vencido",AA95-F95+1,0) -> 0 | AE95: =IF(AD95>0,IF(AD95<31,X95,0),0) -> 0 | AF95: =IF(AD95>30,IF(AD95<61,X95,0),0) -> 0 | AG95: =IF(AD95>60,X95,0) -> 0 | AH95: =IF(Z95="Vigente",X95,0) -> 11110
A96: BILL/2026/06/0033 | B96: OC02545 | C96: NATRIUM DE MEXICO | D96: 398 | E96: 46184 | F96: 46214 | G96: USD | H96: -105903.88 | J96: -105903.88 | K96: -6090 | L96: 6090 | M96: Sin pagar | N96: IRLANDA ROJO | P96: =+F96-E96 -> 30 | Q96: =IF(P96>1,"Crédito","Contado") -> Crédito | R96: =DAY(F96) -> 11 | S96: =MONTH(F96) -> 7 | T96: =YEAR(F96) -> 2026 | U96: =DAY(E96) -> 11 | V96: =MONTH(E96) -> 6 | W96: =YEAR(E96) -> 2026 | X96: =+H96*-1 -> 105903.88 | Y96: =+J96*-1 -> 105903.88 | Z96: =IF(F96>AA96,"Vigente","Vencido") -> Vigente | AA96: 46192 | AB96: =MONTH(AA96) -> 6 | AC96: =WEEKNUM(AA96) -> 25 | AD96: =IF(Z96="Vencido",AA96-F96+1,0) -> 0 | AE96: =IF(AD96>0,IF(AD96<31,X96,0),0) -> 0 | AF96: =IF(AD96>30,IF(AD96<61,X96,0),0) -> 0 | AG96: =IF(AD96>60,X96,0) -> 0 | AH96: =IF(Z96="Vigente",X96,0) -> 105903.88
